Workbook

Sheet About
A1: NexLearn Economic Balance Study — Batch 9
A2: How the numbers were produced and how to reproduce them
A4: Provenance
A5: Engine | B5: NexLearn V2 frozen economic engine (src/simulation). Diff against baseline commit 003f697: none
A6: Valuation model | B6: NXLN-VAL-1.0 (src/production/v2/insights/valuation.ts) — production implementation
A7: Executive scoring | B7: NXLN-EXEC-1.1 (src/production/v2/insights/executive.ts) — production implementation
A8: Terminal score | B8: scoreV2Company (src/simulation/engineV2Scoring.ts)
A9: Runner | B9: scripts/lab/batch9/runner.ts → Test Lab runArc (full eight-quarter arc: market path, Q4 commitment, Q5 contract, Q6 recession, Q7 crisis, Q8 final option, CFO liquidity forecast and financing)
A10: Repository commit | B10: 2d49f89
A11: Generated | B11: 2026-10-13T08:23:42.000Z
A12: Reproduce | B12: LAB_WRITE=1 npx vitest run scripts/lab/batch9/write.test.ts → docs/batch9/lab-results.json; python3 scripts/lab/batch9/build_workbook.py
A13: Verification | B13: npx vitest run scripts/lab/batch9/lab.test.ts — engine unchanged; lab results equal the production replay path (price, executive, terminal, cash) for all ten strategies; ledgers reconcile; overrides restored; re-based mixes are steady states
A15: Assumptions that apply to every run
A16: • All money in $M. Quarter 1 = Q1 2023; Q8 = Q4 2024. Starting company: revenue $200M (Consumer $140M, Enterprise $40M, University $16M, AI-native $4M), operating profit $30M, cash $60M.
A17: • Allocations are $30M per quarter (the strategic envelope); any unallocated amount is held as Cash Reserve. At Q8 the earned final option may raise the envelope to $45M (scale independently) or $60M (raise growth capital); the extra goes to the destination-aligned buckets (Test Lab policy).
A18: • Every strategy uses the same event policy (Test Lab DEFAULT_POLICY): accept the Q5 contract when on strategy and deliverable (fit ≥ 0.3) or fit ≥ 0.55; recession: hiring freeze when not investing in People, plus a targeted cut and $10M slower investment when cash < $40M; debt-first liquidity to keep closing cash ≥ $25M; crisis response by severity; Q8 option by eligibility. Differences between strategies therefore come from the investment strategy and destination.
A19: • Market: the engine’s market path is deterministic (one authored scenario). Sensitivity uses the runner’s supported market-override hook to vary conditions; player briefings (signals) stay as authored, so only the adaptive strategy could react to them. No stochastic outcomes were invented.
A20: • Executive scores (NXLN-EXEC-1.1) are reported only for runs that start from the production company, because the scoring compares against that starting company.
A21: • Starting-mix experiments change calibration constants in memory for one run and restore them afterwards (verified by test). Valuation for those runs is anchored on the production starting company; “price from own start” rescales to the experiment’s own Q0.
A22: • Allocation grid: every allocation of $30M in $5M steps across the six buckets (462 allocations) × five destinations = 2,310 eight-quarter runs.
A24: Strategy definitions
A25: Id | B25: Name | C25: Family | D25: Allocation (per quarter) | E25: Description
A26: consumer-led | B26: Consumer-led | C26: Consumer | D26: $20M Consumer + $10M People | E26: $20M Consumer + $10M People every quarter; commits to Consumer AI
A27: enterprise-led | B27: Enterprise-led | C27: Enterprise | D27: $20M Enterprise + $10M People | E27: $20M Enterprise + $10M People; commits to AI-powered Enterprise
A28: ai-led | B28: AI-led | C28: AI | D28: $20M AI/Product + $10M People | E28: $20M AI/Product + $10M People; commits to Premium Human + AI
A29: diversified | B29: Diversified | C29: Diversified | D29: $10M Consumer + $10M Enterprise + $10M AI | E29: $10M each Consumer, Enterprise, AI/Product; commits to Balanced Marketplace
A30: consumer-only | B30: Consumer-only | C30: Consumer | D30: $30M Consumer | E30: $30M Consumer; commits to Consumer AI
A31: enterprise-only | B31: Enterprise-only | C31: Enterprise | D31: $30M Enterprise | E31: $30M Enterprise; commits to AI-powered Enterprise
A32: ai-only | B32: AI-only | C32: AI | D32: $30M AI/Product | E32: $30M AI/Product; commits to Consumer AI
A33: university-led | B33: University-led | C33: University | D33: $20M University + $10M People | E33: $20M University/Credentials + $10M People; commits to University/Credential Infrastructure
A34: cash-preservation | B34: Cash preservation | C34: Cash | D34: $20M held in reserve; $4M Consumer, $3M Enterprise, $3M AI | E34: Invests $10M a quarter ($4M Consumer, $3M Enterprise, $3M AI/Product) and holds $20M in reserve; Balanced Marketplace
A35: adaptive | B35: Adaptive (evidence-responsive) | C35: Adaptive | D35: Balanced Q1, then shifts with market evidence (Test Lab "evidence-responsive") | E35: Explores broadly in Q1, then follows the evidence: shifts toward Enterprise + AI when AI disruption and enterprise AI demand appear, keeps Consumer defended, commits to AI-powered Enterprise at Q4.
A36: university-only | B36: University-only | C36: University | D36: $30M University | E36: $30M University/Credentials
... A39: enterprise-ai-people | B39: Enterprise + AI + People | C39: Enterprise | D39: $15M Enterprise + $10M AI + $5M People | E39: $15M Enterprise + $10M AI + $5M People
A41: Market scenarios (sensitivity)
A42: Id | B42: Label | C42: Definition
A43: authored | B43: Authored arc | C43: The production scenario: AI disruption from Q2, Q5 contract, Q6 recession, Q7 crisis, Q8 final decision.
A44: consumer-weak | B44: Consumer weaker | C44: Consumer demand ×0.9 and commoditization +0.15 from Q2.
A45: consumer-strong | B45: Consumer stronger | C45: Consumer demand ×1.1, commoditization halved and CAC pressure −0.1 from Q2.
A46: enterprise-boom | B46: Enterprise boom | C46: Enterprise demand ×1.2 and enterprise AI demand ×1.15 from Q2.
A47: enterprise-slump | B47: Enterprise slump | C47: Enterprise demand ×0.85 and enterprise AI demand ×0.9 from Q2.
A48: ai-boom | B48: AI boom | C48: AI-native demand ×1.3 and enterprise AI demand ×1.1 from Q2.
A49: university-boom | B49: University boom | C49: University demand ×1.25 from Q2.
A50: no-disruption | B50: No AI disruption | C50: From Q2: consumer demand +0.1 (max 1, the recession dip remains), commoditization 0, CAC pressure 1; AI-native and enterprise AI demand 1 (capacities as authored).
A51: severe-recession | B51: Severe recession | C51: Macro pressure 1.0 / 0.8 / 0.4 in Q6–Q8 and all segment demand ×0.9 in Q6–Q7.
A52: no-recession | B52: No recession | C52: Q6–Q8 macro pressure 0.1 and demand held at Q5 levels (the Q6 response decision still occurs).
A54: Workbook map
A55: Executive comparison | B55: Q8 outcomes for every strategy, ranks, and how Consumer-only compares with the field
A56: Quarter-by-quarter results | B56: Every quarter of every strategy; revenue, profit, cash and share-price matrices
A57: Investment & capability | B57: Capabilities built, marginal return of each bucket, allocation-grid main effects, bucket economics
A58: Starting revenue distribution | B58: Alternative A and B mixes: validity check, required re-base, and results
A59: Sensitivity analysis | B59: Ten market scenarios × ten strategies: prices, scores and ranks
A60: Contract & financing audit | B60: Contract, envelope, financing and recession mechanics
A61: Recommendations | B61: Answers, tested calibration packages and proposed rule changes
A62: Allocation grid | B62: Appendix: 2,310 runs (462 allocations × 5 destinations)
A63: Destination sweep | B63: Appendix: 14 strategies × 5 destinations
A64: Proposal tests | B64: Appendix: every candidate change and package × 6 scenarios × 10 strategies

Sheet Executive comparison
A1: 1 · Executive comparison — Q8 (Q4 2024) outcomes
A2: Authored market, production starting company, identical event policy. Ranks and comparisons are formulas over the recorded results.
A4: Key findings
A5: • Consumer investment is not the dominant strategy. Consumer-only ranks 7th of 10 on Q8 share price and 8th on the terminal score, and sits at the 27th percentile of all 462 tested allocations. It is near the top only in Q1–Q2 (2nd–3rd, within $1 of the leader) and falls to 5th–7th from Q3.
A6: • AI/Product is the dominant investment. Every best allocation for every destination contains $10M AI/Product; the best allocation without AI scores $116–$133 against $156–$166 with it. An extra $10M a quarter in AI adds $25M of Q8 revenue versus $8M for Consumer.
A7: • Enterprise is not commercially viable as a lead strategy: Enterprise-only finishes last and Enterprise-led 9th in all ten market scenarios. Each extra $5M of Enterprise lowers the average Q8 price. University-led holds a $111 price but University revenue does not grow within eight quarters.
A8: • The strongest single play is Consumer + AI ($15M each, Consumer AI destination): $164.5 share price, 99th percentile. Consumer works as AI’s complement: it defends the 70% revenue base from the AI disruption (strategies without Consumer investment lose up to $19M of Consumer revenue by Q8), carries no recurring cost commitment and matures 50% in the quarter invested.
A10: Q8 outcomes by strategy
A11: Rows 1–10 are the required strategies; rows 11–14 are supplementary. Rank formulas rank the ten required strategies only.
A12: Strategy | B12: Family | C12: Allocation | D12: Destination | E12: Q8 revenue ($M) | F12: Q8 operating profit ($M) | G12: Cumulative OP Q1–Q8 ($M) | H12: Q8 cash ($M) | I12: Q8 debt ($M) | J12: Net cash ($M) | K12: Share price Q8 ($) | L12: Price change vs $100 | M12: Terminal score | N12: Financial | O12: Strategic | P12: Organizational | Q12: Executive team avg | R12: CEO | S12: CFO | T12: CPO | U12: CGO | V12: CPeO | W12: Culture Q8 | X12: Capability gain (pts) | Y12: Financing raised ($M) | Z12: Ever insolvent | AA12: Distressed quarters | AB12: Q8 option | AC12: Q5 contract | AD12: Grid percentile (price) | AE12: Rank: price | AF12: Rank: terminal | AG12: Rank: cumulative OP
A13: Consumer-led | B13: Consumer | C13: $20M Consumer + $10M People | D13: consumer-ai | E13: 212.37071 | F13: 34.530189 | G13: 249.95285 | H13: 46.64691 | I13: 0 | J13: =H13-I13 -> 46.64691 | K13: 116.21624 | L13: =K13/100-1 -> 0.16216236 | M13: 68.063016 | N13: 58.235331 | O13: 73.450224 | P13: 76.245222 | Q13: 64.156937 | R13: 71.793564 | S13: 62.586796 | T13: 59.516852 | U13: 61.344226 | V13: 65.543247 | W13: 72 | X13: 111.04223 | Y13: 0 | Z13: no | AA13: 0 | AB13: scale-independently | AC13: declined | AD13: 0.37445887 | AE13: =RANK(K13,$K$13:$K$22) -> 5 | AF13: =RANK(M13,$M$13:$M$22) -> 5 | AG13: =RANK(G13,$G$13:$G$22) -> 6
A14: Enterprise-led | B14: Enterprise | C14: $20M Enterprise + $10M People | D14: enterprise-ai | E14: 197.52408 | F14: 23.305665 | G14: 199.8321 | H14: 25 | I14: 0.065865433 | J14: =H14-I14 -> 24.934135 | K14: 81.785813 | L14: =K14/100-1 -> -0.18214187 | M14: 58.631732 | N14: 49.065257 | O14: 63.716497 | P14: 66.819419 | Q14: 48.887657 | R14: 60.969206 | S14: 40.557897 | T14: 48.551279 | U14: 43.259555 | V14: 51.100351 | W14: 63 | X14: 137.08348 | Y14: 0.065865433 | Z14: no | AA14: 0 | AB14: continue | AC14: accepted | AD14: 0.067099567 | AE14: =RANK(K14,$K$13:$K$22) -> 9 | AF14: =RANK(M14,$M$13:$M$22) -> 9 | AG14: =RANK(G14,$G$13:$G$22) -> 9
A15: AI-led | B15: AI | C15: $20M AI/Product + $10M People | D15: premium-human-ai | E15: 234.70009 | F15: 45.626067 | G15: 277.75757 | H15: 84.507569 | I15: 0 | J15: =H15-I15 -> 84.507569 | K15: 148.51302 | L15: =K15/100-1 -> 0.48513019 | M15: 80.49111 | N15: 77.675411 | O15: 87.169104 | P15: 75.647035 | Q15: 73.502476 | R15: 78.659525 | S15: 74.380816 | T15: 80.373536 | U15: 65.137403 | V15: 68.961101 | W15: 67.705829 | X15: 134.07519 | Y15: 0 | Z15: no | AA15: 0 | AB15: scale-independently | AC15: declined | AD15: 0.80952381 | AE15: =RANK(K15,$K$13:$K$22) -> 2 | AF15: =RANK(M15,$M$13:$M$22) -> 1 | AG15: =RANK(G15,$G$13:$G$22) -> 1
A16: Diversified | B16: Diversified | C16: $10M Consumer + $10M Enterprise + $10M AI | D16: balanced-marketplace | E16: 226.21999 | F16: 46.040358 | G16: 273.094 | H16: 76.420295 | I16: 0 | J16: =H16-I16 -> 76.420295 | K16: 143.75331 | L16: =K16/100-1 -> 0.43753309 | M16: 76.715858 | N16: 75.13875 | O16: 92.817875 | P16: 56.696408 | Q16: 72.310093 | R16: 82.728366 | S16: 73.919518 | T16: 72.727674 | U16: 68.700898 | V16: 63.474009 | W16: 69.451645 | X16: 194.49002 | Y16: 0 | Z16: no | AA16: 0 | AB16: scale-independently | AC16: declined | AD16: 0.91991342 | AE16: =RANK(K16,$K$13:$K$22) -> 3 | AF16: =RANK(M16,$M$13:$M$22) -> 3 | AG16: =RANK(G16,$G$13:$G$22) -> 2
A17: Consumer-only | B17: Consumer | C17: $30M Consumer | D17: consumer-ai | E17: 203.89316 | F17: 34.747534 | G17: 257.07733 | H17: 56.391335 | I17: 0 | J17: =H17-I17 -> 56.391335 | K17: 109.88221 | L17: =K17/100-1 -> 0.09882212 | M17: 61.803585 | N17: 56.212526 | O17: 71.610483 | P17: 57.019623 | Q17: 58.563156 | R17: 66.165319 | S17: 62.979138 | T17: 52.390534 | U17: 54.515532 | V17: 56.765256 | W17: 70.5 | X17: 65.380066 | Y17: 0 | Z17: no | AA17: 0 | AB17: scale-independently | AC17: declined | AD17: 0.26623377 | AE17: =RANK(K17,$K$13:$K$22) -> 7 | AF17: =RANK(M17,$M$13:$M$22) -> 8 | AG17: =RANK(G17,$G$13:$G$22) -> 5
A18: Enterprise-only | B18: Enterprise | C18: $30M Enterprise | D18: enterprise-ai | E18: 193.27843 | F18: 22.33508 | G18: 196.9351 | H18: 25 | I18: 26.681658 | J18: =H18-I18 -> -1.681658 | K18: 74.746025 | L18: =K18/100-1 -> -0.25253975 | M18: 51.717494 | N18: 45.532497 | O18: 62.658737 | P18: 46.295749 | Q18: 43.022401 | R18: 56.697788 | S18: 37.552587 | T18: 42.437175 | U18: 38.913459 | V18: 39.510998 | W18: 61.5 | X18: 106.25718 | Y18: 26.681658 | Z18: no | AA18: 0 | AB18: continue | AC18: accepted | AD18: 0.025974026 | AE18: =RANK(K18,$K$13:$K$22) -> 10 | AF18: =RANK(M18,$M$13:$M$22) -> 10 | AG18: =RANK(G18,$G$13:$G$22) -> 10
A19: AI-only | B19: AI | C19: $30M AI/Product | D19: consumer-ai | E19: 220.94389 | F19: 38.982539 | G19: 258.24927 | H19: 60.269426 | I19: 0 | J19: =H19-I19 -> 60.269426 | K19: 127.25922 | L19: =K19/100-1 -> 0.2725922 | M19: 69.260958 | N19: 68.303905 | O19: 78.869453 | P19: 57.340351 | Q19: 65.800633 | R19: 77.72633 | S19: 66.623965 | T19: 72.797273 | U19: 51.106466 | V19: 60.749132 | W19: 70.5 | X19: 111.73026 | Y19: 0 | Z19: no | AA19: 0 | AB19: scale-independently | AC19: declined | AD19: 0.49134199 | AE19: =RANK(K19,$K$13:$K$22) -> 4 | AF19: =RANK(M19,$M$13:$M$22) -> 4 | AG19: =RANK(G19,$G$13:$G$22) -> 4
A20: University-led | B20: University | C20: $20M University + $10M People | D20: university-infrastructure | E20: 198.16419 | F20: 24.703897 | G20: 214.01273 | H20: 32.512726 | I20: 0 | J20: =H20-I20 -> 32.512726 | K20: 110.90344 | L20: =K20/100-1 -> 0.10903443 | M20: 63.653293 | N20: 48.961507 | O20: 67.197319 | P20: 82.198515 | Q20: 59.681153 | R20: 68.650174 | S20: 51.596176 | T20: 62.646879 | U20: 52.981846 | V20: 62.530689 | W20: 72 | X20: 125 | Y20: 0 | Z20: no | AA20: 0 | AB20: continue | AC20: declined | AD20: 0.28354978 | AE20: =RANK(K20,$K$13:$K$22) -> 6 | AF20: =RANK(M20,$M$13:$M$22) -> 7 | AG20: =RANK(G20,$G$13:$G$22) -> 8
A21: Cash preservation | B21: Cash | C21: $20M held in reserve; $4M Consumer, $3M Enterprise, $3M AI | D21: balanced-marketplace | E21: 196.35179 | F21: 28.102658 | G21: 223.16578 | H21: 186.7938 | I21: 0 | J21: =H21-I21 -> 186.7938 | K21: 102.81459 | L21: =K21/100-1 -> 0.028145919 | M21: 64.43345 | N21: 61.553448 | O21: 73.119733 | P21: 56.880657 | Q21: 55.27048 | R21: 63.527144 | S21: 55.429968 | T21: 57.889601 | U21: 46.482422 | V21: 53.023263 | W21: 69.524057 | X21: 84.84047 | Y21: 0 | Z21: no | AA21: 0 | AB21: scale-independently | AC21: declined | AD21: n/a (not a constant $5M-step allocation) | AE21: =RANK(K21,$K$13:$K$22) -> 8 | AF21: =RANK(M21,$M$13:$M$22) -> 6 | AG21: =RANK(G21,$G$13:$G$22) -> 7
A22: Adaptive (evidence-responsive) | B22: Adaptive | C22: Balanced Q1, then shifts with market evidence (Test Lab "evidence-responsive") | D22: enterprise-ai | E22: 233.34923 | F22: 47.053928 | G22: 262.125 | H22: 80.90442 | I22: 0 | J22: =H22-I22 -> 80.90442 | K22: 148.82113 | L22: =K22/100-1 -> 0.48821127 | M22: 80.331139 | N22: 79.924649 | O22: 86.873244 | P22: 71.822576 | Q22: 76.139336 | R22: 86.384888 | S22: 73.04494 | T22: 75.574488 | U22: 71.551872 | V22: 74.140492 | W22: 72 | X22: 197.82665 | Y22: 0 | Z22: no | AA22: 0 | AB22: scale-independently | AC22: accepted | AD22: n/a (not a constant $5M-step allocation) | AE22: =RANK(K22,$K$13:$K$22) -> 1 | AF22: =RANK(M22,$M$13:$M$22) -> 2 | AG22: =RANK(G22,$G$13:$G$22) -> 3
A23: University-only | B23: University | C23: $30M University | D23: university-infrastructure | E23: 190.77351 | F23: 25.150063 | G23: 218.92204 | H23: 37.422041 | I23: 0 | J23: =H23-I23 -> 37.422041 | K23: 111.10786 | L23: =K23/100-1 -> 0.11107862 | M23: 60.884119 | N23: 47.227856 | O23: 73.981225 | P23: 64.398192 | Q23: 55.904334 | R23: 64.537132 | S23: 54.901946 | T23: 58.024164 | U23: 48.30228 | V23: 53.756149 | W23: 70.5 | X23: 78.5 | Y23: 0 | Z23: no | AA23: 0 | AB23: scale-independently | AC23: declined | AD23: 0.29004329
A24: Consumer + AI | B24: Consumer | C24: $15M Consumer + $15M AI | D24: consumer-ai | E24: 241.53032 | F24: 57.949347 | G24: 312.17064 | H24: 110.77155 | I24: 0 | J24: =H24-I24 -> 110.77155 | K24: 164.53244 | L24: =K24/100-1 -> 0.64532435 | M24: 81.593225 | N24: 85.668892 | O24: 94.230801 | P24: 57.379552 | Q24: 79.727188 | R24: 89.237723 | S24: 85.340108 | T24: 78.512012 | U24: 76.681307 | V24: 68.864792 | W24: 70.5 | X24: 168.37958 | Y24: 0 | Z24: no | AA24: 0 | AB24: scale-independently | AC24: declined | AD24: 0.99134199
A25: Enterprise + AI | B25: Enterprise | C25: $15M Enterprise + $15M AI | D25: enterprise-ai | E25: 229.37912 | F25: 43.642821 | G25: 254.01798 | H25: 44.339872 | I25: 0 | J25: =H25-I25 -> 44.339872 | K25: 145.25432 | L25: =K25/100-1 -> 0.45254318 | M25: 75.013205 | N25: 74.429964 | O25: 88.374826 | P25: 57.240123 | Q25: 71.297265 | R25: 84.257367 | S25: 70.54433 | T25: 73.128111 | U25: 63.954127 | V25: 64.602389 | W25: 70.5 | X25: 216.79854 | Y25: 0 | Z25: no | AA25: 0 | AB25: scale-independently | AC25: accepted | AD25: 0.75324675
A26: Enterprise + AI + People | B26: Enterprise | C26: $15M Enterprise + $10M AI + $5M People | D26: enterprise-ai | E26: 233.40985 | F26: 44.191944 | G26: 252.58351 | H26: 43.096898 | I26: 0 | J26: =H26-I26 -> 43.096898 | K26: 148.26927 | L26: =K26/100-1 -> 0.48269272 | M26: 79.145913 | N26: 76.224108 | O26: 87.909911 | P26: 71.551201 | Q26: 74.922014 | R26: 87.135568 | S26: 70.802094 | T26: 75.92673 | U26: 67.362364 | V26: 73.383311 | W26: 72 | X26: 224.50146 | Y26: 0 | Z26: no | AA26: 0 | AB26: scale-independently | AC26: accepted | AD26: 0.8030303
A28: Does Consumer-only outperform most alternatives? (formulas over the table above)
A29: Required strategies with a lower Q8 share price than Consumer-only | E29: =COUNTIF($K$13:$K$22,"<"&K17) -> 3
A30: … with a lower terminal score | E30: =COUNTIF($M$13:$M$22,"<"&M17) -> 2
A31: … with lower Q8 revenue | E31: =COUNTIF($E$13:$E$22,"<"&E17) -> 4
A32: … with lower cumulative operating profit | E32: =COUNTIF($G$13:$G$22,"<"&G17) -> 5
A33: Consumer-only price gap to the best required strategy ($) | E33: =K17-MAX($K$13:$K$22) -> -38.938915
A34: Spread of Q8 share price across required strategies ($) | E34: =MAX($K$13:$K$22)-MIN($K$13:$K$22) -> 74.075101
A35: Out of 9 alternatives. Consumer-only beats only Enterprise-led, Enterprise-only and (on price) Cash preservation.

Sheet Quarter-by-quarter results
A1: 2 · Quarter-by-quarter results
A2: Every quarter of every strategy (authored market). Matrices at the right are SUMIFS formulas over the long table.
A4: Strategy | B4: Q | C4: Revenue | D4: Consumer | E4: Enterprise | F4: University | G4: AI-native | H4: Operating profit | I4: Margin | J4: Strategic investment | K4: Event costs | L4: Financing | M4: Cash | N4: Debt | O4: Share price | P4: Culture | Q4: Org capacity | R4: Load ÷ capacity | S4: Solvency | T4: Distressed | V4: Revenue ($M)
A5: Consumer-led | B5: 1 | C5: 200.28931 | D5: 140.28616 | E5: 40 | F5: 15.99968 | G5: 4.003465 | H5: 30.215882 | I5: =IF(C5=0,0,H5/C5) -> 0.15086118 | J5: 30 | K5: 0 | L5: 0 | M5: 60.215882 | N5: 0 | O5: 100.6919 | P5: 72 | Q5: 62.8875 | R5: 0.4293381 | S5: healthy | T5: no | V5: Strategy | W5: Q1 | X5: Q2 | Y5: Q3 | Z5: Q4 | AA5: Q5 | AB5: Q6 | AC5: Q7 | AD5: Q8
A6: Consumer-led | B6: 2 | C6: 199.52648 | D6: 139.2281 | E6: 40.000545 | F6: 15.998792 | G6: 4.2990379 | H6: 29.693849 | I6: =IF(C6=0,0,H6/C6) -> 0.1488216 | J6: 30 | K6: 0 | L6: 0 | M6: 59.90973 | N6: 0 | O6: 99.941385 | P6: 72 | Q6: 67.811746 | R6: 0.39816111 | S6: healthy | T6: no | V6: Consumer-led | W6: =SUMIFS($C$5:$C$116,$A$5:$A$116,$V6,$B$5:$B$116,1) -> 200.28931 | X6: =SUMIFS($C$5:$C$116,$A$5:$A$116,$V6,$B$5:$B$116,2) -> 199.52648 | Y6: =SUMIFS($C$5:$C$116,$A$5:$A$116,$V6,$B$5:$B$116,3) -> 199.72808 | Z6: =SUMIFS($C$5:$C$116,$A$5:$A$116,$V6,$B$5:$B$116,4) -> 201.43358 | AA6: =SUMIFS($C$5:$C$116,$A$5:$A$116,$V6,$B$5:$B$116,5) -> 205.0317 | AB6: =SUMIFS($C$5:$C$116,$A$5:$A$116,$V6,$B$5:$B$116,6) -> 207.6048 | AC6: =SUMIFS($C$5:$C$116,$A$5:$A$116,$V6,$B$5:$B$116,7) -> 207.60835 | AD6: =SUMIFS($C$5:$C$116,$A$5:$A$116,$V6,$B$5:$B$116,8) -> 212.37071
A7: Consumer-led | B7: 3 | C7: 199.72808 | D7: 139.25373 | E7: 40.004778 | F7: 15.997945 | G7: 4.4716251 | H7: 28.946941 | I7: =IF(C7=0,0,H7/C7) -> 0.14493176 | J7: 30 | K7: 0 | L7: 0 | M7: 58.856671 | N7: 0 | O7: 101.91184 | P7: 72 | Q7: 73.636473 | R7: 0.36666612 | S7: healthy | T7: no | V7: Enterprise-led | W7: =SUMIFS($C$5:$C$116,$A$5:$A$116,$V7,$B$5:$B$116,1) -> 200.07623 | X7: =SUMIFS($C$5:$C$116,$A$5:$A$116,$V7,$B$5:$B$116,2) -> 198.70147 | Y7: =SUMIFS($C$5:$C$116,$A$5:$A$116,$V7,$B$5:$B$116,3) -> 197.69015 | Z7: =SUMIFS($C$5:$C$116,$A$5:$A$116,$V7,$B$5:$B$116,4) -> 197.12706 | AA7: =SUMIFS($C$5:$C$116,$A$5:$A$116,$V7,$B$5:$B$116,5) -> 197.13144 | AB7: =SUMIFS($C$5:$C$116,$A$5:$A$116,$V7,$B$5:$B$116,6) -> 198.03997 | AC7: =SUMIFS($C$5:$C$116,$A$5:$A$116,$V7,$B$5:$B$116,7) -> 196.09153 | AD7: =SUMIFS($C$5:$C$116,$A$5:$A$116,$V7,$B$5:$B$116,8) -> 197.52408
A8: Consumer-led | B8: 4 | C8: 201.43358 | D8: 140.77214 | E8: 40.028187 | F8: 15.996736 | G8: 4.6365162 | H8: 29.501711 | I8: =IF(C8=0,0,H8/C8) -> 0.14645875 | J8: 30 | K8: 0 | L8: 0 | M8: 58.358382 | N8: 0 | O8: 106.80956 | P8: 72 | Q8: 79.452458 | R8: 0.40578859 | S8: healthy | T8: no | V8: AI-led | W8: =SUMIFS($C$5:$C$116,$A$5:$A$116,$V8,$B$5:$B$116,1) -> 200.06993 | X8: =SUMIFS($C$5:$C$116,$A$5:$A$116,$V8,$B$5:$B$116,2) -> 199.73857 | Y8: =SUMIFS($C$5:$C$116,$A$5:$A$116,$V8,$B$5:$B$116,3) -> 202.03069 | Z8: =SUMIFS($C$5:$C$116,$A$5:$A$116,$V8,$B$5:$B$116,4) -> 207.59878 | AA8: =SUMIFS($C$5:$C$116,$A$5:$A$116,$V8,$B$5:$B$116,5) -> 215.29644 | AB8: =SUMIFS($C$5:$C$116,$A$5:$A$116,$V8,$B$5:$B$116,6) -> 220.84267 | AC8: =SUMIFS($C$5:$C$116,$A$5:$A$116,$V8,$B$5:$B$116,7) -> 224.97777 | AD8: =SUMIFS($C$5:$C$116,$A$5:$A$116,$V8,$B$5:$B$116,8) -> 234.70009
A9: Consumer-led | B9: 5 | C9: 205.0317 | D9: 144.22209 | E9: 40.052521 | F9: 15.993013 | G9: 4.764075 | H9: 31.444173 | I9: =IF(C9=0,0,H9/C9) -> 0.1533625 | J9: 30 | K9: 0 | L9: 0 | M9: 59.802555 | N9: 0 | O9: 112.37178 | P9: 72 | Q9: 85.288105 | R9: 0.36629846 | S9: healthy | T9: no | V9: Diversified | W9: =SUMIFS($C$5:$C$116,$A$5:$A$116,$V9,$B$5:$B$116,1) -> 200.14854 | X9: =SUMIFS($C$5:$C$116,$A$5:$A$116,$V9,$B$5:$B$116,2) -> 199.16879 | Y9: =SUMIFS($C$5:$C$116,$A$5:$A$116,$V9,$B$5:$B$116,3) -> 199.76185 | Z9: =SUMIFS($C$5:$C$116,$A$5:$A$116,$V9,$B$5:$B$116,4) -> 202.6907 | AA9: =SUMIFS($C$5:$C$116,$A$5:$A$116,$V9,$B$5:$B$116,5) -> 207.92077 | AB9: =SUMIFS($C$5:$C$116,$A$5:$A$116,$V9,$B$5:$B$116,6) -> 211.85648 | AC9: =SUMIFS($C$5:$C$116,$A$5:$A$116,$V9,$B$5:$B$116,7) -> 217.20149 | AD9: =SUMIFS($C$5:$C$116,$A$5:$A$116,$V9,$B$5:$B$116,8) -> 226.21999
A10: Consumer-led | B10: 6 | C10: 207.6048 | D10: 147.01072 | E10: 39.834299 | F10: 15.973898 | G10: 4.7858809 | H10: 33.507525 | I10: =IF(C10=0,0,H10/C10) -> 0.16140053 | J10: 30 | K10: 0 | L10: 0 | M10: 63.31008 | N10: 0 | O10: 113.45071 | P10: 72 | Q10: 91.16675 | R10: 0.33230809 | S10: healthy | T10: no | V10: Consumer-only | W10: =SUMIFS($C$5:$C$116,$A$5:$A$116,$V10,$B$5:$B$116,1) -> 200.27087 | X10: =SUMIFS($C$5:$C$116,$A$5:$A$116,$V10,$B$5:$B$116,2) -> 199.34345 | Y10: =SUMIFS($C$5:$C$116,$A$5:$A$116,$V10,$B$5:$B$116,3) -> 199.23324 | Z10: =SUMIFS($C$5:$C$116,$A$5:$A$116,$V10,$B$5:$B$116,4) -> 200.49999 | AA10: =SUMIFS($C$5:$C$116,$A$5:$A$116,$V10,$B$5:$B$116,5) -> 203.00558 | AB10: =SUMIFS($C$5:$C$116,$A$5:$A$116,$V10,$B$5:$B$116,6) -> 203.93292 | AC10: =SUMIFS($C$5:$C$116,$A$5:$A$116,$V10,$B$5:$B$116,7) -> 201.64853 | AD10: =SUMIFS($C$5:$C$116,$A$5:$A$116,$V10,$B$5:$B$116,8) -> 203.89316
A11: Consumer-led | B11: 7 | C11: 207.60835 | D11: 147.10896 | E11: 39.682619 | F11: 15.941963 | G11: 4.8748069 | H11: 32.112579 | I11: =IF(C11=0,0,H11/C11) -> 0.15467865 | J11: 30 | K11: 12.055938 | L11: 0 | M11: 53.366721 | N11: 0 | O11: 108.28464 | P11: 72 | Q11: 97.086766 | R11: 0.31930202 | S11: healthy | T11: no | V11: Enterprise-only | W11: =SUMIFS($C$5:$C$116,$A$5:$A$116,$V11,$B$5:$B$116,1) -> 200.02084 | X11: =SUMIFS($C$5:$C$116,$A$5:$A$116,$V11,$B$5:$B$116,2) -> 198.38635 | Y11: =SUMIFS($C$5:$C$116,$A$5:$A$116,$V11,$B$5:$B$116,3) -> 196.89297 | Z11: =SUMIFS($C$5:$C$116,$A$5:$A$116,$V11,$B$5:$B$116,4) -> 195.63305 | AA11: =SUMIFS($C$5:$C$116,$A$5:$A$116,$V11,$B$5:$B$116,5) -> 194.7803 | AB11: =SUMIFS($C$5:$C$116,$A$5:$A$116,$V11,$B$5:$B$116,6) -> 194.93357 | AC11: =SUMIFS($C$5:$C$116,$A$5:$A$116,$V11,$B$5:$B$116,7) -> 192.33649 | AD11: =SUMIFS($C$5:$C$116,$A$5:$A$116,$V11,$B$5:$B$116,8) -> 193.27843
A12: Consumer-led | B12: 8 | C12: 212.37071 | D12: 151.88496 | E12: 39.542181 | F12: 15.905861 | G12: 5.0377074 | H12: 34.530189 | I12: =IF(C12=0,0,H12/C12) -> 0.16259393 | J12: 41.25 | K12: 0 | L12: 0 | M12: 46.64691 | N12: 0 | O12: 116.21624 | P12: 72 | Q12: 100 | R12: 0.32 | S12: healthy | T12: no | V12: AI-only | W12: =SUMIFS($C$5:$C$116,$A$5:$A$116,$V12,$B$5:$B$116,1) -> 200.01771 | X12: =SUMIFS($C$5:$C$116,$A$5:$A$116,$V12,$B$5:$B$116,2) -> 199.64951 | Y12: =SUMIFS($C$5:$C$116,$A$5:$A$116,$V12,$B$5:$B$116,3) -> 201.46375 | Z12: =SUMIFS($C$5:$C$116,$A$5:$A$116,$V12,$B$5:$B$116,4) -> 205.48122 | AA12: =SUMIFS($C$5:$C$116,$A$5:$A$116,$V12,$B$5:$B$116,5) -> 210.86212 | AB12: =SUMIFS($C$5:$C$116,$A$5:$A$116,$V12,$B$5:$B$116,6) -> 213.473 | AC12: =SUMIFS($C$5:$C$116,$A$5:$A$116,$V12,$B$5:$B$116,7) -> 214.95644 | AD12: =SUMIFS($C$5:$C$116,$A$5:$A$116,$V12,$B$5:$B$116,8) -> 220.94389
A13: Enterprise-led | B13: 1 | C13: 200.07623 | D13: 140.03908 | E13: 40.033979 | F13: 15.99968 | G13: 4.003495 | H13: 30.05901 | I13: =IF(C13=0,0,H13/C13) -> 0.15023779 | J13: 30 | K13: 0 | L13: 0 | M13: 60.05901 | N13: 0 | O13: 100.19621 | P13: 72 | Q13: 62.9125 | R13: 0.39737731 | S13: healthy | T13: no | V13: University-led | W13: =SUMIFS($C$5:$C$116,$A$5:$A$116,$V13,$B$5:$B$116,1) -> 200.06279 | X13: =SUMIFS($C$5:$C$116,$A$5:$A$116,$V13,$B$5:$B$116,2) -> 198.6582 | Y13: =SUMIFS($C$5:$C$116,$A$5:$A$116,$V13,$B$5:$B$116,3) -> 197.69958 | Z13: =SUMIFS($C$5:$C$116,$A$5:$A$116,$V13,$B$5:$B$116,4) -> 197.41359 | AA13: =SUMIFS($C$5:$C$116,$A$5:$A$116,$V13,$B$5:$B$116,5) -> 197.97951 | AB13: =SUMIFS($C$5:$C$116,$A$5:$A$116,$V13,$B$5:$B$116,6) -> 197.07738 | AC13: =SUMIFS($C$5:$C$116,$A$5:$A$116,$V13,$B$5:$B$116,7) -> 195.91267 | AD13: =SUMIFS($C$5:$C$116,$A$5:$A$116,$V13,$B$5:$B$116,8) -> 198.16419
A14: Enterprise-led | B14: 2 | C14: 198.70147 | D14: 138.23939 | E14: 40.164087 | F14: 15.998792 | G14: 4.2992004 | H14: 28.298153 | I14: =IF(C14=0,0,H14/C14) -> 0.14241542 | J14: 30 | K14: 0 | L14: 0 | M14: 58.357163 | N14: 0 | O14: 97.565656 | P14: 72 | Q14: 67.878217 | R14: 0.36830667 | S14: healthy | T14: no | V14: Cash preservation | W14: =SUMIFS($C$5:$C$116,$A$5:$A$116,$V14,$B$5:$B$116,1) -> 200.05474 | X14: =SUMIFS($C$5:$C$116,$A$5:$A$116,$V14,$B$5:$B$116,2) -> 198.49466 | Y14: =SUMIFS($C$5:$C$116,$A$5:$A$116,$V14,$B$5:$B$116,3) -> 197.26972 | Z14: =SUMIFS($C$5:$C$116,$A$5:$A$116,$V14,$B$5:$B$116,4) -> 196.61118 | AA14: =SUMIFS($C$5:$C$116,$A$5:$A$116,$V14,$B$5:$B$116,5) -> 196.71866 | AB14: =SUMIFS($C$5:$C$116,$A$5:$A$116,$V14,$B$5:$B$116,6) -> 195.06402 | AC14: =SUMIFS($C$5:$C$116,$A$5:$A$116,$V14,$B$5:$B$116,7) -> 194.18132 | AD14: =SUMIFS($C$5:$C$116,$A$5:$A$116,$V14,$B$5:$B$116,8) -> 196.35179
A15: Enterprise-led | B15: 3 | C15: 197.69015 | D15: 136.77097 | E15: 40.44927 | F15: 15.997945 | G15: 4.4719671 | H15: 25.852616 | I15: =IF(C15=0,0,H15/C15) -> 0.13077341 | J15: 30 | K15: 0 | L15: 0 | M15: 54.209779 | N15: 0 | O15: 96.937106 | P15: 72 | Q15: 73.749614 | R15: 0.33898483 | S15: healthy | T15: no | V15: Adaptive (evidence-responsive) | W15: =SUMIFS($C$5:$C$116,$A$5:$A$116,$V15,$B$5:$B$116,1) -> 200.09855 | X15: =SUMIFS($C$5:$C$116,$A$5:$A$116,$V15,$B$5:$B$116,2) -> 198.93269 | Y15: =SUMIFS($C$5:$C$116,$A$5:$A$116,$V15,$B$5:$B$116,3) -> 198.95628 | Z15: =SUMIFS($C$5:$C$116,$A$5:$A$116,$V15,$B$5:$B$116,4) -> 201.05157 | AA15: =SUMIFS($C$5:$C$116,$A$5:$A$116,$V15,$B$5:$B$116,5) -> 205.30529 | AB15: =SUMIFS($C$5:$C$116,$A$5:$A$116,$V15,$B$5:$B$116,6) -> 211.75932 | AC15: =SUMIFS($C$5:$C$116,$A$5:$A$116,$V15,$B$5:$B$116,7) -> 221.27191 | AD15: =SUMIFS($C$5:$C$116,$A$5:$A$116,$V15,$B$5:$B$116,8) -> 233.34923
A16: Enterprise-led | B16: 4 | C16: 197.12706 | D16: 135.52456 | E16: 40.968835 | F16: 15.996736 | G16: 4.6369301 | H16: 23.900445 | I16: =IF(C16=0,0,H16/C16) -> 0.12124386 | J16: 30 | K16: 0 | L16: 0 | M16: 48.110224 | N16: 0 | O16: 95.293269 | P16: 72 | Q16: 79.58108 | R16: 0.4148788 | S16: healthy | T16: no | V16: University-only | W16: =SUMIFS($C$5:$C$116,$A$5:$A$116,$V16,$B$5:$B$116,1) -> 199.99582 | X16: =SUMIFS($C$5:$C$116,$A$5:$A$116,$V16,$B$5:$B$116,2) -> 198.28719 | Y16: =SUMIFS($C$5:$C$116,$A$5:$A$116,$V16,$B$5:$B$116,3) -> 196.75593 | Z16: =SUMIFS($C$5:$C$116,$A$5:$A$116,$V16,$B$5:$B$116,4) -> 195.6407 | AA16: =SUMIFS($C$5:$C$116,$A$5:$A$116,$V16,$B$5:$B$116,5) -> 195.15635 | AB16: =SUMIFS($C$5:$C$116,$A$5:$A$116,$V16,$B$5:$B$116,6) -> 193.04755 | AC16: =SUMIFS($C$5:$C$116,$A$5:$A$116,$V16,$B$5:$B$116,7) -> 190.26812 | AD16: =SUMIFS($C$5:$C$116,$A$5:$A$116,$V16,$B$5:$B$116,8) -> 190.77351
A17: Enterprise-led | B17: 5 | C17: 197.13144 | D17: 134.53598 | E17: 41.838088 | F17: 15.993013 | G17: 4.764353 | H17: 22.370852 | I17: =IF(C17=0,0,H17/C17) -> 0.11348191 | J17: 30 | K17: 9.6407095 | L17: 0 | M17: 30.840366 | N17: 0 | O17: 89.17644 | P17: 72 | Q17: 85.349877 | R17: 0.45165917 | S17: watch | T17: no | V17: Consumer + AI | W17: =SUMIFS($C$5:$C$116,$A$5:$A$116,$V17,$B$5:$B$116,1) -> 200.17583 | X17: =SUMIFS($C$5:$C$116,$A$5:$A$116,$V17,$B$5:$B$116,2) -> 199.55381 | Y17: =SUMIFS($C$5:$C$116,$A$5:$A$116,$V17,$B$5:$B$116,3) -> 201.1182 | Z17: =SUMIFS($C$5:$C$116,$A$5:$A$116,$V17,$B$5:$B$116,4) -> 206.09479 | AA17: =SUMIFS($C$5:$C$116,$A$5:$A$116,$V17,$B$5:$B$116,5) -> 214.11044 | AB17: =SUMIFS($C$5:$C$116,$A$5:$A$116,$V17,$B$5:$B$116,6) -> 221.42378 | AC17: =SUMIFS($C$5:$C$116,$A$5:$A$116,$V17,$B$5:$B$116,7) -> 228.92571 | AD17: =SUMIFS($C$5:$C$116,$A$5:$A$116,$V17,$B$5:$B$116,8) -> 241.53032
... A19: Enterprise-led | B19: 7 | C19: 196.09153 | D19: 128.60297 | E19: 46.733312 | F19: 15.93634 | G19: 4.8189065 | H19: 21.199805 | I19: =IF(C19=0,0,H19/C19) -> 0.10811178 | J19: 23.924984 | K19: 1.4966348 | L19: 0.030112156 | M19: 25 | N19: 0.030112156 | O19: 76.278738 | P19: 64 | Q19: 84.253191 | R19: 0.28708162 | S19: watch | T19: no | V19: Enterprise + AI + People | W19: =SUMIFS($C$5:$C$116,$A$5:$A$116,$V19,$B$5:$B$116,1) -> 200.02783 | X19: =SUMIFS($C$5:$C$116,$A$5:$A$116,$V19,$B$5:$B$116,2) -> 198.85439 | Y19: =SUMIFS($C$5:$C$116,$A$5:$A$116,$V19,$B$5:$B$116,3) -> 199.15544 | Z19: =SUMIFS($C$5:$C$116,$A$5:$A$116,$V19,$B$5:$B$116,4) -> 201.68521 | AA19: =SUMIFS($C$5:$C$116,$A$5:$A$116,$V19,$B$5:$B$116,5) -> 206.34055 | AB19: =SUMIFS($C$5:$C$116,$A$5:$A$116,$V19,$B$5:$B$116,6) -> 212.74417 | AC19: =SUMIFS($C$5:$C$116,$A$5:$A$116,$V19,$B$5:$B$116,7) -> 222.13238 | AD19: =SUMIFS($C$5:$C$116,$A$5:$A$116,$V19,$B$5:$B$116,8) -> 233.40985
A20: Enterprise-led | B20: 8 | C20: 197.52408 | D20: 126.61435 | E20: 50.102165 | F20: 15.889402 | G20: 4.9181626 | H20: 23.305665 | I20: =IF(C20=0,0,H20/C20) -> 0.11798898 | J20: 23.18414 | K20: 0.15727871 | L20: 0.035753278 | M20: 25 | N20: 0.065865433 | O20: 81.785813 | P20: 63 | Q20: 86.030822 | R20: 0.20121258 | S20: watch | T20: no
A21: AI-led | B21: 1 | C21: 200.06993 | D21: 140.04516 | E21: 40 | F21: 15.99968 | G21: 4.0250948 | H21: 30.054717 | I21: =IF(C21=0,0,H21/C21) -> 0.15022106 | J21: 30 | K21: 0 | L21: 0 | M21: 60.054717 | N21: 0 | O21: 100.13259 | P21: 72 | Q21: 62.85 | R21: 0.47732697 | S21: healthy | T21: no | V21: Operating profit ($M)
A22: AI-led | B22: 2 | C22: 199.73857 | D22: 138.47553 | E22: 40.000633 | F22: 15.998792 | G22: 5.2636148 | H22: 28.764069 | I22: =IF(C22=0,0,H22/C22) -> 0.14400859 | J22: 30 | K22: 0 | L22: 0 | M22: 58.818786 | N22: 0 | O22: 99.867395 | P22: 72 | Q22: 67.712005 | R22: 0.4430529 | S22: healthy | T22: no | V22: Strategy | W22: Q1 | X22: Q2 | Y22: Q3 | Z22: Q4 | AA22: Q5 | AB22: Q6 | AC22: Q7 | AD22: Q8
A23: AI-led | B23: 3 | C23: 202.03069 | D23: 137.89068 | E23: 40.007932 | F23: 15.997945 | G23: 8.1341347 | H23: 28.655462 | I23: =IF(C23=0,0,H23/C23) -> 0.14183718 | J23: 30 | K23: 0 | L23: 0 | M23: 57.474249 | N23: 0 | O23: 107.34052 | P23: 72 | Q23: 73.466618 | R23: 0.40834873 | S23: healthy | T23: no | V23: Consumer-led | W23: =SUMIFS($H$5:$H$116,$A$5:$A$116,$V23,$B$5:$B$116,1) -> 30.215882 | X23: =SUMIFS($H$5:$H$116,$A$5:$A$116,$V23,$B$5:$B$116,2) -> 29.693849 | Y23: =SUMIFS($H$5:$H$116,$A$5:$A$116,$V23,$B$5:$B$116,3) -> 28.946941 | Z23: =SUMIFS($H$5:$H$116,$A$5:$A$116,$V23,$B$5:$B$116,4) -> 29.501711 | AA23: =SUMIFS($H$5:$H$116,$A$5:$A$116,$V23,$B$5:$B$116,5) -> 31.444173 | AB23: =SUMIFS($H$5:$H$116,$A$5:$A$116,$V23,$B$5:$B$116,6) -> 33.507525 | AC23: =SUMIFS($H$5:$H$116,$A$5:$A$116,$V23,$B$5:$B$116,7) -> 32.112579 | AD23: =SUMIFS($H$5:$H$116,$A$5:$A$116,$V23,$B$5:$B$116,8) -> 34.530189
A24: AI-led | B24: 4 | C24: 207.59878 | D24: 138.40374 | E24: 40.051696 | F24: 15.996736 | G24: 13.14661 | H24: 31.287224 | I24: =IF(C24=0,0,H24/C24) -> 0.15071006 | J24: 30 | K24: 0 | L24: 0 | M24: 58.761473 | N24: 0 | O24: 119.21099 | P24: 72 | Q24: 79.223503 | R24: 0.43660668 | S24: healthy | T24: no | V24: Enterprise-led | W24: =SUMIFS($H$5:$H$116,$A$5:$A$116,$V24,$B$5:$B$116,1) -> 30.05901 | X24: =SUMIFS($H$5:$H$116,$A$5:$A$116,$V24,$B$5:$B$116,2) -> 28.298153 | Y24: =SUMIFS($H$5:$H$116,$A$5:$A$116,$V24,$B$5:$B$116,3) -> 25.852616 | Z24: =SUMIFS($H$5:$H$116,$A$5:$A$116,$V24,$B$5:$B$116,4) -> 23.900445 | AA24: =SUMIFS($H$5:$H$116,$A$5:$A$116,$V24,$B$5:$B$116,5) -> 22.370852 | AB24: =SUMIFS($H$5:$H$116,$A$5:$A$116,$V24,$B$5:$B$116,6) -> 24.845554 | AC24: =SUMIFS($H$5:$H$116,$A$5:$A$116,$V24,$B$5:$B$116,7) -> 21.199805 | AD24: =SUMIFS($H$5:$H$116,$A$5:$A$116,$V24,$B$5:$B$116,8) -> 23.305665
A25: AI-led | B25: 5 | C25: 215.29644 | D25: 139.74438 | E25: 40.138447 | F25: 15.993013 | G25: 19.420601 | H25: 35.426008 | I25: =IF(C25=0,0,H25/C25) -> 0.16454526 | J25: 30 | K25: 0 | L25: 0 | M25: 64.187482 | N25: 0 | O25: 131.38709 | P25: 72 | Q25: 85.015274 | R25: 0.3868659 | S25: healthy | T25: no | V25: AI-led | W25: =SUMIFS($H$5:$H$116,$A$5:$A$116,$V25,$B$5:$B$116,1) -> 30.054717 | X25: =SUMIFS($H$5:$H$116,$A$5:$A$116,$V25,$B$5:$B$116,2) -> 28.764069 | Y25: =SUMIFS($H$5:$H$116,$A$5:$A$116,$V25,$B$5:$B$116,3) -> 28.655462 | Z25: =SUMIFS($H$5:$H$116,$A$5:$A$116,$V25,$B$5:$B$116,4) -> 31.287224 | AA25: =SUMIFS($H$5:$H$116,$A$5:$A$116,$V25,$B$5:$B$116,5) -> 35.426008 | AB25: =SUMIFS($H$5:$H$116,$A$5:$A$116,$V25,$B$5:$B$116,6) -> 38.654433 | AC25: =SUMIFS($H$5:$H$116,$A$5:$A$116,$V25,$B$5:$B$116,7) -> 39.289588 | AD25: =SUMIFS($H$5:$H$116,$A$5:$A$116,$V25,$B$5:$B$116,8) -> 45.626067
A26: AI-led | B26: 6 | C26: 220.84267 | D26: 139.73842 | E26: 40.040839 | F26: 15.973898 | G26: 25.089508 | H26: 38.654433 | I26: =IF(C26=0,0,H26/C26) -> 0.17503154 | J26: 30 | K26: 0 | L26: 0 | M26: 72.841914 | N26: 0 | O26: 135.12215 | P26: 72 | Q26: 90.866235 | R26: 0.34324643 | S26: healthy | T26: no | V26: Diversified | W26: =SUMIFS($H$5:$H$116,$A$5:$A$116,$V26,$B$5:$B$116,1) -> 30.1117 | X26: =SUMIFS($H$5:$H$116,$A$5:$A$116,$V26,$B$5:$B$116,2) -> 29.067783 | Y26: =SUMIFS($H$5:$H$116,$A$5:$A$116,$V26,$B$5:$B$116,3) -> 28.324262 | Z26: =SUMIFS($H$5:$H$116,$A$5:$A$116,$V26,$B$5:$B$116,4) -> 29.61444 | AA26: =SUMIFS($H$5:$H$116,$A$5:$A$116,$V26,$B$5:$B$116,5) -> 32.611535 | AB26: =SUMIFS($H$5:$H$116,$A$5:$A$116,$V26,$B$5:$B$116,6) -> 37.527177 | AC26: =SUMIFS($H$5:$H$116,$A$5:$A$116,$V26,$B$5:$B$116,7) -> 39.79674 | AD26: =SUMIFS($H$5:$H$116,$A$5:$A$116,$V26,$B$5:$B$116,8) -> 46.040358
A27: AI-led | B27: 7 | C27: 224.97777 | D27: 138.14459 | E27: 39.22803 | F27: 15.94785 | G27: 31.657299 | H27: 39.289588 | I27: =IF(C27=0,0,H27/C27) -> 0.17463764 | J27: 30 | K27: 2 | L27: 0 | M27: 80.131502 | N27: 0 | O27: 134.98332 | P27: 67.705829 | Q27: 92.783134 | R27: 0.31471237 | S27: healthy | T27: no | V27: Consumer-only | W27: =SUMIFS($H$5:$H$116,$A$5:$A$116,$V27,$B$5:$B$116,1) -> 30.201781 | X27: =SUMIFS($H$5:$H$116,$A$5:$A$116,$V27,$B$5:$B$116,2) -> 30.156762 | Y27: =SUMIFS($H$5:$H$116,$A$5:$A$116,$V27,$B$5:$B$116,3) -> 29.777154 | Z27: =SUMIFS($H$5:$H$116,$A$5:$A$116,$V27,$B$5:$B$116,4) -> 30.606775 | AA27: =SUMIFS($H$5:$H$116,$A$5:$A$116,$V27,$B$5:$B$116,5) -> 32.385685 | AB27: =SUMIFS($H$5:$H$116,$A$5:$A$116,$V27,$B$5:$B$116,6) -> 35.791929 | AC27: =SUMIFS($H$5:$H$116,$A$5:$A$116,$V27,$B$5:$B$116,7) -> 33.409712 | AD27: =SUMIFS($H$5:$H$116,$A$5:$A$116,$V27,$B$5:$B$116,8) -> 34.747534
A28: AI-led | B28: 8 | C28: 234.70009 | D28: 140.15309 | E28: 39.370979 | F28: 15.922167 | G28: 39.253856 | H28: 45.626067 | I28: =IF(C28=0,0,H28/C28) -> 0.19440157 | J28: 41.25 | K28: 0 | L28: 0 | M28: 84.507569 | N28: 0 | O28: 148.51302 | P28: 67.705829 | Q28: 100 | R28: 0.289 | S28: healthy | T28: no | V28: Enterprise-only | W28: =SUMIFS($H$5:$H$116,$A$5:$A$116,$V28,$B$5:$B$116,1) -> 30.018163 | X28: =SUMIFS($H$5:$H$116,$A$5:$A$116,$V28,$B$5:$B$116,2) -> 28.268054 | Y28: =SUMIFS($H$5:$H$116,$A$5:$A$116,$V28,$B$5:$B$116,3) -> 25.666744 | Z28: =SUMIFS($H$5:$H$116,$A$5:$A$116,$V28,$B$5:$B$116,4) -> 23.397288 | AA28: =SUMIFS($H$5:$H$116,$A$5:$A$116,$V28,$B$5:$B$116,5) -> 21.425138 | AB28: =SUMIFS($H$5:$H$116,$A$5:$A$116,$V28,$B$5:$B$116,6) -> 25.258734 | AC28: =SUMIFS($H$5:$H$116,$A$5:$A$116,$V28,$B$5:$B$116,7) -> 20.565899 | AD28: =SUMIFS($H$5:$H$116,$A$5:$A$116,$V28,$B$5:$B$116,8) -> 22.33508
A29: Diversified | B29: 1 | C29: 200.14854 | D29: 140.13031 | E29: 40.017833 | F29: 15.99968 | G29: 4.0007133 | H29: 30.1117 | I29: =IF(C29=0,0,H29/C29) -> 0.15044676 | J29: 30 | K29: 0 | L29: 0 | M29: 60.1117 | N29: 0 | O29: 100.37877 | P29: 72 | Q29: 60 | R29: 0.61666667 | S29: healthy | T29: no | V29: AI-only | W29: =SUMIFS($H$5:$H$116,$A$5:$A$116,$V29,$B$5:$B$116,1) -> 30.016835 | X29: =SUMIFS($H$5:$H$116,$A$5:$A$116,$V29,$B$5:$B$116,2) -> 28.725131 | Y29: =SUMIFS($H$5:$H$116,$A$5:$A$116,$V29,$B$5:$B$116,3) -> 28.277115 | Z29: =SUMIFS($H$5:$H$116,$A$5:$A$116,$V29,$B$5:$B$116,4) -> 29.765741 | AA29: =SUMIFS($H$5:$H$116,$A$5:$A$116,$V29,$B$5:$B$116,5) -> 32.25307 | AB29: =SUMIFS($H$5:$H$116,$A$5:$A$116,$V29,$B$5:$B$116,6) -> 35.665351 | AC29: =SUMIFS($H$5:$H$116,$A$5:$A$116,$V29,$B$5:$B$116,7) -> 34.563491 | AD29: =SUMIFS($H$5:$H$116,$A$5:$A$116,$V29,$B$5:$B$116,8) -> 38.982539
A30: Diversified | B30: 2 | C30: 199.16879 | D30: 138.5111 | E30: 40.085695 | F30: 15.998792 | G30: 4.573204 | H30: 29.067783 | I30: =IF(C30=0,0,H30/C30) -> 0.14594548 | J30: 30 | K30: 0 | L30: 0 | M30: 59.179483 | N30: 0 | O30: 99.14872 | P30: 72 | Q30: 60 | R30: 0.61666667 | S30: healthy | T30: no | V30: University-led | W30: =SUMIFS($H$5:$H$116,$A$5:$A$116,$V30,$B$5:$B$116,1) -> 30.047579 | X30: =SUMIFS($H$5:$H$116,$A$5:$A$116,$V30,$B$5:$B$116,2) -> 29.060567 | Y30: =SUMIFS($H$5:$H$116,$A$5:$A$116,$V30,$B$5:$B$116,3) -> 27.452077 | Z30: =SUMIFS($H$5:$H$116,$A$5:$A$116,$V30,$B$5:$B$116,4) -> 26.528025 | AA30: =SUMIFS($H$5:$H$116,$A$5:$A$116,$V30,$B$5:$B$116,5) -> 26.286722 | AB30: =SUMIFS($H$5:$H$116,$A$5:$A$116,$V30,$B$5:$B$116,6) -> 25.996002 | AC30: =SUMIFS($H$5:$H$116,$A$5:$A$116,$V30,$B$5:$B$116,7) -> 23.937857 | AD30: =SUMIFS($H$5:$H$116,$A$5:$A$116,$V30,$B$5:$B$116,8) -> 24.703897
A31: Diversified | B31: 3 | C31: 199.76185 | D31: 137.75436 | E31: 40.233503 | F31: 15.997945 | G31: 5.776035 | H31: 28.324262 | I31: =IF(C31=0,0,H31/C31) -> 0.14179015 | J31: 30 | K31: 0 | L31: 0 | M31: 57.503745 | N31: 0 | O31: 103.21868 | P31: 72 | Q31: 60 | R31: 0.61666667 | S31: healthy | T31: no | V31: Cash preservation | W31: =SUMIFS($H$5:$H$116,$A$5:$A$116,$V31,$B$5:$B$116,1) -> 30.041117 | X31: =SUMIFS($H$5:$H$116,$A$5:$A$116,$V31,$B$5:$B$116,2) -> 29.237487 | Y31: =SUMIFS($H$5:$H$116,$A$5:$A$116,$V31,$B$5:$B$116,3) -> 27.743483 | Z31: =SUMIFS($H$5:$H$116,$A$5:$A$116,$V31,$B$5:$B$116,4) -> 26.878731 | AA31: =SUMIFS($H$5:$H$116,$A$5:$A$116,$V31,$B$5:$B$116,5) -> 26.660549 | AB31: =SUMIFS($H$5:$H$116,$A$5:$A$116,$V31,$B$5:$B$116,6) -> 27.917646 | AC31: =SUMIFS($H$5:$H$116,$A$5:$A$116,$V31,$B$5:$B$116,7) -> 26.584109 | AD31: =SUMIFS($H$5:$H$116,$A$5:$A$116,$V31,$B$5:$B$116,8) -> 28.102658
A32: Diversified | B32: 4 | C32: 202.6907 | D32: 138.0142 | E32: 40.512554 | F32: 15.996736 | G32: 8.1672066 | H32: 29.61444 | I32: =IF(C32=0,0,H32/C32) -> 0.14610656 | J32: 30 | K32: 0 | L32: 0 | M32: 57.118185 | N32: 0 | O32: 109.93568 | P32: 72 | Q32: 60 | R32: 0.70775495 | S32: healthy | T32: no | V32: Adaptive (evidence-responsive) | W32: =SUMIFS($H$5:$H$116,$A$5:$A$116,$V32,$B$5:$B$116,1) -> 30.074246 | X32: =SUMIFS($H$5:$H$116,$A$5:$A$116,$V32,$B$5:$B$116,2) -> 29.081194 | Y32: =SUMIFS($H$5:$H$116,$A$5:$A$116,$V32,$B$5:$B$116,3) -> 27.57945 | Z32: =SUMIFS($H$5:$H$116,$A$5:$A$116,$V32,$B$5:$B$116,4) -> 27.94324 | AA32: =SUMIFS($H$5:$H$116,$A$5:$A$116,$V32,$B$5:$B$116,5) -> 30.449025 | AB32: =SUMIFS($H$5:$H$116,$A$5:$A$116,$V32,$B$5:$B$116,6) -> 32.593425 | AC32: =SUMIFS($H$5:$H$116,$A$5:$A$116,$V32,$B$5:$B$116,7) -> 37.350486 | AD32: =SUMIFS($H$5:$H$116,$A$5:$A$116,$V32,$B$5:$B$116,8) -> 47.053928
A33: Diversified | B33: 5 | C33: 207.92077 | D33: 139.33709 | E33: 40.993322 | F33: 15.993013 | G33: 11.597347 | H33: 32.611535 | I33: =IF(C33=0,0,H33/C33) -> 0.15684597 | J33: 30 | K33: 0 | L33: 0 | M33: 59.72972 | N33: 0 | O33: 119.50045 | P33: 72 | Q33: 60 | R33: 0.70775495 | S33: healthy | T33: no | V33: University-only | W33: =SUMIFS($H$5:$H$116,$A$5:$A$116,$V33,$B$5:$B$116,1) -> 29.997419 | X33: =SUMIFS($H$5:$H$116,$A$5:$A$116,$V33,$B$5:$B$116,2) -> 29.386161 | Y33: =SUMIFS($H$5:$H$116,$A$5:$A$116,$V33,$B$5:$B$116,3) -> 27.951445 | Z33: =SUMIFS($H$5:$H$116,$A$5:$A$116,$V33,$B$5:$B$116,4) -> 27.012943 | AA33: =SUMIFS($H$5:$H$116,$A$5:$A$116,$V33,$B$5:$B$116,5) -> 26.595442 | AB33: =SUMIFS($H$5:$H$116,$A$5:$A$116,$V33,$B$5:$B$116,6) -> 27.745563 | AC33: =SUMIFS($H$5:$H$116,$A$5:$A$116,$V33,$B$5:$B$116,7) -> 25.083006 | AD33: =SUMIFS($H$5:$H$116,$A$5:$A$116,$V33,$B$5:$B$116,8) -> 25.150063
A34: Diversified | B34: 6 | C34: 211.85648 | D34: 139.32885 | E34: 41.555803 | F34: 15.973898 | G34: 14.997934 | H34: 37.527177 | I34: =IF(C34=0,0,H34/C34) -> 0.1771349 | J34: 30 | K34: 0 | L34: 0 | M34: 67.256897 | N34: 0 | O34: 124.7436 | P34: 70.5 | Q34: 59 | R34: 0.71975079 | S34: healthy | T34: no | V34: Consumer + AI | W34: =SUMIFS($H$5:$H$116,$A$5:$A$116,$V34,$B$5:$B$116,1) -> 30.131077 | X34: =SUMIFS($H$5:$H$116,$A$5:$A$116,$V34,$B$5:$B$116,2) -> 29.472986 | Y34: =SUMIFS($H$5:$H$116,$A$5:$A$116,$V34,$B$5:$B$116,3) -> 29.608923 | Z34: =SUMIFS($H$5:$H$116,$A$5:$A$116,$V34,$B$5:$B$116,4) -> 32.578589 | AA34: =SUMIFS($H$5:$H$116,$A$5:$A$116,$V34,$B$5:$B$116,5) -> 37.734804 | AB34: =SUMIFS($H$5:$H$116,$A$5:$A$116,$V34,$B$5:$B$116,6) -> 45.443239 | AC34: =SUMIFS($H$5:$H$116,$A$5:$A$116,$V34,$B$5:$B$116,7) -> 49.251677 | AD34: =SUMIFS($H$5:$H$116,$A$5:$A$116,$V34,$B$5:$B$116,8) -> 57.949347
... A36: Diversified | B36: 8 | C36: 226.21999 | D36: 141.87752 | E36: 43.797326 | F36: 15.922167 | G36: 24.622982 | H36: 46.040358 | I36: =IF(C36=0,0,H36/C36) -> 0.20352029 | J36: 40.555556 | K36: 0 | L36: 0 | M36: 76.420295 | N36: 0 | O36: 143.75331 | P36: 69.451645 | Q36: 59.90329 | R36: 0.77439634 | S36: healthy | T36: no | V36: Enterprise + AI + People | W36: =SUMIFS($H$5:$H$116,$A$5:$A$116,$V36,$B$5:$B$116,1) -> 30.022385 | X36: =SUMIFS($H$5:$H$116,$A$5:$A$116,$V36,$B$5:$B$116,2) -> 28.348261 | Y36: =SUMIFS($H$5:$H$116,$A$5:$A$116,$V36,$B$5:$B$116,3) -> 26.909004 | Z36: =SUMIFS($H$5:$H$116,$A$5:$A$116,$V36,$B$5:$B$116,4) -> 27.446792 | AA36: =SUMIFS($H$5:$H$116,$A$5:$A$116,$V36,$B$5:$B$116,5) -> 29.619542 | AB36: =SUMIFS($H$5:$H$116,$A$5:$A$116,$V36,$B$5:$B$116,6) -> 31.037599 | AC36: =SUMIFS($H$5:$H$116,$A$5:$A$116,$V36,$B$5:$B$116,7) -> 35.007985 | AD36: =SUMIFS($H$5:$H$116,$A$5:$A$116,$V36,$B$5:$B$116,8) -> 44.191944
A37: Consumer-only | B37: 1 | C37: 200.27087 | D37: 140.27119 | E37: 40 | F37: 15.99968 | G37: 4 | H37: 30.201781 | I37: =IF(C37=0,0,H37/C37) -> 0.15080466 | J37: 30 | K37: 0 | L37: 0 | M37: 60.201781 | N37: 0 | O37: 100.65677 | P37: 72 | Q37: 60 | R37: 0.46666667 | S37: healthy | T37: no
A38: Consumer-only | B38: 2 | C38: 199.34345 | D38: 139.06488 | E38: 39.99978 | F38: 15.998792 | G38: 4.28 | H38: 30.156762 | I38: =IF(C38=0,0,H38/C38) -> 0.15128042 | J38: 30 | K38: 0 | L38: 0 | M38: 60.358542 | N38: 0 | O38: 100.09447 | P38: 72 | Q38: 60 | R38: 0.46666667 | S38: healthy | T38: no | V38: Cash ($M)
A39: Consumer-only | B39: 3 | C39: 199.23324 | D39: 138.80566 | E39: 39.998746 | F39: 15.997945 | G39: 4.4308877 | H39: 29.777154 | I39: =IF(C39=0,0,H39/C39) -> 0.14945877 | J39: 30 | K39: 0 | L39: 0 | M39: 60.135696 | N39: 0 | O39: 102.82663 | P39: 72 | Q39: 60 | R39: 0.46666667 | S39: healthy | T39: no | V39: Strategy | W39: Q1 | X39: Q2 | Y39: Q3 | Z39: Q4 | AA39: Q5 | AB39: Q6 | AC39: Q7 | AD39: Q8
A40: Consumer-only | B40: 4 | C40: 200.49999 | D40: 139.93158 | E40: 40.005432 | F40: 15.996736 | G40: 4.5662357 | H40: 30.606775 | I40: =IF(C40=0,0,H40/C40) -> 0.15265225 | J40: 30 | K40: 0 | L40: 0 | M40: 60.742471 | N40: 0 | O40: 106.8341 | P40: 72 | Q40: 60 | R40: 0.557875 | S40: healthy | T40: no | V40: Consumer-led | W40: =SUMIFS($M$5:$M$116,$A$5:$A$116,$V40,$B$5:$B$116,1) -> 60.215882 | X40: =SUMIFS($M$5:$M$116,$A$5:$A$116,$V40,$B$5:$B$116,2) -> 59.90973 | Y40: =SUMIFS($M$5:$M$116,$A$5:$A$116,$V40,$B$5:$B$116,3) -> 58.856671 | Z40: =SUMIFS($M$5:$M$116,$A$5:$A$116,$V40,$B$5:$B$116,4) -> 58.358382 | AA40: =SUMIFS($M$5:$M$116,$A$5:$A$116,$V40,$B$5:$B$116,5) -> 59.802555 | AB40: =SUMIFS($M$5:$M$116,$A$5:$A$116,$V40,$B$5:$B$116,6) -> 63.31008 | AC40: =SUMIFS($M$5:$M$116,$A$5:$A$116,$V40,$B$5:$B$116,7) -> 53.366721 | AD40: =SUMIFS($M$5:$M$116,$A$5:$A$116,$V40,$B$5:$B$116,8) -> 46.64691
A41: Consumer-only | B41: 5 | C41: 203.00558 | D41: 142.35838 | E41: 39.994841 | F41: 15.993013 | G41: 4.6593461 | H41: 32.385685 | I41: =IF(C41=0,0,H41/C41) -> 0.15953101 | J41: 30 | K41: 0 | L41: 0 | M41: 63.128157 | N41: 0 | O41: 110.90693 | P41: 72 | Q41: 60 | R41: 0.53454167 | S41: healthy | T41: no | V41: Enterprise-led | W41: =SUMIFS($M$5:$M$116,$A$5:$A$116,$V41,$B$5:$B$116,1) -> 60.05901 | X41: =SUMIFS($M$5:$M$116,$A$5:$A$116,$V41,$B$5:$B$116,2) -> 58.357163 | Y41: =SUMIFS($M$5:$M$116,$A$5:$A$116,$V41,$B$5:$B$116,3) -> 54.209779 | Z41: =SUMIFS($M$5:$M$116,$A$5:$A$116,$V41,$B$5:$B$116,4) -> 48.110224 | AA41: =SUMIFS($M$5:$M$116,$A$5:$A$116,$V41,$B$5:$B$116,5) -> 30.840366 | AB41: =SUMIFS($M$5:$M$116,$A$5:$A$116,$V41,$B$5:$B$116,6) -> 29.191702 | AC41: =SUMIFS($M$5:$M$116,$A$5:$A$116,$V41,$B$5:$B$116,7) -> 25 | AD41: =SUMIFS($M$5:$M$116,$A$5:$A$116,$V41,$B$5:$B$116,8) -> 25
A42: Consumer-only | B42: 6 | C42: 203.93292 | D42: 143.58975 | E42: 39.719983 | F42: 15.973898 | G42: 4.6492861 | H42: 35.791929 | I42: =IF(C42=0,0,H42/C42) -> 0.17550835 | J42: 30 | K42: 0 | L42: 0 | M42: 68.920085 | N42: 0 | O42: 111.71564 | P42: 70.5 | Q42: 59 | R42: 0.51987288 | S42: healthy | T42: no | V42: AI-led | W42: =SUMIFS($M$5:$M$116,$A$5:$A$116,$V42,$B$5:$B$116,1) -> 60.054717 | X42: =SUMIFS($M$5:$M$116,$A$5:$A$116,$V42,$B$5:$B$116,2) -> 58.818786 | Y42: =SUMIFS($M$5:$M$116,$A$5:$A$116,$V42,$B$5:$B$116,3) -> 57.474249 | Z42: =SUMIFS($M$5:$M$116,$A$5:$A$116,$V42,$B$5:$B$116,4) -> 58.761473 | AA42: =SUMIFS($M$5:$M$116,$A$5:$A$116,$V42,$B$5:$B$116,5) -> 64.187482 | AB42: =SUMIFS($M$5:$M$116,$A$5:$A$116,$V42,$B$5:$B$116,6) -> 72.841914 | AC42: =SUMIFS($M$5:$M$116,$A$5:$A$116,$V42,$B$5:$B$116,7) -> 80.131502 | AD42: =SUMIFS($M$5:$M$116,$A$5:$A$116,$V42,$B$5:$B$116,8) -> 84.507569
A43: Consumer-only | B43: 7 | C43: 201.64853 | D43: 141.52523 | E43: 39.484995 | F43: 15.941361 | G43: 4.6969445 | H43: 33.409712 | I43: =IF(C43=0,0,H43/C43) -> 0.16568289 | J43: 30 | K43: 13.185996 | L43: 0 | M43: 59.143801 | N43: 0 | O43: 103.9525 | P43: 70.5 | Q43: 59 | R43: 0.51525424 | S43: healthy | T43: no | V43: Diversified | W43: =SUMIFS($M$5:$M$116,$A$5:$A$116,$V43,$B$5:$B$116,1) -> 60.1117 | X43: =SUMIFS($M$5:$M$116,$A$5:$A$116,$V43,$B$5:$B$116,2) -> 59.179483 | Y43: =SUMIFS($M$5:$M$116,$A$5:$A$116,$V43,$B$5:$B$116,3) -> 57.503745 | Z43: =SUMIFS($M$5:$M$116,$A$5:$A$116,$V43,$B$5:$B$116,4) -> 57.118185 | AA43: =SUMIFS($M$5:$M$116,$A$5:$A$116,$V43,$B$5:$B$116,5) -> 59.72972 | AB43: =SUMIFS($M$5:$M$116,$A$5:$A$116,$V43,$B$5:$B$116,6) -> 67.256897 | AC43: =SUMIFS($M$5:$M$116,$A$5:$A$116,$V43,$B$5:$B$116,7) -> 70.935492 | AD43: =SUMIFS($M$5:$M$116,$A$5:$A$116,$V43,$B$5:$B$116,8) -> 76.420295
A44: Consumer-only | B44: 8 | C44: 203.89316 | D44: 143.95298 | E44: 39.246379 | F44: 15.904194 | G44: 4.7896082 | H44: 34.747534 | I44: =IF(C44=0,0,H44/C44) -> 0.1704203 | J44: 37.5 | K44: 0 | L44: 0 | M44: 56.391335 | N44: 0 | O44: 109.88221 | P44: 70.5 | Q44: 59 | R44: 0.51525424 | S44: healthy | T44: no | V44: Consumer-only | W44: =SUMIFS($M$5:$M$116,$A$5:$A$116,$V44,$B$5:$B$116,1) -> 60.201781 | X44: =SUMIFS($M$5:$M$116,$A$5:$A$116,$V44,$B$5:$B$116,2) -> 60.358542 | Y44: =SUMIFS($M$5:$M$116,$A$5:$A$116,$V44,$B$5:$B$116,3) -> 60.135696 | Z44: =SUMIFS($M$5:$M$116,$A$5:$A$116,$V44,$B$5:$B$116,4) -> 60.742471 | AA44: =SUMIFS($M$5:$M$116,$A$5:$A$116,$V44,$B$5:$B$116,5) -> 63.128157 | AB44: =SUMIFS($M$5:$M$116,$A$5:$A$116,$V44,$B$5:$B$116,6) -> 68.920085 | AC44: =SUMIFS($M$5:$M$116,$A$5:$A$116,$V44,$B$5:$B$116,7) -> 59.143801 | AD44: =SUMIFS($M$5:$M$116,$A$5:$A$116,$V44,$B$5:$B$116,8) -> 56.391335
A45: Enterprise-only | B45: 1 | C45: 200.02084 | D45: 139.97282 | E45: 40.048333 | F45: 15.99968 | G45: 4 | H45: 30.018163 | I45: =IF(C45=0,0,H45/C45) -> 0.15007518 | J45: 30 | K45: 0 | L45: 0 | M45: 60.018163 | N45: 0 | O45: 100.07818 | P45: 72 | Q45: 60 | R45: 0.43333333 | S45: healthy | T45: no | V45: Enterprise-only | W45: =SUMIFS($M$5:$M$116,$A$5:$A$116,$V45,$B$5:$B$116,1) -> 60.018163 | X45: =SUMIFS($M$5:$M$116,$A$5:$A$116,$V45,$B$5:$B$116,2) -> 58.286217 | Y45: =SUMIFS($M$5:$M$116,$A$5:$A$116,$V45,$B$5:$B$116,3) -> 53.952961 | Z45: =SUMIFS($M$5:$M$116,$A$5:$A$116,$V45,$B$5:$B$116,4) -> 47.350248 | AA45: =SUMIFS($M$5:$M$116,$A$5:$A$116,$V45,$B$5:$B$116,5) -> 28.400387 | AB45: =SUMIFS($M$5:$M$116,$A$5:$A$116,$V45,$B$5:$B$116,6) -> 25 | AC45: =SUMIFS($M$5:$M$116,$A$5:$A$116,$V45,$B$5:$B$116,7) -> 25 | AD45: =SUMIFS($M$5:$M$116,$A$5:$A$116,$V45,$B$5:$B$116,8) -> 25
A46: Enterprise-only | B46: 2 | C46: 198.38635 | D46: 137.87554 | E46: 40.232015 | F46: 15.998792 | G46: 4.28 | H46: 28.268054 | I46: =IF(C46=0,0,H46/C46) -> 0.14248992 | J46: 30 | K46: 0 | L46: 0 | M46: 58.286217 | N46: 0 | O46: 96.84225 | P46: 72 | Q46: 60 | R46: 0.43333333 | S46: healthy | T46: no | V46: AI-only | W46: =SUMIFS($M$5:$M$116,$A$5:$A$116,$V46,$B$5:$B$116,1) -> 60.016835 | X46: =SUMIFS($M$5:$M$116,$A$5:$A$116,$V46,$B$5:$B$116,2) -> 58.741965 | Y46: =SUMIFS($M$5:$M$116,$A$5:$A$116,$V46,$B$5:$B$116,3) -> 57.019081 | Z46: =SUMIFS($M$5:$M$116,$A$5:$A$116,$V46,$B$5:$B$116,4) -> 56.784822 | AA46: =SUMIFS($M$5:$M$116,$A$5:$A$116,$V46,$B$5:$B$116,5) -> 59.037892 | AB46: =SUMIFS($M$5:$M$116,$A$5:$A$116,$V46,$B$5:$B$116,6) -> 64.703243 | AC46: =SUMIFS($M$5:$M$116,$A$5:$A$116,$V46,$B$5:$B$116,7) -> 58.786887 | AD46: =SUMIFS($M$5:$M$116,$A$5:$A$116,$V46,$B$5:$B$116,8) -> 60.269426
A47: Enterprise-only | B47: 3 | C47: 196.89297 | D47: 135.83777 | E47: 40.626363 | F47: 15.997945 | G47: 4.4308877 | H47: 25.666744 | I47: =IF(C47=0,0,H47/C47) -> 0.13035886 | J47: 30 | K47: 0 | L47: 0 | M47: 53.952961 | N47: 0 | O47: 95.434245 | P47: 72 | Q47: 60 | R47: 0.43333333 | S47: healthy | T47: no | V47: University-led | W47: =SUMIFS($M$5:$M$116,$A$5:$A$116,$V47,$B$5:$B$116,1) -> 60.047579 | X47: =SUMIFS($M$5:$M$116,$A$5:$A$116,$V47,$B$5:$B$116,2) -> 59.108146 | Y47: =SUMIFS($M$5:$M$116,$A$5:$A$116,$V47,$B$5:$B$116,3) -> 56.560223 | Z47: =SUMIFS($M$5:$M$116,$A$5:$A$116,$V47,$B$5:$B$116,4) -> 53.088248 | AA47: =SUMIFS($M$5:$M$116,$A$5:$A$116,$V47,$B$5:$B$116,5) -> 49.37497 | AB47: =SUMIFS($M$5:$M$116,$A$5:$A$116,$V47,$B$5:$B$116,6) -> 45.370972 | AC47: =SUMIFS($M$5:$M$116,$A$5:$A$116,$V47,$B$5:$B$116,7) -> 37.808829 | AD47: =SUMIFS($M$5:$M$116,$A$5:$A$116,$V47,$B$5:$B$116,8) -> 32.512726
A48: Enterprise-only | B48: 4 | C48: 195.63305 | D48: 133.75282 | E48: 41.317335 | F48: 15.996736 | G48: 4.5661648 | H48: 23.397288 | I48: =IF(C48=0,0,H48/C48) -> 0.11959782 | J48: 30 | K48: 0 | L48: 0 | M48: 47.350248 | N48: 0 | O48: 94.667928 | P48: 72 | Q48: 60 | R48: 0.52765516 | S48: healthy | T48: no | V48: Cash preservation | W48: =SUMIFS($M$5:$M$116,$A$5:$A$116,$V48,$B$5:$B$116,1) -> 80.041117 | X48: =SUMIFS($M$5:$M$116,$A$5:$A$116,$V48,$B$5:$B$116,2) -> 99.278604 | Y48: =SUMIFS($M$5:$M$116,$A$5:$A$116,$V48,$B$5:$B$116,3) -> 117.02209 | Z48: =SUMIFS($M$5:$M$116,$A$5:$A$116,$V48,$B$5:$B$116,4) -> 133.90082 | AA48: =SUMIFS($M$5:$M$116,$A$5:$A$116,$V48,$B$5:$B$116,5) -> 150.56137 | AB48: =SUMIFS($M$5:$M$116,$A$5:$A$116,$V48,$B$5:$B$116,6) -> 168.47901 | AC48: =SUMIFS($M$5:$M$116,$A$5:$A$116,$V48,$B$5:$B$116,7) -> 179.24669 | AD48: =SUMIFS($M$5:$M$116,$A$5:$A$116,$V48,$B$5:$B$116,8) -> 186.7938
A49: Enterprise-only | B49: 5 | C49: 194.7803 | D49: 131.68878 | E49: 42.439352 | F49: 15.993013 | G49: 4.6591552 | H49: 21.425138 | I49: =IF(C49=0,0,H49/C49) -> 0.10999643 | J49: 30 | K49: 10.375 | L49: 0 | M49: 28.400387 | N49: 0 | O49: 84.705799 | P49: 72 | Q49: 60 | R49: 0.61420339 | S49: watch | T49: no | V49: Adaptive (evidence-responsive) | W49: =SUMIFS($M$5:$M$116,$A$5:$A$116,$V49,$B$5:$B$116,1) -> 65.074246 | X49: =SUMIFS($M$5:$M$116,$A$5:$A$116,$V49,$B$5:$B$116,2) -> 64.15544 | Y49: =SUMIFS($M$5:$M$116,$A$5:$A$116,$V49,$B$5:$B$116,3) -> 61.73489 | Z49: =SUMIFS($M$5:$M$116,$A$5:$A$116,$V49,$B$5:$B$116,4) -> 64.678131 | AA49: =SUMIFS($M$5:$M$116,$A$5:$A$116,$V49,$B$5:$B$116,5) -> 61.44374 | AB49: =SUMIFS($M$5:$M$116,$A$5:$A$116,$V49,$B$5:$B$116,6) -> 69.037165 | AC49: =SUMIFS($M$5:$M$116,$A$5:$A$116,$V49,$B$5:$B$116,7) -> 70.100492 | AD49: =SUMIFS($M$5:$M$116,$A$5:$A$116,$V49,$B$5:$B$116,8) -> 80.90442
A50: Enterprise-only | B50: 6 | C50: 194.93357 | D50: 127.51306 | E50: 46.811317 | F50: 15.973898 | G50: 4.635288 | H50: 25.258734 | I50: =IF(C50=0,0,H50/C50) -> 0.12957612 | J50: 30 | K50: 6.4941052 | L50: 7.8349841 | M50: 25 | N50: 7.8349841 | O50: 82.231883 | P50: 63.5 | Q50: 53 | R50: 0.67079629 | S50: watch | T50: no | V50: University-only | W50: =SUMIFS($M$5:$M$116,$A$5:$A$116,$V50,$B$5:$B$116,1) -> 59.997419 | X50: =SUMIFS($M$5:$M$116,$A$5:$A$116,$V50,$B$5:$B$116,2) -> 59.38358 | Y50: =SUMIFS($M$5:$M$116,$A$5:$A$116,$V50,$B$5:$B$116,3) -> 57.335025 | Z50: =SUMIFS($M$5:$M$116,$A$5:$A$116,$V50,$B$5:$B$116,4) -> 54.347967 | AA50: =SUMIFS($M$5:$M$116,$A$5:$A$116,$V50,$B$5:$B$116,5) -> 50.94341 | AB50: =SUMIFS($M$5:$M$116,$A$5:$A$116,$V50,$B$5:$B$116,6) -> 48.688972 | AC50: =SUMIFS($M$5:$M$116,$A$5:$A$116,$V50,$B$5:$B$116,7) -> 42.271979 | AD50: =SUMIFS($M$5:$M$116,$A$5:$A$116,$V50,$B$5:$B$116,8) -> 37.422041
A51: Enterprise-only | B51: 7 | C51: 192.33649 | D51: 123.66018 | E51: 48.085938 | F51: 15.936008 | G51: 4.6543624 | H51: 20.565899 | I51: =IF(C51=0,0,H51/C51) -> 0.10692666 | J51: 30 | K51: 1.5697468 | L51: 11.003848 | M51: 25 | N51: 18.838832 | O51: 70.557057 | P51: 62.5 | Q51: 53 | R51: 0.51496026 | S51: watch | T51: no | V51: Consumer + AI | W51: =SUMIFS($M$5:$M$116,$A$5:$A$116,$V51,$B$5:$B$116,1) -> 60.131077 | X51: =SUMIFS($M$5:$M$116,$A$5:$A$116,$V51,$B$5:$B$116,2) -> 59.604062 | Y51: =SUMIFS($M$5:$M$116,$A$5:$A$116,$V51,$B$5:$B$116,3) -> 59.212985 | Z51: =SUMIFS($M$5:$M$116,$A$5:$A$116,$V51,$B$5:$B$116,4) -> 61.791574 | AA51: =SUMIFS($M$5:$M$116,$A$5:$A$116,$V51,$B$5:$B$116,5) -> 69.526378 | AB51: =SUMIFS($M$5:$M$116,$A$5:$A$116,$V51,$B$5:$B$116,6) -> 84.969616 | AC51: =SUMIFS($M$5:$M$116,$A$5:$A$116,$V51,$B$5:$B$116,7) -> 94.0722 | AD51: =SUMIFS($M$5:$M$116,$A$5:$A$116,$V51,$B$5:$B$116,8) -> 110.77155
... A53: AI-only | B53: 1 | C53: 200.01771 | D53: 139.98319 | E53: 40 | F53: 15.99968 | G53: 4.0348403 | H53: 30.016835 | I53: =IF(C53=0,0,H53/C53) -> 0.15007089 | J53: 30 | K53: 0 | L53: 0 | M53: 60.016835 | N53: 0 | O53: 100.01827 | P53: 72 | Q53: 60 | R53: 0.53333333 | S53: healthy | T53: no | V53: Enterprise + AI + People | W53: =SUMIFS($M$5:$M$116,$A$5:$A$116,$V53,$B$5:$B$116,1) -> 60.022385 | X53: =SUMIFS($M$5:$M$116,$A$5:$A$116,$V53,$B$5:$B$116,2) -> 58.370646 | Y53: =SUMIFS($M$5:$M$116,$A$5:$A$116,$V53,$B$5:$B$116,3) -> 55.27965 | Z53: =SUMIFS($M$5:$M$116,$A$5:$A$116,$V53,$B$5:$B$116,4) -> 52.726442 | AA53: =SUMIFS($M$5:$M$116,$A$5:$A$116,$V53,$B$5:$B$116,5) -> 44.564905 | AB53: =SUMIFS($M$5:$M$116,$A$5:$A$116,$V53,$B$5:$B$116,6) -> 45.602504 | AC53: =SUMIFS($M$5:$M$116,$A$5:$A$116,$V53,$B$5:$B$116,7) -> 40.154954 | AD53: =SUMIFS($M$5:$M$116,$A$5:$A$116,$V53,$B$5:$B$116,8) -> 43.096898
A54: AI-only | B54: 2 | C54: 199.64951 | D54: 138.15411 | E54: 39.999909 | F54: 15.998792 | G54: 5.4967073 | H54: 28.725131 | I54: =IF(C54=0,0,H54/C54) -> 0.14387779 | J54: 30 | K54: 0 | L54: 0 | M54: 58.741965 | N54: 0 | O54: 99.159191 | P54: 72 | Q54: 60 | R54: 0.53333333 | S54: healthy | T54: no
A55: AI-only | B55: 3 | C55: 201.46375 | D55: 136.95189 | E55: 40.002519 | F55: 15.997945 | G55: 8.5113924 | H55: 28.277115 | I55: =IF(C55=0,0,H55/C55) -> 0.14035833 | J55: 30 | K55: 0 | L55: 0 | M55: 57.019081 | N55: 0 | O55: 105.42119 | P55: 72 | Q55: 60 | R55: 0.53333333 | S55: healthy | T55: no | V55: Share price ($)
A56: AI-only | B56: 4 | C56: 205.48122 | D56: 136.12552 | E56: 40.030369 | F56: 15.996736 | G56: 13.32859 | H56: 29.765741 | I56: =IF(C56=0,0,H56/C56) -> 0.1448587 | J56: 30 | K56: 0 | L56: 0 | M56: 56.784822 | N56: 0 | O56: 114.18083 | P56: 72 | Q56: 60 | R56: 0.62122833 | S56: healthy | T56: no | V56: Strategy | W56: Q1 | X56: Q2 | Y56: Q3 | Z56: Q4 | AA56: Q5 | AB56: Q6 | AC56: Q7 | AD56: Q8
A57: AI-only | B57: 5 | C57: 210.86212 | D57: 135.51307 | E57: 40.077113 | F57: 15.993013 | G57: 19.278927 | H57: 32.25307 | I57: =IF(C57=0,0,H57/C57) -> 0.1529581 | J57: 30 | K57: 0 | L57: 0 | M57: 59.037892 | N57: 0 | O57: 122.28344 | P57: 72 | Q57: 60 | R57: 0.59456167 | S57: healthy | T57: no | V57: Consumer-led | W57: =SUMIFS($O$5:$O$116,$A$5:$A$116,$V57,$B$5:$B$116,1) -> 100.6919 | X57: =SUMIFS($O$5:$O$116,$A$5:$A$116,$V57,$B$5:$B$116,2) -> 99.941385 | Y57: =SUMIFS($O$5:$O$116,$A$5:$A$116,$V57,$B$5:$B$116,3) -> 101.91184 | Z57: =SUMIFS($O$5:$O$116,$A$5:$A$116,$V57,$B$5:$B$116,4) -> 106.80956 | AA57: =SUMIFS($O$5:$O$116,$A$5:$A$116,$V57,$B$5:$B$116,5) -> 112.37178 | AB57: =SUMIFS($O$5:$O$116,$A$5:$A$116,$V57,$B$5:$B$116,6) -> 113.45071 | AC57: =SUMIFS($O$5:$O$116,$A$5:$A$116,$V57,$B$5:$B$116,7) -> 108.28464 | AD57: =SUMIFS($O$5:$O$116,$A$5:$A$116,$V57,$B$5:$B$116,8) -> 116.21624
A58: AI-only | B58: 6 | C58: 213.473 | D58: 132.95753 | E58: 39.901017 | F58: 15.973898 | G58: 24.640559 | H58: 35.665351 | I58: =IF(C58=0,0,H58/C58) -> 0.16707195 | J58: 30 | K58: 0 | L58: 0 | M58: 64.703243 | N58: 0 | O58: 121.72129 | P58: 70.5 | Q58: 59 | R58: 0.57752034 | S58: healthy | T58: no | V58: Enterprise-led | W58: =SUMIFS($O$5:$O$116,$A$5:$A$116,$V58,$B$5:$B$116,1) -> 100.19621 | X58: =SUMIFS($O$5:$O$116,$A$5:$A$116,$V58,$B$5:$B$116,2) -> 97.565656 | Y58: =SUMIFS($O$5:$O$116,$A$5:$A$116,$V58,$B$5:$B$116,3) -> 96.937106 | Z58: =SUMIFS($O$5:$O$116,$A$5:$A$116,$V58,$B$5:$B$116,4) -> 95.293269 | AA58: =SUMIFS($O$5:$O$116,$A$5:$A$116,$V58,$B$5:$B$116,5) -> 89.17644 | AB58: =SUMIFS($O$5:$O$116,$A$5:$A$116,$V58,$B$5:$B$116,6) -> 88.903004 | AC58: =SUMIFS($O$5:$O$116,$A$5:$A$116,$V58,$B$5:$B$116,7) -> 76.278738 | AD58: =SUMIFS($O$5:$O$116,$A$5:$A$116,$V58,$B$5:$B$116,8) -> 81.785813
A59: AI-only | B59: 7 | C59: 214.95644 | D59: 127.99427 | E59: 39.804784 | F59: 15.942802 | G59: 31.214576 | H59: 34.563491 | I59: =IF(C59=0,0,H59/C59) -> 0.160793 | J59: 30 | K59: 10.479848 | L59: 0 | M59: 58.786887 | N59: 0 | O59: 117.71237 | P59: 70.5 | Q59: 59 | R59: 0.56949153 | S59: healthy | T59: no | V59: AI-led | W59: =SUMIFS($O$5:$O$116,$A$5:$A$116,$V59,$B$5:$B$116,1) -> 100.13259 | X59: =SUMIFS($O$5:$O$116,$A$5:$A$116,$V59,$B$5:$B$116,2) -> 99.867395 | Y59: =SUMIFS($O$5:$O$116,$A$5:$A$116,$V59,$B$5:$B$116,3) -> 107.34052 | Z59: =SUMIFS($O$5:$O$116,$A$5:$A$116,$V59,$B$5:$B$116,4) -> 119.21099 | AA59: =SUMIFS($O$5:$O$116,$A$5:$A$116,$V59,$B$5:$B$116,5) -> 131.38709 | AB59: =SUMIFS($O$5:$O$116,$A$5:$A$116,$V59,$B$5:$B$116,6) -> 135.12215 | AC59: =SUMIFS($O$5:$O$116,$A$5:$A$116,$V59,$B$5:$B$116,7) -> 134.98332 | AD59: =SUMIFS($O$5:$O$116,$A$5:$A$116,$V59,$B$5:$B$116,8) -> 148.51302
A60: AI-only | B60: 8 | C60: 220.94389 | D60: 126.57191 | E60: 39.712694 | F60: 15.908185 | G60: 38.751097 | H60: 38.982539 | I60: =IF(C60=0,0,H60/C60) -> 0.17643638 | J60: 37.5 | K60: 0 | L60: 0 | M60: 60.269426 | N60: 0 | O60: 127.25922 | P60: 70.5 | Q60: 59 | R60: 0.54915254 | S60: healthy | T60: no | V60: Diversified | W60: =SUMIFS($O$5:$O$116,$A$5:$A$116,$V60,$B$5:$B$116,1) -> 100.37877 | X60: =SUMIFS($O$5:$O$116,$A$5:$A$116,$V60,$B$5:$B$116,2) -> 99.14872 | Y60: =SUMIFS($O$5:$O$116,$A$5:$A$116,$V60,$B$5:$B$116,3) -> 103.21868 | Z60: =SUMIFS($O$5:$O$116,$A$5:$A$116,$V60,$B$5:$B$116,4) -> 109.93568 | AA60: =SUMIFS($O$5:$O$116,$A$5:$A$116,$V60,$B$5:$B$116,5) -> 119.50045 | AB60: =SUMIFS($O$5:$O$116,$A$5:$A$116,$V60,$B$5:$B$116,6) -> 124.7436 | AC60: =SUMIFS($O$5:$O$116,$A$5:$A$116,$V60,$B$5:$B$116,7) -> 130.9056 | AD60: =SUMIFS($O$5:$O$116,$A$5:$A$116,$V60,$B$5:$B$116,8) -> 143.75331
A61: University-led | B61: 1 | C61: 200.06279 | D61: 140.05147 | E61: 40.0059 | F61: 16.001882 | G61: 4.00354 | H61: 30.047579 | I61: =IF(C61=0,0,H61/C61) -> 0.15019074 | J61: 30 | K61: 0 | L61: 0 | M61: 60.047579 | N61: 0 | O61: 100.92228 | P61: 72 | Q61: 62.95 | R61: 0.34948372 | S61: healthy | T61: no | V61: Consumer-only | W61: =SUMIFS($O$5:$O$116,$A$5:$A$116,$V61,$B$5:$B$116,1) -> 100.65677 | X61: =SUMIFS($O$5:$O$116,$A$5:$A$116,$V61,$B$5:$B$116,2) -> 100.09447 | Y61: =SUMIFS($O$5:$O$116,$A$5:$A$116,$V61,$B$5:$B$116,3) -> 102.82663 | Z61: =SUMIFS($O$5:$O$116,$A$5:$A$116,$V61,$B$5:$B$116,4) -> 106.8341 | AA61: =SUMIFS($O$5:$O$116,$A$5:$A$116,$V61,$B$5:$B$116,5) -> 110.90693 | AB61: =SUMIFS($O$5:$O$116,$A$5:$A$116,$V61,$B$5:$B$116,6) -> 111.71564 | AC61: =SUMIFS($O$5:$O$116,$A$5:$A$116,$V61,$B$5:$B$116,7) -> 103.9525 | AD61: =SUMIFS($O$5:$O$116,$A$5:$A$116,$V61,$B$5:$B$116,8) -> 109.88221
A62: University-led | B62: 2 | C62: 198.6582 | D62: 138.31712 | E62: 40.030077 | F62: 16.011557 | G62: 4.299444 | H62: 29.060567 | I62: =IF(C62=0,0,H62/C62) -> 0.14628426 | J62: 30 | K62: 0 | L62: 0 | M62: 59.108146 | N62: 0 | O62: 100.48155 | P62: 72 | Q62: 67.977887 | R62: 0.32363465 | S62: healthy | T62: no | V62: Enterprise-only | W62: =SUMIFS($O$5:$O$116,$A$5:$A$116,$V62,$B$5:$B$116,1) -> 100.07818 | X62: =SUMIFS($O$5:$O$116,$A$5:$A$116,$V62,$B$5:$B$116,2) -> 96.84225 | Y62: =SUMIFS($O$5:$O$116,$A$5:$A$116,$V62,$B$5:$B$116,3) -> 95.434245 | Z62: =SUMIFS($O$5:$O$116,$A$5:$A$116,$V62,$B$5:$B$116,4) -> 94.667928 | AA62: =SUMIFS($O$5:$O$116,$A$5:$A$116,$V62,$B$5:$B$116,5) -> 84.705799 | AB62: =SUMIFS($O$5:$O$116,$A$5:$A$116,$V62,$B$5:$B$116,6) -> 82.231883 | AC62: =SUMIFS($O$5:$O$116,$A$5:$A$116,$V62,$B$5:$B$116,7) -> 70.557057 | AD62: =SUMIFS($O$5:$O$116,$A$5:$A$116,$V62,$B$5:$B$116,8) -> 74.746025
A63: University-led | B63: 3 | C63: 197.69958 | D63: 137.09937 | E63: 40.088074 | F63: 16.039654 | G63: 4.4724797 | H63: 27.452077 | I63: =IF(C63=0,0,H63/C63) -> 0.13885754 | J63: 30 | K63: 0 | L63: 0 | M63: 56.560223 | N63: 0 | O63: 103.48854 | P63: 72 | Q63: 73.919182 | R63: 0.29762234 | S63: healthy | T63: no | V63: AI-only | W63: =SUMIFS($O$5:$O$116,$A$5:$A$116,$V63,$B$5:$B$116,1) -> 100.01827 | X63: =SUMIFS($O$5:$O$116,$A$5:$A$116,$V63,$B$5:$B$116,2) -> 99.159191 | Y63: =SUMIFS($O$5:$O$116,$A$5:$A$116,$V63,$B$5:$B$116,3) -> 105.42119 | Z63: =SUMIFS($O$5:$O$116,$A$5:$A$116,$V63,$B$5:$B$116,4) -> 114.18083 | AA63: =SUMIFS($O$5:$O$116,$A$5:$A$116,$V63,$B$5:$B$116,5) -> 122.28344 | AB63: =SUMIFS($O$5:$O$116,$A$5:$A$116,$V63,$B$5:$B$116,6) -> 121.72129 | AC63: =SUMIFS($O$5:$O$116,$A$5:$A$116,$V63,$B$5:$B$116,7) -> 117.71237 | AD63: =SUMIFS($O$5:$O$116,$A$5:$A$116,$V63,$B$5:$B$116,8) -> 127.25922
A64: University-led | B64: 4 | C64: 197.41359 | D64: 136.4772 | E64: 40.19776 | F64: 16.100866 | G64: 4.6377643 | H64: 26.528025 | I64: =IF(C64=0,0,H64/C64) -> 0.13437791 | J64: 30 | K64: 0 | L64: 0 | M64: 53.088248 | N64: 0 | O64: 108.14252 | P64: 72 | Q64: 79.839777 | R64: 0.34671358 | S64: healthy | T64: no | V64: University-led | W64: =SUMIFS($O$5:$O$116,$A$5:$A$116,$V64,$B$5:$B$116,1) -> 100.92228 | X64: =SUMIFS($O$5:$O$116,$A$5:$A$116,$V64,$B$5:$B$116,2) -> 100.48155 | Y64: =SUMIFS($O$5:$O$116,$A$5:$A$116,$V64,$B$5:$B$116,3) -> 103.48854 | Z64: =SUMIFS($O$5:$O$116,$A$5:$A$116,$V64,$B$5:$B$116,4) -> 108.14252 | AA64: =SUMIFS($O$5:$O$116,$A$5:$A$116,$V64,$B$5:$B$116,5) -> 114.27383 | AB64: =SUMIFS($O$5:$O$116,$A$5:$A$116,$V64,$B$5:$B$116,6) -> 114.98885 | AC64: =SUMIFS($O$5:$O$116,$A$5:$A$116,$V64,$B$5:$B$116,7) -> 108.24409 | AD64: =SUMIFS($O$5:$O$116,$A$5:$A$116,$V64,$B$5:$B$116,8) -> 110.90344
A65: University-led | B65: 5 | C65: 197.97951 | D65: 136.65558 | E65: 40.34891 | F65: 16.209393 | G65: 4.7656319 | H65: 26.286722 | I65: =IF(C65=0,0,H65/C65) -> 0.13277496 | J65: 30 | K65: 0 | L65: 0 | M65: 49.37497 | N65: 0 | O65: 114.27383 | P65: 72 | Q65: 85.767366 | R65: 0.31400678 | S65: healthy | T65: no | V65: Cash preservation | W65: =SUMIFS($O$5:$O$116,$A$5:$A$116,$V65,$B$5:$B$116,1) -> 100.12603 | X65: =SUMIFS($O$5:$O$116,$A$5:$A$116,$V65,$B$5:$B$116,2) -> 97.297876 | Y65: =SUMIFS($O$5:$O$116,$A$5:$A$116,$V65,$B$5:$B$116,3) -> 96.527527 | Z65: =SUMIFS($O$5:$O$116,$A$5:$A$116,$V65,$B$5:$B$116,4) -> 96.86333 | AA65: =SUMIFS($O$5:$O$116,$A$5:$A$116,$V65,$B$5:$B$116,5) -> 98.294908 | AB65: =SUMIFS($O$5:$O$116,$A$5:$A$116,$V65,$B$5:$B$116,6) -> 96.441074 | AC65: =SUMIFS($O$5:$O$116,$A$5:$A$116,$V65,$B$5:$B$116,7) -> 95.820962 | AD65: =SUMIFS($O$5:$O$116,$A$5:$A$116,$V65,$B$5:$B$116,8) -> 102.81459
A66: University-led | B66: 6 | C66: 197.07738 | D66: 135.60122 | E66: 40.314807 | F66: 16.373759 | G66: 4.7875949 | H66: 25.996002 | I66: =IF(C66=0,0,H66/C66) -> 0.13190759 | J66: 30 | K66: 0 | L66: 0 | M66: 45.370972 | N66: 0 | O66: 114.98885 | P66: 72 | Q66: 91.726603 | R66: 0.28600876 | S66: healthy | T66: no | V66: Adaptive (evidence-responsive) | W66: =SUMIFS($O$5:$O$116,$A$5:$A$116,$V66,$B$5:$B$116,1) -> 100.49545 | X66: =SUMIFS($O$5:$O$116,$A$5:$A$116,$V66,$B$5:$B$116,2) -> 98.700854 | Y66: =SUMIFS($O$5:$O$116,$A$5:$A$116,$V66,$B$5:$B$116,3) -> 100.65096 | Z66: =SUMIFS($O$5:$O$116,$A$5:$A$116,$V66,$B$5:$B$116,4) -> 104.12782 | AA66: =SUMIFS($O$5:$O$116,$A$5:$A$116,$V66,$B$5:$B$116,5) -> 113.38771 | AB66: =SUMIFS($O$5:$O$116,$A$5:$A$116,$V66,$B$5:$B$116,6) -> 120.17986 | AC66: =SUMIFS($O$5:$O$116,$A$5:$A$116,$V66,$B$5:$B$116,7) -> 131.00897 | AD66: =SUMIFS($O$5:$O$116,$A$5:$A$116,$V66,$B$5:$B$116,8) -> 148.82113
A67: University-led | B67: 7 | C67: 195.91267 | D67: 135.68889 | E67: 40.430396 | F67: 14.931531 | G67: 4.8618521 | H67: 23.937857 | I67: =IF(C67=0,0,H67/C67) -> 0.12218637 | J67: 30 | K67: 1.5 | L67: 0 | M67: 37.808829 | N67: 0 | O67: 108.24409 | P67: 72 | Q67: 97.715119 | R67: 0.19444279 | S67: watch | T67: no | V67: University-only | W67: =SUMIFS($O$5:$O$116,$A$5:$A$116,$V67,$B$5:$B$116,1) -> 100.94668 | X67: =SUMIFS($O$5:$O$116,$A$5:$A$116,$V67,$B$5:$B$116,2) -> 100.93139 | Y67: =SUMIFS($O$5:$O$116,$A$5:$A$116,$V67,$B$5:$B$116,3) -> 104.37558 | Z67: =SUMIFS($O$5:$O$116,$A$5:$A$116,$V67,$B$5:$B$116,4) -> 109.27706 | AA67: =SUMIFS($O$5:$O$116,$A$5:$A$116,$V67,$B$5:$B$116,5) -> 114.73881 | AB67: =SUMIFS($O$5:$O$116,$A$5:$A$116,$V67,$B$5:$B$116,6) -> 114.46767 | AC67: =SUMIFS($O$5:$O$116,$A$5:$A$116,$V67,$B$5:$B$116,7) -> 107.62009 | AD67: =SUMIFS($O$5:$O$116,$A$5:$A$116,$V67,$B$5:$B$116,8) -> 111.10786
A68: University-led | B68: 8 | C68: 198.16419 | D68: 137.39844 | E68: 40.652857 | F68: 15.121688 | G68: 4.9911986 | H68: 24.703897 | I68: =IF(C68=0,0,H68/C68) -> 0.12466378 | J68: 30 | K68: 0 | L68: 0 | M68: 32.512726 | N68: 0 | O68: 110.90344 | P68: 72 | Q68: 100 | R68: 0.19 | S68: watch | T68: no | V68: Consumer + AI | W68: =SUMIFS($O$5:$O$116,$A$5:$A$116,$V68,$B$5:$B$116,1) -> 100.41414 | X68: =SUMIFS($O$5:$O$116,$A$5:$A$116,$V68,$B$5:$B$116,2) -> 100.42707 | Y68: =SUMIFS($O$5:$O$116,$A$5:$A$116,$V68,$B$5:$B$116,3) -> 107.37499 | Z68: =SUMIFS($O$5:$O$116,$A$5:$A$116,$V68,$B$5:$B$116,4) -> 119.96219 | AA68: =SUMIFS($O$5:$O$116,$A$5:$A$116,$V68,$B$5:$B$116,5) -> 134.74088 | AB68: =SUMIFS($O$5:$O$116,$A$5:$A$116,$V68,$B$5:$B$116,6) -> 144.96864 | AC68: =SUMIFS($O$5:$O$116,$A$5:$A$116,$V68,$B$5:$B$116,7) -> 150.74499 | AD68: =SUMIFS($O$5:$O$116,$A$5:$A$116,$V68,$B$5:$B$116,8) -> 164.53244
... A70: Cash preservation | B70: 2 | C70: 198.49466 | D70: 138.17884 | E70: 40.028747 | F70: 15.998792 | G70: 4.2882824 | H70: 29.237487 | I70: =IF(C70=0,0,H70/C70) -> 0.14729609 | J70: 10 | K70: 0 | L70: 0 | M70: 99.278604 | N70: 0 | O70: 97.297876 | P70: 72 | Q70: 60 | R70: 0.25 | S70: healthy | T70: no | V70: Enterprise + AI + People | W70: =SUMIFS($O$5:$O$116,$A$5:$A$116,$V70,$B$5:$B$116,1) -> 100.07534 | X70: =SUMIFS($O$5:$O$116,$A$5:$A$116,$V70,$B$5:$B$116,2) -> 97.945766 | Y70: =SUMIFS($O$5:$O$116,$A$5:$A$116,$V70,$B$5:$B$116,3) -> 100.43551 | Z70: =SUMIFS($O$5:$O$116,$A$5:$A$116,$V70,$B$5:$B$116,4) -> 107.14846 | AA70: =SUMIFS($O$5:$O$116,$A$5:$A$116,$V70,$B$5:$B$116,5) -> 117.39619 | AB70: =SUMIFS($O$5:$O$116,$A$5:$A$116,$V70,$B$5:$B$116,6) -> 124.15883 | AC70: =SUMIFS($O$5:$O$116,$A$5:$A$116,$V70,$B$5:$B$116,7) -> 133.36866 | AD70: =SUMIFS($O$5:$O$116,$A$5:$A$116,$V70,$B$5:$B$116,8) -> 148.26927
A71: Cash preservation | B71: 3 | C71: 197.26972 | D71: 136.59398 | E71: 40.078716 | F71: 15.997945 | G71: 4.5990689 | H71: 27.743483 | I71: =IF(C71=0,0,H71/C71) -> 0.14063732 | J71: 10 | K71: 0 | L71: 0 | M71: 117.02209 | N71: 0 | O71: 96.527527 | P71: 72 | Q71: 60 | R71: 0.25 | S71: healthy | T71: no
A72: Cash preservation | B72: 4 | C72: 196.61118 | D72: 135.26015 | E72: 40.179339 | F72: 15.996736 | G72: 5.1749532 | H72: 26.878731 | I72: =IF(C72=0,0,H72/C72) -> 0.13671009 | J72: 10 | K72: 0 | L72: 0 | M72: 133.90082 | N72: 0 | O72: 96.86333 | P72: 72 | Q72: 60 | R72: 0.434175 | S72: healthy | T72: no
A73: Cash preservation | B73: 5 | C73: 196.71866 | D73: 134.326 | E73: 40.335111 | F73: 15.993013 | G73: 6.0645379 | H73: 26.660549 | I73: =IF(C73=0,0,H73/C73) -> 0.13552628 | J73: 10 | K73: 0 | L73: 0 | M73: 150.56137 | N73: 0 | O73: 98.294908 | P73: 72 | Q73: 60 | R73: 0.434175 | S73: healthy | T73: no
A74: Cash preservation | B74: 6 | C74: 195.06402 | D74: 131.71821 | E74: 40.336904 | F74: 15.973898 | G74: 7.0350014 | H74: 27.917646 | I74: =IF(C74=0,0,H74/C74) -> 0.14312043 | J74: 10 | K74: 0 | L74: 0 | M74: 168.47901 | N74: 0 | O74: 96.441074 | P74: 70.5 | Q74: 59 | R74: 0.4415339 | S74: healthy | T74: no
A75: Cash preservation | B75: 7 | C75: 194.18132 | D75: 129.24143 | E75: 40.514949 | F75: 15.94785 | G75: 8.47709 | H75: 26.584109 | I75: =IF(C75=0,0,H75/C75) -> 0.13690353 | J75: 10 | K75: 5.8164286 | L75: 0 | M75: 179.24669 | N75: 0 | O75: 95.820962 | P75: 69.524057 | Q75: 57.048114 | R75: 0.35058126 | S75: healthy | T75: no
A76: Cash preservation | B76: 8 | C76: 196.35179 | D76: 129.00819 | E76: 40.775678 | F76: 15.922167 | G76: 10.645756 | H76: 28.102658 | I76: =IF(C76=0,0,H76/C76) -> 0.14312402 | J76: 20.555556 | K76: 0 | L76: 0 | M76: 186.7938 | N76: 0 | O76: 102.81459 | P76: 69.524057 | Q76: 60.048114 | R76: 0.44297811 | S76: healthy | T76: no
A77: Adaptive (evidence-responsive) | B77: 1 | C77: 200.09855 | D77: 140.08555 | E77: 40.010446 | F77: 16.000378 | G77: 4.00218 | H77: 30.074246 | I77: =IF(C77=0,0,H77/C77) -> 0.15029717 | J77: 25 | K77: 0 | L77: 0 | M77: 65.074246 | N77: 0 | O77: 100.49545 | P77: 72 | Q77: 61.3625 | R77: 0.57038093 | S77: healthy | T77: no
A78: Adaptive (evidence-responsive) | B78: 2 | C78: 198.93269 | D78: 138.41292 | E78: 40.058006 | F78: 16.002052 | G78: 4.4597119 | H78: 29.081194 | I78: =IF(C78=0,0,H78/C78) -> 0.1461861 | J78: 30 | K78: 0 | L78: 0 | M78: 64.15544 | N78: 0 | O78: 98.700854 | P78: 72 | Q78: 63.651797 | R78: 0.59699807 | S78: healthy | T78: no
A79: Adaptive (evidence-responsive) | B79: 3 | C79: 198.95628 | D79: 137.42885 | E79: 40.17913 | F79: 16.006575 | G79: 5.341731 | H79: 27.57945 | I79: =IF(C79=0,0,H79/C79) -> 0.13862065 | J79: 30 | K79: 0 | L79: 0 | M79: 61.73489 | N79: 0 | O79: 100.65096 | P79: 72 | Q79: 66.357108 | R79: 0.5606031 | S79: healthy | T79: no
A80: Adaptive (evidence-responsive) | B80: 4 | C80: 201.05157 | D80: 137.36004 | E80: 40.418326 | F80: 16.01386 | G80: 7.2593467 | H80: 27.94324 | I80: =IF(C80=0,0,H80/C80) -> 0.13898544 | J80: 25 | K80: 0 | L80: 0 | M80: 64.678131 | N80: 0 | O80: 104.12782 | P80: 72 | Q80: 69.019323 | R80: 0.63021293 | S80: healthy | T80: no
A81: Adaptive (evidence-responsive) | B81: 5 | C81: 205.30529 | D81: 138.29259 | E81: 40.818602 | F81: 16.023789 | G81: 10.170314 | H81: 30.449025 | I81: =IF(C81=0,0,H81/C81) -> 0.14831096 | J81: 25 | K81: 8.6834162 | L81: 0 | M81: 61.44374 | N81: 0 | O81: 113.38771 | P81: 72 | Q81: 71.611894 | R81: 0.68048121 | S81: healthy | T81: no
A82: Adaptive (evidence-responsive) | B82: 6 | C82: 211.75932 | D82: 138.06839 | E82: 44.315335 | F82: 16.026978 | G82: 13.348621 | H82: 32.593425 | I82: =IF(C82=0,0,H82/C82) -> 0.15391731 | J82: 25 | K82: 0 | L82: 0 | M82: 69.037165 | N82: 0 | O82: 120.17986 | P82: 72 | Q82: 74.198545 | R82: 0.63519505 | S82: healthy | T82: no
... A116: Enterprise + AI + People | B116: 8 | C116: 233.40985 | D116: 132.04648 | E116: 55.193197 | F116: 15.907361 | G116: 30.262814 | H116: 44.191944 | I116: =IF(C116=0,0,H116/C116) -> 0.18933196 | J116: 41.25 | K116: 0 | L116: 0 | M116: 43.096898 | N116: 0 | O116: 148.26927 | P116: 72 | Q116: 80.424346 | R116: 0.41529713 | S116: healthy | T116: no

Sheet Investment & capability
A1: 3 · Investment and capability outcomes
A2: Capabilities built by Q8, the marginal return of each bucket, allocation-grid main effects and the bucket economics that drive them.
A4: A · Capability and organizational state at Q8 (start: Consumer 55, Enterprise 30, AI 10, Talent 55, Credential 40, Culture 72; capability ceiling 120)
A5: Strategy | B5: Consumer | C5: Enterprise | D5: AI | E5: Talent | F5: Credential | G5: Culture | H5: Org capacity | I5: Capability gain | J5: Consumer rev Q8 | K5: Enterprise rev Q8 | L5: University rev Q8 | M5: AI-native rev Q8 | N5: Δ Consumer rev vs Q0 | O5: Δ Enterprise rev vs Q0 | P5: Δ University rev vs Q0 | Q5: Δ AI-native rev vs Q0
A6: Consumer-led | B6: 120 | C6: 30 | D6: 11.042229 | E6: 100 | F6: 40 | G6: 72 | H6: 100 | I6: 111.04223 | J6: 151.88496 | K6: 39.542181 | L6: 15.905861 | M6: 5.0377074 | N6: =J6-140 -> 11.884958 | O6: =K6-40 -> -0.45781896 | P6: =L6-16 -> -0.094139367 | Q6: =M6-4 -> 1.0377074
A7: Enterprise-led | B7: 53 | C7: 120 | D7: 10 | E7: 84.861371 | F7: 40 | G7: 63 | H7: 86.030822 | I7: 137.08348 | J7: 126.61435 | K7: 50.102165 | L7: 15.889402 | M7: 4.9181626 | N7: =J7-140 -> -13.385651 | O7: =K7-40 -> 10.102165 | P7: =L7-16 -> -0.11059788 | Q7: =M7-4 -> 0.91816257
A8: AI-led | B8: 55 | C8: 30 | D8: 100 | E8: 99.075189 | F8: 40 | G8: 67.705829 | H8: 100 | I8: 134.07519 | J8: 140.15309 | K8: 39.370979 | L8: 15.922167 | M8: 39.253856 | N8: =J8-140 -> 0.15309239 | O8: =K8-40 -> -0.62902121 | P8: =L8-16 -> -0.077833229 | Q8: =M8-4 -> 35.253856
A9: Diversified | B9: 100 | C9: 95.94084 | D9: 86.178235 | E9: 53.5 | F9: 40 | G9: 69.451645 | H9: 59.90329 | I9: 194.49002 | J9: 141.87752 | K9: 43.797326 | L9: 15.922167 | M9: 24.622982 | N9: =J9-140 -> 1.8775167 | O9: =K9-40 -> 3.7973264 | P9: =L9-16 -> -0.077833229 | Q9: =M9-4 -> 20.622982
A10: Consumer-only | B10: 120 | C10: 30 | D10: 11.880066 | E10: 53.5 | F10: 40 | G10: 70.5 | H10: 59 | I10: 65.380066 | J10: 143.95298 | K10: 39.246379 | L10: 15.904194 | M10: 4.7896082 | N10: =J10-140 -> 3.9529786 | O10: =K10-40 -> -0.75362131 | P10: =L10-16 -> -0.095805623 | Q10: =M10-4 -> 0.78960818
A11: Enterprise-only | B11: 53 | C11: 120 | D11: 10 | E11: 45.5 | F11: 40 | G11: 61.5 | H11: 53 | I11: 106.25718 | J11: 120.68708 | K11: 51.985268 | L11: 15.888332 | M11: 4.717746 | N11: =J11-140 -> -19.312916 | O11: =K11-40 -> 11.985268 | P11: =L11-16 -> -0.11166822 | Q11: =M11-4 -> 0.71774604
A12: AI-only | B12: 58.230255 | C12: 30 | D12: 120 | E12: 53.5 | F12: 40 | G12: 70.5 | H12: 59 | I12: 111.73026 | J12: 126.57191 | K12: 39.712694 | L12: 15.908185 | M12: 38.751097 | N12: =J12-140 -> -13.428088 | O12: =K12-40 -> -0.28730559 | P12: =L12-16 -> -0.091815307 | Q12: =M12-4 -> 34.751097
A13: University-led | B13: 55 | C13: 30 | D13: 10 | E13: 100 | F13: 120 | G13: 72 | H13: 100 | I13: 125 | J13: 137.39844 | K13: 40.652857 | L13: 15.121688 | M13: 4.9911986 | N13: =J13-140 -> -2.6015564 | O13: =K13-40 -> 0.65285734 | P13: =L13-16 -> -0.87831172 | Q13: =M13-4 -> 0.99119857
A14: Cash preservation | B14: 85.885219 | C14: 55.477039 | D14: 38.649172 | E14: 53.5 | F14: 40 | G14: 69.524057 | H14: 60.048114 | I14: 84.84047 | J14: 129.00819 | K14: 40.775678 | L14: 15.922167 | M14: 10.645756 | N14: =J14-140 -> -10.991806 | O14: =K14-40 -> 0.77567781 | P14: =L14-16 -> -0.077833229 | Q14: =M14-4 -> 6.6457555
A15: Adaptive (evidence-responsive) | B15: 87.711857 | C15: 81.16835 | D15: 61.676565 | E15: 81.169485 | F15: 61.158904 | G15: 72 | H15: 79.627114 | I15: 197.82665 | J15: 142.01742 | K15: 51.660652 | L15: 16.040153 | M15: 23.63101 | N15: =J15-140 -> 2.0174174 | O15: =K15-40 -> 11.660652 | P15: =L15-16 -> 0.040152728 | Q15: =M15-4 -> 19.63101
A16: University-only | B16: 55 | C16: 30 | D16: 10 | E16: 53.5 | F16: 120 | G16: 70.5 | H16: 59 | I16: 78.5 | J16: 130.27857 | K16: 40.557616 | L16: 15.179565 | M16: 4.7577498 | N16: =J16-140 -> -9.7214257 | O16: =K16-40 -> 0.55761642 | P16: =L16-16 -> -0.82043518 | Q16: =M16-4 -> 0.75774983
A17: Consumer + AI | B17: 120 | C17: 30 | D17: 114.87958 | E17: 53.5 | F17: 40 | G17: 70.5 | H17: 59 | I17: 168.37958 | J17: 154.62878 | K17: 39.58206 | L17: 15.908672 | M17: 31.410805 | N17: =J17-140 -> 14.628781 | O17: =K17-40 -> -0.41793955 | P17: =L17-16 -> -0.091327564 | Q17: =M17-4 -> 27.410805
... A19: Enterprise + AI + People | B19: 55 | C19: 120 | D19: 92.277593 | E19: 82.232461 | F19: 40 | G19: 72 | H19: 80.424346 | I19: 224.50146 | J19: 132.04648 | K19: 55.193197 | L19: 15.907361 | M19: 30.262814 | N19: =J19-140 -> -7.953519 | O19: =K19-40 -> 15.193197 | P19: =L19-16 -> -0.092639418 | Q19: =M19-4 -> 26.262814
A21: B · Marginal return of $10M a quarter in each bucket
A22: Base: $3M in each bucket + $15M reserve; one bucket +$10M, reserve −$10M; Balanced Marketplace destination; contract declined; 12 quarters (Q9–Q12 extend the last authored market). Deltas vs the base run.
A23: Starting mix | B23: Bucket | C23: Δ Rev Q2 | D23: Δ Rev Q4 | E23: Δ Rev Q8 | F23: Δ Rev Q12 | G23: Δ Cum OP Q8 | H23: Δ Cum OP Q12 | I23: Δ Net cash Q8 | J23: Δ Price Q4 | K23: Δ Price Q8 | L23: Δ Consumer rev Q8 | M23: Δ Enterprise rev Q8 | N23: Δ University rev Q8 | O23: Δ AI-native rev Q8 | P23: Cum OP Q8 per $80M invested
A24: Baseline (production) | B24: Consumer | C24: 0.46334982 | D24: 2.2009572 | E24: 8.2863839 | F24: 10.463468 | G24: 20.212242 | H24: 45.247773 | I24: -59.958638 | J24: 4.9018674 | K24: 10.898799 | L24: 9.1434231 | M24: -0.11382962 | N24: -0.0094125942 | O24: -0.733797 | P24: =G24/80 -> 0.25265303
A25: Baseline (production) | B25: Enterprise | C25: 0.059485044 | D25: 0.28207311 | E25: 2.0446371 | F25: 5.285008 | G25: -7.3588901 | H25: -7.5747194 | I25: -87.515466 | J25: 1.0107898 | K25: 3.0797019 | L25: -0.75319853 | M25: 3.4743171 | N25: -0.0085495022 | O25: -0.66793191 | P25: =G25/80 -> -0.091986126
A26: Baseline (production) | B26: AI/Product | C26: 0.46247769 | D26: 5.690927 | E26: 25.009457 | F26: 36.783926 | G26: 44.88426 | H26: 126.40712 | I26: -35.322176 | J26: 10.758272 | K26: 30.321122 | L26: 6.2367023 | M26: 0.26345699 | N26: -0.011545213 | O26: 18.520843 | P26: =G26/80 -> 0.56105325
A27: Baseline (production) | B27: People | C27: 0.42675645 | D27: 2.0099529 | E27: 9.7097534 | F27: 22.449122 | G27: 4.621693 | H27: 34.25326 | I27: -74.984693 | J27: 2.7884606 | K27: 11.190685 | L27: 7.2217318 | M27: 0.30598168 | N27: -0.0018962096 | O27: 2.1839361 | P27: =G27/80 -> 0.057771163
A28: Baseline (production) | B28: University | C28: 0.036248703 | D28: 0.43251325 | E28: 3.6390521 | F28: 11.648347 | G28: 6.7103393 | H28: 29.041521 | I28: -73.409837 | J28: 3.0442888 | K28: 11.482374 | L28: 3.276765 | M28: 0.45990373 | N28: 0.40766567 | O28: -0.50528229 | P28: =G28/80 -> 0.083879241
A29: Alt A re-based (proportional) | B29: Consumer | C29: 0.29374163 | D29: 1.2525612 | E29: 3.5938261 | F29: 1.0717631 | G29: 8.801794 | H29: 11.057476 | I29: -71.369086 | J29: 3.5502142 | K29: 5.1371678 | L29: 6.5310165 | M29: -0.17074443 | N29: -0.014707178 | O29: -2.7517388 | P29: =G29/80 -> 0.11002243
A30: Alt A re-based (proportional) | B30: Enterprise | C30: 0.072549301 | D30: 0.27576697 | E30: 2.1553734 | F30: 5.604819 | G30: -8.1288841 | H30: -10.356478 | I30: -88.28546 | J30: 1.2850585 | K30: 3.337456 | L30: -0.53799895 | M30: 5.2114756 | N30: -0.013358597 | O30: -2.5047446 | P30: =G30/80 -> -0.10161105
A31: Alt A re-based (proportional) | B31: AI/Product | C31: 1.5911397 | D31: 16.980517 | E31: 74.285093 | F31: 108.44591 | G31: 165.32603 | H31: 441.10181 | I31: 85.119592 | J31: 25.530605 | K31: 44.939624 | L31: 4.4547873 | M31: 0.39518548 | N31: -0.018039395 | O31: 69.45316 | P31: =G31/80 -> 2.0665754
A32: Alt A re-based (proportional) | B32: People | C32: 0.45012003 | D32: 2.4503404 | E32: 13.80415 | F32: 36.304089 | G32: 11.727488 | H32: 72.278307 | I32: -67.878897 | J32: 3.3745603 | K32: 13.803551 | L32: 5.1583799 | M32: 0.45897252 | N32: -0.0029628275 | O32: 8.1897604 | P32: =G32/80 -> 0.1465936
A33: Alt A re-based (proportional) | B33: University | C33: 0.016620724 | D33: 0.19457156 | E33: 1.772571 | F33: 6.5939915 | G33: 2.6173395 | H33: 12.760033 | I33: -77.502837 | J33: 2.8516994 | K33: 9.517628 | L33: 2.3405464 | M33: 0.6898556 | N33: 0.63697761 | O33: -1.8948086 | P33: =G33/80 -> 0.032716744
A34: Alt B re-based (proportional) | B34: Consumer | C34: 0.21039299 | D34: 0.79106096 | E34: 1.3389777 | F34: -3.3762896 | G34: 3.8929881 | H34: -4.2192074 | I34: -76.277892 | J34: 2.9418062 | K34: 3.1635853 | L34: 5.2248132 | M34: -0.19920183 | N34: -0.017648614 | O34: -3.668985 | P34: =G34/80 -> 0.048662352
A35: Alt B re-based (proportional) | B35: Enterprise | C35: 0.080402025 | D35: 0.28412617 | E35: 2.2939658 | F35: 5.9897205 | G35: -8.2202801 | H35: -10.786389 | I35: -88.376856 | J35: 1.4390783 | K35: 2.6968267 | L35: -0.43039916 | M35: 6.0800548 | N35: -0.016030317 | O35: -3.3396595 | P35: =G35/80 -> -0.1027535
... A48: Alt B re-based (AI reward fixed) | B48: University | C48: 0.036475896 | D48: 0.33856336 | E48: 2.7809991 | F48: 9.3678093 | G48: 4.7646777 | H48: 21.720737 | I48: -75.355498 | J48: 3.1481836 | K48: 10.420759 | L48: 1.8724371 | M48: 0.80483153 | N48: 0.76437313 | O48: -0.66064274 | P48: =G48/80 -> 0.059558472
A50: C · Allocation-grid main effects (AVERAGEIFS over the Allocation grid, best destination per allocation)
A51: Average Q8 outcome of all allocations that put the given amount in the bucket. Reads as: how much does a bucket help on average, whatever else is funded.
A52: Mean Q8 share price ($) | B52: $0M | C52: $5M | D52: $10M | E52: $15M | F52: $20M | G52: $25M | H52: $30M
A53: Consumer | B53: =AVERAGEIFS('Allocation grid'!$N$5:$N$2314,'Allocation grid'!$A$5:$A$2314,0,'Allocation grid'!$S$5:$S$2314,1) -> 121.0951 | C53: =AVERAGEIFS('Allocation grid'!$N$5:$N$2314,'Allocation grid'!$A$5:$A$2314,5,'Allocation grid'!$S$5:$S$2314,1) -> 129.93681 | D53: =AVERAGEIFS('Allocation grid'!$N$5:$N$2314,'Allocation grid'!$A$5:$A$2314,10,'Allocation grid'!$S$5:$S$2314,1) -> 133.56589 | E53: =AVERAGEIFS('Allocation grid'!$N$5:$N$2314,'Allocation grid'!$A$5:$A$2314,15,'Allocation grid'!$S$5:$S$2314,1) -> 130.95957 | F53: =AVERAGEIFS('Allocation grid'!$N$5:$N$2314,'Allocation grid'!$A$5:$A$2314,20,'Allocation grid'!$S$5:$S$2314,1) -> 126.80673 | G53: =AVERAGEIFS('Allocation grid'!$N$5:$N$2314,'Allocation grid'!$A$5:$A$2314,25,'Allocation grid'!$S$5:$S$2314,1) -> 118.76919 | H53: =AVERAGEIFS('Allocation grid'!$N$5:$N$2314,'Allocation grid'!$A$5:$A$2314,30,'Allocation grid'!$S$5:$S$2314,1) -> 109.88221
A54: Enterprise | B54: =AVERAGEIFS('Allocation grid'!$N$5:$N$2314,'Allocation grid'!$B$5:$B$2314,0,'Allocation grid'!$S$5:$S$2314,1) -> 130.49344 | C54: =AVERAGEIFS('Allocation grid'!$N$5:$N$2314,'Allocation grid'!$B$5:$B$2314,5,'Allocation grid'!$S$5:$S$2314,1) -> 127.02758 | D54: =AVERAGEIFS('Allocation grid'!$N$5:$N$2314,'Allocation grid'!$B$5:$B$2314,10,'Allocation grid'!$S$5:$S$2314,1) -> 124.23204 | E54: =AVERAGEIFS('Allocation grid'!$N$5:$N$2314,'Allocation grid'!$B$5:$B$2314,15,'Allocation grid'!$S$5:$S$2314,1) -> 116.45127 | F54: =AVERAGEIFS('Allocation grid'!$N$5:$N$2314,'Allocation grid'!$B$5:$B$2314,20,'Allocation grid'!$S$5:$S$2314,1) -> 107.7519 | G54: =AVERAGEIFS('Allocation grid'!$N$5:$N$2314,'Allocation grid'!$B$5:$B$2314,25,'Allocation grid'!$S$5:$S$2314,1) -> 91.883098 | H54: =AVERAGEIFS('Allocation grid'!$N$5:$N$2314,'Allocation grid'!$B$5:$B$2314,30,'Allocation grid'!$S$5:$S$2314,1) -> 84.20773
A55: AI/Product | B55: =AVERAGEIFS('Allocation grid'!$N$5:$N$2314,'Allocation grid'!$C$5:$C$2314,0,'Allocation grid'!$S$5:$S$2314,1) -> 105.98367 | C55: =AVERAGEIFS('Allocation grid'!$N$5:$N$2314,'Allocation grid'!$C$5:$C$2314,5,'Allocation grid'!$S$5:$S$2314,1) -> 137.17575 | D55: =AVERAGEIFS('Allocation grid'!$N$5:$N$2314,'Allocation grid'!$C$5:$C$2314,10,'Allocation grid'!$S$5:$S$2314,1) -> 150.71157 | E55: =AVERAGEIFS('Allocation grid'!$N$5:$N$2314,'Allocation grid'!$C$5:$C$2314,15,'Allocation grid'!$S$5:$S$2314,1) -> 149.9526 | F55: =AVERAGEIFS('Allocation grid'!$N$5:$N$2314,'Allocation grid'!$C$5:$C$2314,20,'Allocation grid'!$S$5:$S$2314,1) -> 145.69436 | G55: =AVERAGEIFS('Allocation grid'!$N$5:$N$2314,'Allocation grid'!$C$5:$C$2314,25,'Allocation grid'!$S$5:$S$2314,1) -> 137.89884 | H55: =AVERAGEIFS('Allocation grid'!$N$5:$N$2314,'Allocation grid'!$C$5:$C$2314,30,'Allocation grid'!$S$5:$S$2314,1) -> 127.25922
A56: People | B56: =AVERAGEIFS('Allocation grid'!$N$5:$N$2314,'Allocation grid'!$D$5:$D$2314,0,'Allocation grid'!$S$5:$S$2314,1) -> 127.95337 | C56: =AVERAGEIFS('Allocation grid'!$N$5:$N$2314,'Allocation grid'!$D$5:$D$2314,5,'Allocation grid'!$S$5:$S$2314,1) -> 128.73175 | D56: =AVERAGEIFS('Allocation grid'!$N$5:$N$2314,'Allocation grid'!$D$5:$D$2314,10,'Allocation grid'!$S$5:$S$2314,1) -> 126.88302 | E56: =AVERAGEIFS('Allocation grid'!$N$5:$N$2314,'Allocation grid'!$D$5:$D$2314,15,'Allocation grid'!$S$5:$S$2314,1) -> 119.61683 | F56: =AVERAGEIFS('Allocation grid'!$N$5:$N$2314,'Allocation grid'!$D$5:$D$2314,20,'Allocation grid'!$S$5:$S$2314,1) -> 109.31948 | G56: =AVERAGEIFS('Allocation grid'!$N$5:$N$2314,'Allocation grid'!$D$5:$D$2314,25,'Allocation grid'!$S$5:$S$2314,1) -> 93.679089 | H56: =AVERAGEIFS('Allocation grid'!$N$5:$N$2314,'Allocation grid'!$D$5:$D$2314,30,'Allocation grid'!$S$5:$S$2314,1) -> 74.038612
A57: University | B57: =AVERAGEIFS('Allocation grid'!$N$5:$N$2314,'Allocation grid'!$E$5:$E$2314,0,'Allocation grid'!$S$5:$S$2314,1) -> 125.20343 | C57: =AVERAGEIFS('Allocation grid'!$N$5:$N$2314,'Allocation grid'!$E$5:$E$2314,5,'Allocation grid'!$S$5:$S$2314,1) -> 126.47059 | D57: =AVERAGEIFS('Allocation grid'!$N$5:$N$2314,'Allocation grid'!$E$5:$E$2314,10,'Allocation grid'!$S$5:$S$2314,1) -> 129.73337 | E57: =AVERAGEIFS('Allocation grid'!$N$5:$N$2314,'Allocation grid'!$E$5:$E$2314,15,'Allocation grid'!$S$5:$S$2314,1) -> 127.25571 | F57: =AVERAGEIFS('Allocation grid'!$N$5:$N$2314,'Allocation grid'!$E$5:$E$2314,20,'Allocation grid'!$S$5:$S$2314,1) -> 125.27368 | G57: =AVERAGEIFS('Allocation grid'!$N$5:$N$2314,'Allocation grid'!$E$5:$E$2314,25,'Allocation grid'!$S$5:$S$2314,1) -> 117.50428 | H57: =AVERAGEIFS('Allocation grid'!$N$5:$N$2314,'Allocation grid'!$E$5:$E$2314,30,'Allocation grid'!$S$5:$S$2314,1) -> 111.10786
A58: Reserve | B58: =AVERAGEIFS('Allocation grid'!$N$5:$N$2314,'Allocation grid'!$F$5:$F$2314,0,'Allocation grid'!$S$5:$S$2314,1) -> 131.87956 | C58: =AVERAGEIFS('Allocation grid'!$N$5:$N$2314,'Allocation grid'!$F$5:$F$2314,5,'Allocation grid'!$S$5:$S$2314,1) -> 128.8268 | D58: =AVERAGEIFS('Allocation grid'!$N$5:$N$2314,'Allocation grid'!$F$5:$F$2314,10,'Allocation grid'!$S$5:$S$2314,1) -> 121.55516 | E58: =AVERAGEIFS('Allocation grid'!$N$5:$N$2314,'Allocation grid'!$F$5:$F$2314,15,'Allocation grid'!$S$5:$S$2314,1) -> 111.61985 | F58: =AVERAGEIFS('Allocation grid'!$N$5:$N$2314,'Allocation grid'!$F$5:$F$2314,20,'Allocation grid'!$S$5:$S$2314,1) -> 99.545539 | G58: =AVERAGEIFS('Allocation grid'!$N$5:$N$2314,'Allocation grid'!$F$5:$F$2314,25,'Allocation grid'!$S$5:$S$2314,1) -> 86.327582 | H58: =AVERAGEIFS('Allocation grid'!$N$5:$N$2314,'Allocation grid'!$F$5:$F$2314,30,'Allocation grid'!$S$5:$S$2314,1) -> 73.774379
A60: Mean terminal score | B60: $0M | C60: $5M | D60: $10M | E60: $15M | F60: $20M | G60: $25M | H60: $30M
A61: Consumer | B61: =AVERAGEIFS('Allocation grid'!$O$5:$O$2314,'Allocation grid'!$A$5:$A$2314,0,'Allocation grid'!$S$5:$S$2314,1) -> 69.190673 | C61: =AVERAGEIFS('Allocation grid'!$O$5:$O$2314,'Allocation grid'!$A$5:$A$2314,5,'Allocation grid'!$S$5:$S$2314,1) -> 71.924578 | D61: =AVERAGEIFS('Allocation grid'!$O$5:$O$2314,'Allocation grid'!$A$5:$A$2314,10,'Allocation grid'!$S$5:$S$2314,1) -> 73.009318 | E61: =AVERAGEIFS('Allocation grid'!$O$5:$O$2314,'Allocation grid'!$A$5:$A$2314,15,'Allocation grid'!$S$5:$S$2314,1) -> 71.500222 | F61: =AVERAGEIFS('Allocation grid'!$O$5:$O$2314,'Allocation grid'!$A$5:$A$2314,20,'Allocation grid'!$S$5:$S$2314,1) -> 69.166677 | G61: =AVERAGEIFS('Allocation grid'!$O$5:$O$2314,'Allocation grid'!$A$5:$A$2314,25,'Allocation grid'!$S$5:$S$2314,1) -> 65.722984 | H61: =AVERAGEIFS('Allocation grid'!$O$5:$O$2314,'Allocation grid'!$A$5:$A$2314,30,'Allocation grid'!$S$5:$S$2314,1) -> 61.803585
A62: Enterprise | B62: =AVERAGEIFS('Allocation grid'!$O$5:$O$2314,'Allocation grid'!$B$5:$B$2314,0,'Allocation grid'!$S$5:$S$2314,1) -> 72.385926 | C62: =AVERAGEIFS('Allocation grid'!$O$5:$O$2314,'Allocation grid'!$B$5:$B$2314,5,'Allocation grid'!$S$5:$S$2314,1) -> 70.958043 | D62: =AVERAGEIFS('Allocation grid'!$O$5:$O$2314,'Allocation grid'!$B$5:$B$2314,10,'Allocation grid'!$S$5:$S$2314,1) -> 70.05645 | E62: =AVERAGEIFS('Allocation grid'!$O$5:$O$2314,'Allocation grid'!$B$5:$B$2314,15,'Allocation grid'!$S$5:$S$2314,1) -> 66.852599 | F62: =AVERAGEIFS('Allocation grid'!$O$5:$O$2314,'Allocation grid'!$B$5:$B$2314,20,'Allocation grid'!$S$5:$S$2314,1) -> 61.587446 | G62: =AVERAGEIFS('Allocation grid'!$O$5:$O$2314,'Allocation grid'!$B$5:$B$2314,25,'Allocation grid'!$S$5:$S$2314,1) -> 55.138843 | H62: =AVERAGEIFS('Allocation grid'!$O$5:$O$2314,'Allocation grid'!$B$5:$B$2314,30,'Allocation grid'!$S$5:$S$2314,1) -> 48.560902
A63: AI/Product | B63: =AVERAGEIFS('Allocation grid'!$O$5:$O$2314,'Allocation grid'!$C$5:$C$2314,0,'Allocation grid'!$S$5:$S$2314,1) -> 63.489459 | C63: =AVERAGEIFS('Allocation grid'!$O$5:$O$2314,'Allocation grid'!$C$5:$C$2314,5,'Allocation grid'!$S$5:$S$2314,1) -> 74.640886 | D63: =AVERAGEIFS('Allocation grid'!$O$5:$O$2314,'Allocation grid'!$C$5:$C$2314,10,'Allocation grid'!$S$5:$S$2314,1) -> 79.250464 | E63: =AVERAGEIFS('Allocation grid'!$O$5:$O$2314,'Allocation grid'!$C$5:$C$2314,15,'Allocation grid'!$S$5:$S$2314,1) -> 78.718087 | F63: =AVERAGEIFS('Allocation grid'!$O$5:$O$2314,'Allocation grid'!$C$5:$C$2314,20,'Allocation grid'!$S$5:$S$2314,1) -> 77.017628 | G63: =AVERAGEIFS('Allocation grid'!$O$5:$O$2314,'Allocation grid'!$C$5:$C$2314,25,'Allocation grid'!$S$5:$S$2314,1) -> 73.777626 | H63: =AVERAGEIFS('Allocation grid'!$O$5:$O$2314,'Allocation grid'!$C$5:$C$2314,30,'Allocation grid'!$S$5:$S$2314,1) -> 69.260958
A64: People | B64: =AVERAGEIFS('Allocation grid'!$O$5:$O$2314,'Allocation grid'!$D$5:$D$2314,0,'Allocation grid'!$S$5:$S$2314,1) -> 69.328728 | C64: =AVERAGEIFS('Allocation grid'!$O$5:$O$2314,'Allocation grid'!$D$5:$D$2314,5,'Allocation grid'!$S$5:$S$2314,1) -> 72.83966 | D64: =AVERAGEIFS('Allocation grid'!$O$5:$O$2314,'Allocation grid'!$D$5:$D$2314,10,'Allocation grid'!$S$5:$S$2314,1) -> 72.757098 | E64: =AVERAGEIFS('Allocation grid'!$O$5:$O$2314,'Allocation grid'!$D$5:$D$2314,15,'Allocation grid'!$S$5:$S$2314,1) -> 70.096301 | F64: =AVERAGEIFS('Allocation grid'!$O$5:$O$2314,'Allocation grid'!$D$5:$D$2314,20,'Allocation grid'!$S$5:$S$2314,1) -> 66.253148 | G64: =AVERAGEIFS('Allocation grid'!$O$5:$O$2314,'Allocation grid'!$D$5:$D$2314,25,'Allocation grid'!$S$5:$S$2314,1) -> 60.565663 | H64: =AVERAGEIFS('Allocation grid'!$O$5:$O$2314,'Allocation grid'!$D$5:$D$2314,30,'Allocation grid'!$S$5:$S$2314,1) -> 53.79412
A65: University | B65: =AVERAGEIFS('Allocation grid'!$O$5:$O$2314,'Allocation grid'!$E$5:$E$2314,0,'Allocation grid'!$S$5:$S$2314,1) -> 71.447828 | C65: =AVERAGEIFS('Allocation grid'!$O$5:$O$2314,'Allocation grid'!$E$5:$E$2314,5,'Allocation grid'!$S$5:$S$2314,1) -> 70.85665 | D65: =AVERAGEIFS('Allocation grid'!$O$5:$O$2314,'Allocation grid'!$E$5:$E$2314,10,'Allocation grid'!$S$5:$S$2314,1) -> 70.369009 | E65: =AVERAGEIFS('Allocation grid'!$O$5:$O$2314,'Allocation grid'!$E$5:$E$2314,15,'Allocation grid'!$S$5:$S$2314,1) -> 68.5972 | F65: =AVERAGEIFS('Allocation grid'!$O$5:$O$2314,'Allocation grid'!$E$5:$E$2314,20,'Allocation grid'!$S$5:$S$2314,1) -> 66.637431 | G65: =AVERAGEIFS('Allocation grid'!$O$5:$O$2314,'Allocation grid'!$E$5:$E$2314,25,'Allocation grid'!$S$5:$S$2314,1) -> 62.891388 | H65: =AVERAGEIFS('Allocation grid'!$O$5:$O$2314,'Allocation grid'!$E$5:$E$2314,30,'Allocation grid'!$S$5:$S$2314,1) -> 60.884119
A66: Reserve | B66: =AVERAGEIFS('Allocation grid'!$O$5:$O$2314,'Allocation grid'!$F$5:$F$2314,0,'Allocation grid'!$S$5:$S$2314,1) -> 71.451475 | C66: =AVERAGEIFS('Allocation grid'!$O$5:$O$2314,'Allocation grid'!$F$5:$F$2314,5,'Allocation grid'!$S$5:$S$2314,1) -> 71.624521 | D66: =AVERAGEIFS('Allocation grid'!$O$5:$O$2314,'Allocation grid'!$F$5:$F$2314,10,'Allocation grid'!$S$5:$S$2314,1) -> 70.342287 | E66: =AVERAGEIFS('Allocation grid'!$O$5:$O$2314,'Allocation grid'!$F$5:$F$2314,15,'Allocation grid'!$S$5:$S$2314,1) -> 67.909263 | F66: =AVERAGEIFS('Allocation grid'!$O$5:$O$2314,'Allocation grid'!$F$5:$F$2314,20,'Allocation grid'!$S$5:$S$2314,1) -> 63.9138 | G66: =AVERAGEIFS('Allocation grid'!$O$5:$O$2314,'Allocation grid'!$F$5:$F$2314,25,'Allocation grid'!$S$5:$S$2314,1) -> 58.565613 | H66: =AVERAGEIFS('Allocation grid'!$O$5:$O$2314,'Allocation grid'!$F$5:$F$2314,30,'Allocation grid'!$S$5:$S$2314,1) -> 51.798239
A68: Mean Q8 revenue ($M) | B68: $0M | C68: $5M | D68: $10M | E68: $15M | F68: $20M | G68: $25M | H68: $30M
A69: Consumer | B69: =AVERAGEIFS('Allocation grid'!$J$5:$J$2314,'Allocation grid'!$A$5:$A$2314,0,'Allocation grid'!$S$5:$S$2314,1) -> 210.09771 | C69: =AVERAGEIFS('Allocation grid'!$J$5:$J$2314,'Allocation grid'!$A$5:$A$2314,5,'Allocation grid'!$S$5:$S$2314,1) -> 215.41588 | D69: =AVERAGEIFS('Allocation grid'!$J$5:$J$2314,'Allocation grid'!$A$5:$A$2314,10,'Allocation grid'!$S$5:$S$2314,1) -> 217.95377 | E69: =AVERAGEIFS('Allocation grid'!$J$5:$J$2314,'Allocation grid'!$A$5:$A$2314,15,'Allocation grid'!$S$5:$S$2314,1) -> 216.77039 | F69: =AVERAGEIFS('Allocation grid'!$J$5:$J$2314,'Allocation grid'!$A$5:$A$2314,20,'Allocation grid'!$S$5:$S$2314,1) -> 214.72344 | G69: =AVERAGEIFS('Allocation grid'!$J$5:$J$2314,'Allocation grid'!$A$5:$A$2314,25,'Allocation grid'!$S$5:$S$2314,1) -> 209.47428 | H69: =AVERAGEIFS('Allocation grid'!$J$5:$J$2314,'Allocation grid'!$A$5:$A$2314,30,'Allocation grid'!$S$5:$S$2314,1) -> 203.89316
A70: Enterprise | B70: =AVERAGEIFS('Allocation grid'!$J$5:$J$2314,'Allocation grid'!$B$5:$B$2314,0,'Allocation grid'!$S$5:$S$2314,1) -> 214.73841 | C70: =AVERAGEIFS('Allocation grid'!$J$5:$J$2314,'Allocation grid'!$B$5:$B$2314,5,'Allocation grid'!$S$5:$S$2314,1) -> 213.02735 | D70: =AVERAGEIFS('Allocation grid'!$J$5:$J$2314,'Allocation grid'!$B$5:$B$2314,10,'Allocation grid'!$S$5:$S$2314,1) -> 213.89259 | E70: =AVERAGEIFS('Allocation grid'!$J$5:$J$2314,'Allocation grid'!$B$5:$B$2314,15,'Allocation grid'!$S$5:$S$2314,1) -> 210.80349 | F70: =AVERAGEIFS('Allocation grid'!$J$5:$J$2314,'Allocation grid'!$B$5:$B$2314,20,'Allocation grid'!$S$5:$S$2314,1) -> 206.68447 | G70: =AVERAGEIFS('Allocation grid'!$J$5:$J$2314,'Allocation grid'!$B$5:$B$2314,25,'Allocation grid'!$S$5:$S$2314,1) -> 199.66442 | H70: =AVERAGEIFS('Allocation grid'!$J$5:$J$2314,'Allocation grid'!$B$5:$B$2314,30,'Allocation grid'!$S$5:$S$2314,1) -> 193.05917
A71: AI/Product | B71: =AVERAGEIFS('Allocation grid'!$J$5:$J$2314,'Allocation grid'!$C$5:$C$2314,0,'Allocation grid'!$S$5:$S$2314,1) -> 199.82784 | C71: =AVERAGEIFS('Allocation grid'!$J$5:$J$2314,'Allocation grid'!$C$5:$C$2314,5,'Allocation grid'!$S$5:$S$2314,1) -> 218.69144 | D71: =AVERAGEIFS('Allocation grid'!$J$5:$J$2314,'Allocation grid'!$C$5:$C$2314,10,'Allocation grid'!$S$5:$S$2314,1) -> 230.42704 | E71: =AVERAGEIFS('Allocation grid'!$J$5:$J$2314,'Allocation grid'!$C$5:$C$2314,15,'Allocation grid'!$S$5:$S$2314,1) -> 231.74402 | F71: =AVERAGEIFS('Allocation grid'!$J$5:$J$2314,'Allocation grid'!$C$5:$C$2314,20,'Allocation grid'!$S$5:$S$2314,1) -> 230.79435 | G71: =AVERAGEIFS('Allocation grid'!$J$5:$J$2314,'Allocation grid'!$C$5:$C$2314,25,'Allocation grid'!$S$5:$S$2314,1) -> 227.20098 | H71: =AVERAGEIFS('Allocation grid'!$J$5:$J$2314,'Allocation grid'!$C$5:$C$2314,30,'Allocation grid'!$S$5:$S$2314,1) -> 220.94389
A72: People | B72: =AVERAGEIFS('Allocation grid'!$J$5:$J$2314,'Allocation grid'!$D$5:$D$2314,0,'Allocation grid'!$S$5:$S$2314,1) -> 212.22811 | C72: =AVERAGEIFS('Allocation grid'!$J$5:$J$2314,'Allocation grid'!$D$5:$D$2314,5,'Allocation grid'!$S$5:$S$2314,1) -> 215.65901 | D72: =AVERAGEIFS('Allocation grid'!$J$5:$J$2314,'Allocation grid'!$D$5:$D$2314,10,'Allocation grid'!$S$5:$S$2314,1) -> 215.51959 | E72: =AVERAGEIFS('Allocation grid'!$J$5:$J$2314,'Allocation grid'!$D$5:$D$2314,15,'Allocation grid'!$S$5:$S$2314,1) -> 212.23881 | F72: =AVERAGEIFS('Allocation grid'!$J$5:$J$2314,'Allocation grid'!$D$5:$D$2314,20,'Allocation grid'!$S$5:$S$2314,1) -> 208.48942 | G72: =AVERAGEIFS('Allocation grid'!$J$5:$J$2314,'Allocation grid'!$D$5:$D$2314,25,'Allocation grid'!$S$5:$S$2314,1) -> 200.44225 | H72: =AVERAGEIFS('Allocation grid'!$J$5:$J$2314,'Allocation grid'!$D$5:$D$2314,30,'Allocation grid'!$S$5:$S$2314,1) -> 193.54277
A73: University | B73: =AVERAGEIFS('Allocation grid'!$J$5:$J$2314,'Allocation grid'!$E$5:$E$2314,0,'Allocation grid'!$S$5:$S$2314,1) -> 216.40201 | C73: =AVERAGEIFS('Allocation grid'!$J$5:$J$2314,'Allocation grid'!$E$5:$E$2314,5,'Allocation grid'!$S$5:$S$2314,1) -> 214.22216 | D73: =AVERAGEIFS('Allocation grid'!$J$5:$J$2314,'Allocation grid'!$E$5:$E$2314,10,'Allocation grid'!$S$5:$S$2314,1) -> 210.42329 | E73: =AVERAGEIFS('Allocation grid'!$J$5:$J$2314,'Allocation grid'!$E$5:$E$2314,15,'Allocation grid'!$S$5:$S$2314,1) -> 206.05956 | F73: =AVERAGEIFS('Allocation grid'!$J$5:$J$2314,'Allocation grid'!$E$5:$E$2314,20,'Allocation grid'!$S$5:$S$2314,1) -> 201.95084 | G73: =AVERAGEIFS('Allocation grid'!$J$5:$J$2314,'Allocation grid'!$E$5:$E$2314,25,'Allocation grid'!$S$5:$S$2314,1) -> 196.12006 | H73: =AVERAGEIFS('Allocation grid'!$J$5:$J$2314,'Allocation grid'!$E$5:$E$2314,30,'Allocation grid'!$S$5:$S$2314,1) -> 190.77351
A74: Reserve | B74: =AVERAGEIFS('Allocation grid'!$J$5:$J$2314,'Allocation grid'!$F$5:$F$2314,0,'Allocation grid'!$S$5:$S$2314,1) -> 218.5352 | C74: =AVERAGEIFS('Allocation grid'!$J$5:$J$2314,'Allocation grid'!$F$5:$F$2314,5,'Allocation grid'!$S$5:$S$2314,1) -> 214.53397 | D74: =AVERAGEIFS('Allocation grid'!$J$5:$J$2314,'Allocation grid'!$F$5:$F$2314,10,'Allocation grid'!$S$5:$S$2314,1) -> 208.67728 | E74: =AVERAGEIFS('Allocation grid'!$J$5:$J$2314,'Allocation grid'!$F$5:$F$2314,15,'Allocation grid'!$S$5:$S$2314,1) -> 201.44753 | F74: =AVERAGEIFS('Allocation grid'!$J$5:$J$2314,'Allocation grid'!$F$5:$F$2314,20,'Allocation grid'!$S$5:$S$2314,1) -> 192.61705 | G74: =AVERAGEIFS('Allocation grid'!$J$5:$J$2314,'Allocation grid'!$F$5:$F$2314,25,'Allocation grid'!$S$5:$S$2314,1) -> 185.49262 | H74: =AVERAGEIFS('Allocation grid'!$J$5:$J$2314,'Allocation grid'!$F$5:$F$2314,30,'Allocation grid'!$S$5:$S$2314,1) -> 180.29984
A76: D · Bucket economics in the frozen engine (constants from src/simulation; for reference)
A77: Bucket | B77: Gain at $30M (pts) | C77: Secondary gains at $30M | D77: Maturation (in-quarter / +1 / +2) | E77: Transformation load at $30M | F77: Recurring cost commitment | G77: Commitment duration | H77: Revenue channel
A78: Consumer | B78: 17 | C78: — | D78: 50% / 35% / 15% | E78: 28 | F78: none | G78: — | H78: Retention and CAC on the $140M base (70% of revenue); acquisition
A79: Enterprise | B79: 21 | C79: Customer Success +5 | D79: 25% / 45% / 30% | E79: 26 | F79: 4% of investment per quarter | G79: 6 quarters | H79: Pipeline inflow and win rate → bookings (ACV ÷ 4) recognized 25/50/25% over the next three quarters
A80: AI/Product | B80: 27 | C80: Product Quality +2 | D80: 20% / 40% / 40% | E80: 32 | F80: 6% of investment per quarter | G80: 6 quarters | H80: AI adoption → new AI-native monetization every quarter ($0.08M per adoption point above 10); retention and pricing synergies
A81: People | B81: 13 | C81: Org capacity +12, Product Quality +4 | D81: 50% / 35% / 15% | E81: 16 | F81: 6% of investment per quarter | G81: 8 quarters | H81: Indirect: capacity, absorption, AI readiness support
A82: University/Credentials | B82: 17 | C82: Trust +2.5 | D82: 20% / 40% / 40% | E82: 22 | F82: none | G82: — | H82: University pipeline (resolution 20%) → wins recognized 10/30/30/30% from Q+2 to Q+5; credential-network spillovers

Sheet Starting revenue distribution
A1: 4 · Starting revenue distribution comparison
A2: Experimental only — production economics unchanged. Total revenue stays $200M in every mix.
A4: A · The three mixes
A5: Mix | B5: Consumer | C5: Enterprise | D5: University | E5: AI-native | F5: Total | G5: Consumer share
A6: Baseline (production) | B6: 140 | C6: 40 | D6: 16 | E6: 4 | F6: =SUM(B6:E6) -> 200 | G6: =B6/F6 -> 0.7
A7: Alternative A | B7: 100 | C7: 60 | D7: 25 | E7: 15 | F7: =SUM(B7:E7) -> 200 | G7: =B7/F7 -> 0.5
A8: Alternative B | B8: 80 | C8: 70 | D8: 30 | E8: 20 | F8: =SUM(B8:E8) -> 200 | G8: =B8/F8 -> 0.4
A10: B · Does the engine support changing the starting segment revenues? — No, not by itself
A11: Steady-state test: no investment, neutral market, three quarters. A valid opening barely moves (baseline drifts −$0.4M). “Naive” changes only the four revenues; “re-based” also changes the constants below.
A12: Variant | B12: Segment | C12: Q0 | D12: Q3 | E12: Drift
A13: baseline | B13: consumer | C13: 140 | D13: 139.62819 | E13: =D13-C13 -> -0.37180774
A14: baseline | B14: enterprise | C14: 40 | D14: 39.995783 | E14: =D14-C14 -> -0.0042173721
A15: baseline | B15: university | C15: 16 | D15: 15.997146 | E15: =D15-C15 -> -0.0028544559
A16: baseline | B16: aiNative | C16: 4 | D16: 4 | E16: =D16-C16 -> 0
A17: baseline | B17: operating profit | C17: 30 | D17: 29.719319 | E17: =D17-C17 -> -0.28068089
A18: altA:naive | B18: consumer | C18: 100 | D18: 108.9641 | E18: =D18-C18 -> 8.9641032
A19: altA:naive | B19: enterprise | C19: 60 | D19: 57.462157 | E19: =D19-C19 -> -2.5378432
A20: altA:naive | B20: university | C20: 25 | D20: 24.322333 | E20: =D20-C20 -> -0.67766686
A21: altA:naive | B21: aiNative | C21: 15 | D21: 11.879137 | E21: =D21-C21 -> -3.1208631
A22: altA:naive | B22: operating profit | C22: 30 | D22: 34.191792 | E22: =D22-C22 -> 4.1917916
A23: altA:rebased | B23: consumer | C23: 100 | D23: 99.734423 | E23: =D23-C23 -> -0.26557696
A24: altA:rebased | B24: enterprise | C24: 60 | D24: 59.993674 | E24: =D24-C24 -> -0.0063260581
... A47: altB:rebased-aifixed | B47: operating profit | C47: 30 | D47: 29.834983 | E47: =D47-C47 -> -0.16501653
A49: C · Initial conditions that must change with the mix (proportional re-base)
A50: Each flow is calibrated so the starting company is a fixed point. Re-basing scales each segment’s flows by (new revenue ÷ baseline revenue).
A51: Constant (source) | B51: Baseline | C51: Alt A | D51: Alt B | E51: Why it must change
A52: Headroom anchor = starting segment revenue (revenue.start) | B52: 140 / 40 / 16 / 4 | C52: 100 / 60 / 25 / 15 | D52: 80 / 70 / 30 / 20 | E52: Headroom multiplier is 1 only at the anchor; otherwise growth is distorted from Q1
A53: Consumer base acquisition $M/q (revenue.consumer.baseAcquisition) | B53: 6.3 | C53: 4.5 | D53: 3.6 | E53: Must equal baseline churn (base × 30% × 15%)
A54: Consumer acquisition spend $M/q (costs.variable) | B54: 6.3 | C54: 4.5 | D54: 3.6 | E54: Marketing spend scales with the consumer base
A55: AI-native monetization to baseline $M/pt (revenue.aiNative) | B55: 0.04 | C55: 0.15 | D55: 0.2 | E55: Must replace AI-native churn at starting adoption
A56: AI-native monetization above baseline $M/pt (revenue.aiNative) | B56: 0.08 | C56: 0.30 (proportional) or 0.08 (AI reward fixed) | D56: 0.40 (proportional) or 0.08 (AI reward fixed) | E56: A choice, not a requirement: whether the AI growth reward scales with the AI base. Both variants are reported.
A57: Enterprise pipeline base inflow $M/q (commercial.enterprise.baseInflow) | B57: 24 | C57: 36 | D57: 42 | E57: Bookings must replace enterprise churn
A58: Enterprise starting pipeline $M (commercial start) | B58: 80 | C58: 120 | D58: 140 | E58: Pipeline stock at steady state
A59: University pipeline base inflow $M/q (commercial.university.baseInflow) | B59: 4.8 | C59: 7.5 | D59: 9 | E59: Wins must replace university churn
A60: University starting pipeline $M (commercial start; also the adoption anchor) | B60: 24 | C60: 37.5 | D60: 45 | E60: Pipeline stock; credential-network anchor
A61: Enterprise and University backlogs (state) | B61: steady state | C61: recomputed | D61: recomputed | E61: Contracted-not-live revenue consistent with the new churn
A62: Fixed/semi-fixed cost pool $M/q (state.costs) | B62: 115.45 | C62: 119.625 | D62: 121.6875 | E62: Keeps Q0 operating cost at $170M (profit $30M). Consumer carries the highest servicing rate (25.5%), so a naive mix raises Q0 profit by $2–4M.
A63: Segment capacity (market) | B63: 300 / 120→135 / 40 / 80→150 | C63: × 0.71 / × 1.5 / × 1.56 / × 3.75 | D63: × 0.57 / × 1.75 / × 1.88 / × 5 | E63: Keeps the starting market-fill ratio; University capacity 40 would otherwise bind at $30M
A64: Capabilities, culture, trust, cash and competitor benchmarks are held at production values to isolate the revenue-mix effect.
A66: D · Results by mix
A67: Share price from the experiment’s own starting point (=100 × P8 ÷ P0). Ranks are formulas within each variant.
A68: Q8 share price (from own start, $) | B68: Baseline | C68: A naive | D68: A re-based | E68: A re-based, AI fixed | F68: B naive | G68: B re-based | H68: B re-based, AI fixed
A69: Consumer-led | B69: 116.21624 | C69: 119.92112 | D69: 114.96628 | E69: 114.89392 | F69: 121.84493 | G69: 113.76836 | H69: 113.66428
A70: Enterprise-led | B70: 81.785813 | C70: 97.576245 | D70: 106.15424 | E70: 106.15424 | F70: 107.43901 | G70: 112.99907 | H70: 112.57256
A71: AI-led | B71: 148.51302 | C71: 151.43923 | D71: 182.11249 | E71: 155.57462 | F71: 152.99667 | G71: 180.85163 | H71: 157.37683
A72: Diversified | B72: 143.75331 | C72: 147.74677 | D72: 180.69797 | E72: 149.72772 | F72: 149.76817 | G72: 179.74752 | H72: 151.78518
A73: Consumer-only | B73: 109.88221 | C73: 114.41821 | D73: 110.21676 | E73: 110.21676 | F73: 116.74153 | G73: 109.84305 | H73: 109.84305
A74: Enterprise-only | B74: 74.746025 | C74: 95.681752 | D74: 95.704807 | E74: 95.704807 | F74: 108.00697 | G74: 111.86179 | H74: 111.86179
A75: AI-only | B75: 127.25922 | C75: 132.79785 | D75: 172.44996 | E75: 138.35225 | F75: 135.40897 | G75: 171.31431 | H75: 142.00787
A76: University-led | B76: 110.90344 | C76: 121.44752 | D76: 117.5243 | E76: 117.5243 | F76: 123.35393 | G76: 124.94225 | H76: 124.94225
A77: Cash preservation | B77: 102.81459 | C77: 109.14445 | D77: 126.6964 | E77: 109.6161 | F77: 112.20272 | G77: 136.15327 | H77: 112.377
A78: Adaptive (evidence-responsive) | B78: 148.82113 | C78: 153.01845 | D78: 181.77197 | E78: 155.12689 | F78: 155.10945 | G78: 180.42491 | H78: 156.71442
A79: Rank of Consumer-only | B79: =RANK(B73,B69:B78) -> 7 | C79: =RANK(C73,C69:C78) -> 7 | D79: =RANK(D73,D69:D78) -> 8 | E79: =RANK(E73,E69:E78) -> 7 | F79: =RANK(F73,F69:F78) -> 7 | G79: =RANK(G73,G69:G78) -> 10 | H79: =RANK(H73,H69:H78) -> 10
A80: Rank of Enterprise-only | B80: =RANK(B74,B69:B78) -> 10 | C80: =RANK(C74,C69:C78) -> 10 | D80: =RANK(D74,D69:D78) -> 10 | E80: =RANK(E74,E69:E78) -> 10 | F80: =RANK(F74,F69:F78) -> 9 | G80: =RANK(G74,G69:G78) -> 9 | H80: =RANK(H74,H69:H78) -> 9
A81: Best − worst | B81: =MAX(B69:B78)-MIN(B69:B78) -> 74.075101 | C81: =MAX(C69:C78)-MIN(C69:C78) -> 57.3367 | D81: =MAX(D69:D78)-MIN(D69:D78) -> 86.407688 | E81: =MAX(E69:E78)-MIN(E69:E78) -> 59.869814 | F81: =MAX(F69:F78)-MIN(F69:F78) -> 47.670441 | G81: =MAX(G69:G78)-MIN(G69:G78) -> 71.008579 | H81: =MAX(H69:H78)-MIN(H69:H78) -> 47.533786
A83: Terminal score | B83: Baseline | C83: A naive | D83: A re-based | E83: A re-based, AI fixed | F83: B naive | G83: B re-based | H83: B re-based, AI fixed
A84: Consumer-led | B84: 68.063016 | C84: 71.793086 | D84: 70.396207 | E84: 70.383348 | F84: 73.143181 | G84: 70.528041 | H84: 70.507858
A85: Enterprise-led | B85: 58.631732 | C85: 66.055257 | D85: 66.094229 | E85: 66.094229 | F85: 70.138748 | G85: 72.25007 | H85: 72.164222
A86: AI-led | B86: 80.49111 | C86: 83.115566 | D86: 87.992962 | E86: 84.931089 | F86: 84.474154 | G86: 88.324399 | H86: 86.464369
A87: Diversified | B87: 76.715858 | C87: 79.878795 | D87: 85.25689 | E87: 80.72304 | F87: 81.319011 | G87: 85.432003 | H87: 82.362167
A88: Consumer-only | B88: 61.803585 | C88: 65.783656 | D88: 64.496293 | E88: 64.496293 | F88: 67.193784 | G88: 64.735068 | H88: 64.735068
A89: Enterprise-only | B89: 51.717494 | C89: 61.305235 | D89: 57.497584 | E89: 57.497584 | F89: 65.552037 | G89: 68.001095 | H89: 68.001095
A90: AI-only | B90: 69.260958 | C90: 72.789331 | D90: 80.625141 | E90: 75.090249 | F90: 74.508815 | G90: 80.914429 | H90: 77.481816
A91: University-led | B91: 63.653293 | C91: 70.167738 | D91: 69.839812 | E91: 69.839812 | F91: 71.658421 | G91: 71.864954 | H91: 71.864954
A92: Cash preservation | B92: 64.43345 | C92: 67.426932 | D92: 72.972782 | E92: 67.961883 | F92: 68.581978 | G92: 75.93157 | H92: 68.841942
A93: Adaptive (evidence-responsive) | B93: 80.331139 | C93: 83.858337 | D93: 87.938629 | E93: 84.587389 | F93: 85.39553 | G93: 88.380891 | H93: 85.986673
A94: Rank of Consumer-only | B94: =RANK(B88,B84:B93) -> 8 | C94: =RANK(C88,C84:C93) -> 9 | D94: =RANK(D88,D84:D93) -> 9 | E94: =RANK(E88,E84:E93) -> 9 | F94: =RANK(F88,F84:F93) -> 9 | G94: =RANK(G88,G84:G93) -> 10 | H94: =RANK(H88,H84:H93) -> 10
A95: Rank of Enterprise-only | B95: =RANK(B89,B84:B93) -> 10 | C95: =RANK(C89,C84:C93) -> 10 | D95: =RANK(D89,D84:D93) -> 10 | E95: =RANK(E89,E84:E93) -> 10 | F95: =RANK(F89,F84:F93) -> 10 | G95: =RANK(G89,G84:G93) -> 9 | H95: =RANK(H89,H84:H93) -> 9
A96: Best − worst | B96: =MAX(B84:B93)-MIN(B84:B93) -> 28.773616 | C96: =MAX(C84:C93)-MIN(C84:C93) -> 22.553102 | D96: =MAX(D84:D93)-MIN(D84:D93) -> 30.495377 | E96: =MAX(E84:E93)-MIN(E84:E93) -> 27.433505 | F96: =MAX(F84:F93)-MIN(F84:F93) -> 19.843493 | G96: =MAX(G84:G93)-MIN(G84:G93) -> 23.645823 | H96: =MAX(H84:H93)-MIN(H84:H93) -> 21.729301
A98: Q8 revenue ($M) | B98: Baseline | C98: A naive | D98: A re-based | E98: A re-based, AI fixed | F98: B naive | G98: B re-based | H98: B re-based, AI fixed
A99: Consumer-led | B99: 212.37071 | C99: 215.11835 | D99: 212.00084 | E99: 211.95466 | F99: 216.62537 | G99: 211.38115 | H99: 211.31399
A100: Enterprise-led | B100: 197.52408 | C100: 209.98165 | D100: 212.30156 | E100: 212.30156 | F100: 212.78236 | G100: 219.97404 | H100: 219.68891
A101: AI-led | B101: 234.70009 | C101: 237.34175 | D101: 331.24617 | E101: 244.34596 | F101: 238.81007 | G101: 375.11004 | H101: 247.71877
A102: Diversified | B102: 226.21999 | C102: 229.8989 | D102: 284.25164 | E102: 233.6987 | F102: 231.8329 | G102: 310.68716 | H102: 236.85965
A103: Consumer-only | B103: 203.89316 | C103: 207.40246 | D103: 204.90449 | E103: 204.90449 | F103: 209.29109 | G103: 205.03607 | H103: 205.03607
A104: Enterprise-only | B104: 193.27843 | C104: 206.11661 | D104: 204.97576 | E104: 204.97576 | F104: 209.44026 | G104: 217.98056 | H104: 217.98056
A105: AI-only | B105: 220.94389 | C105: 226.01877 | D105: 320.34608 | E105: 233.87493 | F105: 228.55571 | G105: 365.56692 | H105: 238.99957
A106: University-led | B106: 198.16419 | C106: 201.28553 | D106: 201.221 | E106: 201.221 | F106: 202.94695 | G106: 204.90561 | H106: 204.90561
A107: Cash preservation | B107: 196.35179 | C107: 201.32856 | D107: 218.1122 | E107: 203.00312 | F107: 203.95778 | G107: 228.15924 | H107: 206.15901
A108: Adaptive (evidence-responsive) | B108: 233.34923 | C108: 237.26689 | D108: 288.80847 | E108: 240.95033 | F108: 239.31429 | G108: 314.05979 | H108: 244.21867
A109: Rank of Consumer-only | B109: =RANK(B103,B99:B108) -> 6 | C109: =RANK(C103,C99:C108) -> 7 | D109: =RANK(D103,D99:D108) -> 9 | E109: =RANK(E103,E99:E108) -> 8 | F109: =RANK(F103,F99:F108) -> 8 | G109: =RANK(G103,G99:G108) -> 9 | H109: =RANK(H103,H99:H108) -> 9
A110: Rank of Enterprise-only | B110: =RANK(B104,B99:B108) -> 10 | C110: =RANK(C104,C99:C108) -> 8 | D110: =RANK(D104,D99:D108) -> 8 | E110: =RANK(E104,E99:E108) -> 7 | F110: =RANK(F104,F99:F108) -> 7 | G110: =RANK(G104,G99:G108) -> 7 | H110: =RANK(H104,H99:H108) -> 6
A111: Best − worst | B111: =MAX(B99:B108)-MIN(B99:B108) -> 41.421664 | C111: =MAX(C99:C108)-MIN(C99:C108) -> 36.05622 | D111: =MAX(D99:D108)-MIN(D99:D108) -> 130.02517 | E111: =MAX(E99:E108)-MIN(E99:E108) -> 43.124961 | F111: =MAX(F99:F108)-MIN(F99:F108) -> 36.367337 | G111: =MAX(G99:G108)-MIN(G99:G108) -> 170.20443 | H111: =MAX(H99:H108)-MIN(H99:H108) -> 42.813157
A113: Cumulative operating profit ($M) | B113: Baseline | C113: A naive | D113: A re-based | E113: A re-based, AI fixed | F113: B naive | G113: B re-based | H113: B re-based, AI fixed
A114: Consumer-led | B114: 249.95285 | C114: 279.25515 | D114: 253.54864 | E114: 253.5094 | F114: 294.35454 | G114: 254.44107 | H114: 254.38398
A115: Enterprise-led | B115: 199.8321 | C115: 229.79175 | D115: 231.67094 | E115: 231.67094 | F115: 248.40471 | G115: 229.50329 | H115: 229.26094
A116: AI-led | B116: 277.75757 | C116: 308.9756 | D116: 524.3487 | E116: 304.79019 | F116: 325.01633 | G116: 636.39441 | H116: 315.40705
A117: Diversified | B117: 273.094 | C117: 307.11806 | D117: 411.14887 | E117: 294.39035 | F117: 324.38917 | G117: 473.94663 | H117: 303.66807
A118: Consumer-only | B118: 257.07733 | C118: 288.37365 | D118: 263.08987 | E118: 263.08987 | F118: 304.4138 | G118: 265.22677 | H118: 265.22677
A119: Enterprise-only | B119: 196.9351 | C119: 231.98211 | D119: 228.70467 | E119: 228.70467 | F119: 252.27706 | G119: 236.02187 | H119: 236.02187
A120: AI-only | B120: 258.24927 | C120: 294.66812 | D120: 515.35313 | E120: 292.25122 | F120: 313.10114 | G120: 632.3825 | H120: 306.52932
A121: University-led | B121: 214.01273 | C121: 247.68692 | D121: 228.67412 | E121: 228.67412 | F121: 264.2481 | G121: 238.04016 | H121: 238.04016
A122: Cash preservation | B122: 223.16578 | C122: 260.93367 | D122: 274.27529 | E122: 244.62751 | F122: 279.57555 | G122: 297.04569 | H122: 254.06862
A123: Adaptive (evidence-responsive) | B123: 262.125 | C123: 296.32282 | D123: 384.10009 | E123: 283.25959 | F123: 313.63512 | G123: 439.53361 | H123: 292.53382
A124: Rank of Consumer-only | B124: =RANK(B118,B114:B123) -> 5 | C124: =RANK(C118,C114:C123) -> 5 | D124: =RANK(D118,D114:D123) -> 6 | E124: =RANK(E118,E114:E123) -> 5 | F124: =RANK(F118,F114:F123) -> 5 | G124: =RANK(G118,G114:G123) -> 6 | H124: =RANK(H118,H114:H123) -> 5
A125: Rank of Enterprise-only | B125: =RANK(B119,B114:B123) -> 10 | C125: =RANK(C119,C114:C123) -> 9 | D125: =RANK(D119,D114:D123) -> 9 | E125: =RANK(E119,E114:E123) -> 9 | F125: =RANK(F119,F114:F123) -> 9 | G125: =RANK(G119,G114:G123) -> 9 | H125: =RANK(H119,H114:H123) -> 9
A126: Best − worst | B126: =MAX(B114:B123)-MIN(B114:B123) -> 80.822469 | C126: =MAX(C114:C123)-MIN(C114:C123) -> 79.183853 | D126: =MAX(D114:D123)-MIN(D114:D123) -> 295.67457 | E126: =MAX(E114:E123)-MIN(E114:E123) -> 76.11607 | F126: =MAX(F114:F123)-MIN(F114:F123) -> 76.611624 | G126: =MAX(G114:G123)-MIN(G114:G123) -> 406.89111 | H126: =MAX(H114:H123)-MIN(H114:H123) -> 86.146115
A128: E · What the mix experiment shows
A129: • Changing only the four starting revenues is not valid: within three quarters with no investment, Consumer drifts +$9M (A) and +$14M (B) and AI-native −$3M to −$5M, because every flow is calibrated to the baseline mix. A proportional re-base (section C) makes both alternatives steady states (drift within the baseline’s −$0.4M).
A130: • With the AI growth reward held fixed, AI/Product is still the highest-return bucket in every mix (+$27–28M Q8 revenue for $10M a quarter; see Investment & capability, B). AI dominance therefore comes from the investment-return formulas, not the mix.
...

Sheet Sensitivity analysis
A1: 5 · Sensitivity analysis — ten market scenarios × ten strategies
A2: The engine market path is deterministic; scenarios are explicit variations through the supported market-override hook (definitions on the About sheet). Player briefings stay as authored.
A4: Strategy | B4: Authored arc | C4: Consumer weaker | D4: Consumer stronger | E4: Enterprise boom | F4: Enterprise slump | G4: AI boom | H4: University boom | I4: No AI disruption | J4: Severe recession | K4: No recession | L4: Mean | M4: Min | N4: Max
A5: Consumer-led | B5: 116.21624 | C5: 103.92829 | D5: 131.28035 | E5: 117.73677 | F5: 115.11322 | G5: 117.14532 | H5: 117.82822 | I5: 132.31353 | J5: 110.36125 | K5: 124.49846 | L5: =AVERAGE(B5:K5) -> 118.64217 | M5: =MIN(B5:K5) -> 103.92829 | N5: =MAX(B5:K5) -> 132.31353
A6: Enterprise-led | B6: 81.785813 | C6: 71.575302 | D6: 110.92104 | E6: 84.932614 | F6: 79.495859 | G6: 82.796971 | H6: 83.419972 | I6: 111.09206 | J6: 75.849984 | K6: 90.406538 | L6: =AVERAGE(B6:K6) -> 87.227614 | M6: =MIN(B6:K6) -> 71.575302 | N6: =MAX(B6:K6) -> 111.09206
A7: AI-led | B7: 148.51302 | C7: 142.52239 | D7: 157.52416 | E7: 150.24852 | F7: 147.27877 | G7: 164.08849 | H7: 150.06223 | I7: 142.05412 | J7: 140.91061 | K7: 157.57326 | L7: =AVERAGE(B7:K7) -> 150.07756 | M7: =MIN(B7:K7) -> 140.91061 | N7: =MAX(B7:K7) -> 164.08849
A8: Diversified | B8: 143.75331 | C8: 136.53023 | D8: 154.36406 | E8: 146.22616 | F8: 141.9773 | G8: 156.04606 | H8: 145.32351 | I8: 144.90791 | J8: 136.60525 | K8: 152.86908 | L8: =AVERAGE(B8:K8) -> 145.86029 | M8: =MIN(B8:K8) -> 136.53023 | N8: =MAX(B8:K8) -> 156.04606
A9: Consumer-only | B9: 109.88221 | C9: 95.558665 | D9: 124.31983 | E9: 111.38572 | F9: 108.79239 | G9: 110.74617 | H9: 111.48895 | I9: 125.95702 | J9: 104.12648 | K9: 118.10439 | L9: =AVERAGE(B9:K9) -> 112.03618 | M9: =MIN(B9:K9) -> 95.558665 | N9: =MAX(B9:K9) -> 125.95702
A10: Enterprise-only | B10: 74.746025 | C10: 63.717205 | D10: 90.674549 | E10: 78.423017 | F10: 72.074683 | G10: 76.165661 | H10: 76.474029 | I10: 96.14365 | J10: 68.474352 | K10: 84.177111 | L10: =AVERAGE(B10:K10) -> 78.107028 | M10: =MIN(B10:K10) -> 63.717205 | N10: =MAX(B10:K10) -> 96.14365
A11: AI-only | B11: 127.25922 | C11: 120.91943 | D11: 136.33991 | E11: 129.00572 | F11: 126.01923 | G11: 144.50163 | H11: 128.81547 | I11: 120.47805 | J11: 119.53931 | K11: 136.46617 | L11: =AVERAGE(B11:K11) -> 128.93442 | M11: =MIN(B11:K11) -> 119.53931 | N11: =MAX(B11:K11) -> 144.50163
A12: University-led | B12: 110.90344 | C12: 94.970782 | D12: 130.17637 | E12: 113.98221 | F12: 108.68406 | G12: 106.40892 | H12: 114.98479 | I12: 131.20383 | J12: 101.21317 | K12: 117.66379 | L12: =AVERAGE(B12:K12) -> 113.01914 | M12: =MIN(B12:K12) -> 94.970782 | N12: =MAX(B12:K12) -> 131.20383
A13: Cash preservation | B13: 102.81459 | C13: 94.106188 | D13: 114.86312 | E13: 104.83072 | F13: 101.35684 | G13: 109.13346 | H13: 104.43516 | I13: 112.38561 | J13: 96.373336 | K13: 111.43852 | L13: =AVERAGE(B13:K13) -> 105.17375 | M13: =MIN(B13:K13) -> 94.106188 | N13: =MAX(B13:K13) -> 114.86312
A14: Adaptive (evidence-responsive) | B14: 148.82113 | C14: 141.94146 | D14: 158.91461 | E14: 151.31999 | F14: 148.21921 | G14: 159.89677 | H14: 150.59291 | I14: 149.55691 | J14: 141.56956 | K14: 157.9773 | L14: =AVERAGE(B14:K14) -> 150.88098 | M14: =MIN(B14:K14) -> 141.56956 | N14: =MAX(B14:K14) -> 159.89677
A15: Leader | B15: =INDEX($A$5:$A$14,MATCH(MAX(B5:B14),B5:B14,0)) -> Adaptive (evidence-responsive) | C15: =INDEX($A$5:$A$14,MATCH(MAX(C5:C14),C5:C14,0)) -> AI-led | D15: =INDEX($A$5:$A$14,MATCH(MAX(D5:D14),D5:D14,0)) -> Adaptive (evidence-responsive) | E15: =INDEX($A$5:$A$14,MATCH(MAX(E5:E14),E5:E14,0)) -> Adaptive (evidence-responsive) | F15: =INDEX($A$5:$A$14,MATCH(MAX(F5:F14),F5:F14,0)) -> Adaptive (evidence-responsive) | G15: =INDEX($A$5:$A$14,MATCH(MAX(G5:G14),G5:G14,0)) -> AI-led | H15: =INDEX($A$5:$A$14,MATCH(MAX(H5:H14),H5:H14,0)) -> Adaptive (evidence-responsive) | I15: =INDEX($A$5:$A$14,MATCH(MAX(I5:I14),I5:I14,0)) -> Adaptive (evidence-responsive) | ... K15: =INDEX($A$5:$A$14,MATCH(MAX(K5:K14),K5:K14,0)) -> Adaptive (evidence-responsive)
A17: Strategy | B17: Authored arc | C17: Consumer weaker | D17: Consumer stronger | E17: Enterprise boom | F17: Enterprise slump | G17: AI boom | H17: University boom | I17: No AI disruption | J17: Severe recession | K17: No recession | L17: Mean | M17: Min | N17: Max
A18: Consumer-led | B18: 68.063016 | C18: 63.09822 | D18: 73.606695 | E18: 69.726003 | F18: 67.81418 | G18: 69.716548 | H18: 69.513019 | I18: 73.896883 | J18: 66.942553 | K18: 71.191547 | L18: =AVERAGE(B18:K18) -> 69.356866 | M18: =MIN(B18:K18) -> 63.09822 | N18: =MAX(B18:K18) -> 73.896883
A19: Enterprise-led | B19: 58.631732 | C19: 56.372887 | D19: 67.226609 | E19: 59.400843 | F19: 58.082176 | G19: 59.092535 | H19: 58.788912 | I19: 68.694001 | J19: 57.622198 | K19: 60.32367 | L19: =AVERAGE(B19:K19) -> 60.423556 | M19: =MIN(B19:K19) -> 56.372887 | N19: =MAX(B19:K19) -> 68.694001
A20: AI-led | B20: 80.49111 | C20: 78.534461 | D20: 83.157004 | E20: 80.875317 | F20: 80.224361 | G20: 85.430381 | H20: 80.621157 | I20: 77.665797 | J20: 78.549895 | K20: 82.72811 | L20: =AVERAGE(B20:K20) -> 80.827759 | M20: =MIN(B20:K20) -> 77.665797 | N20: =MAX(B20:K20) -> 85.430381
A21: Diversified | B21: 76.715858 | C21: 74.645042 | D21: 79.975533 | E21: 77.293984 | F21: 76.310676 | G21: 80.92056 | H21: 76.844132 | I21: 76.920748 | J21: 75.097768 | K21: 78.921119 | L21: =AVERAGE(B21:K21) -> 77.364542 | M21: =MIN(B21:K21) -> 74.645042 | N21: =MAX(B21:K21) -> 80.92056
A22: Consumer-only | B22: 61.803585 | C22: 59.26784 | D22: 67.080713 | E22: 62.141929 | F22: 61.563698 | G22: 62.121038 | H22: 61.937922 | I22: 67.501301 | J22: 60.748077 | K22: 63.553929 | L22: =AVERAGE(B22:K22) -> 62.772003 | M22: =MIN(B22:K22) -> 59.26784 | N22: =MAX(B22:K22) -> 67.501301
A23: Enterprise-only | B23: 51.717494 | C23: 49.727876 | D23: 54.653994 | E23: 52.47138 | F23: 51.179589 | G23: 52.059477 | H23: 51.851051 | I23: 54.991507 | J23: 50.854841 | K23: 53.18612 | L23: =AVERAGE(B23:K23) -> 52.269333 | M23: =MIN(B23:K23) -> 49.727876 | N23: =MAX(B23:K23) -> 54.991507
A24: AI-only | B24: 69.260958 | C24: 67.398695 | D24: 72.104389 | E24: 69.633146 | F24: 69.003151 | G24: 75.64117 | H24: 69.383401 | I24: 66.401939 | J24: 67.418307 | K24: 71.649532 | L24: =AVERAGE(B24:K24) -> 69.789469 | M24: =MIN(B24:K24) -> 66.401939 | N24: =MAX(B24:K24) -> 75.64117
A25: University-led | B25: 63.653293 | C25: 61.734645 | D25: 69.355511 | E25: 64.05591 | F25: 63.366879 | G25: 66.426791 | H25: 63.912392 | I25: 69.584676 | J25: 62.650717 | K25: 67.709478 | L25: =AVERAGE(B25:K25) -> 65.245029 | M25: =MIN(B25:K25) -> 61.734645 | N25: =MAX(B25:K25) -> 69.584676
A26: Cash preservation | B26: 64.43345 | C26: 62.853937 | D26: 66.785622 | E26: 64.823182 | F26: 64.157774 | G26: 65.770234 | H26: 64.54405 | I26: 66.217661 | J26: 63.421999 | K26: 65.924026 | L26: =AVERAGE(B26:K26) -> 64.893194 | M26: =MIN(B26:K26) -> 62.853937 | N26: =MAX(B26:K26) -> 66.785622
A27: Adaptive (evidence-responsive) | B27: 80.331139 | C27: 78.177709 | D27: 82.913962 | E27: 80.932464 | F27: 80.297851 | G27: 83.223128 | H27: 80.474964 | I27: 81.089349 | J27: 78.681958 | K27: 82.019614 | L27: =AVERAGE(B27:K27) -> 80.814214 | M27: =MIN(B27:K27) -> 78.177709 | N27: =MAX(B27:K27) -> 83.223128
A28: Leader | B28: =INDEX($A$18:$A$27,MATCH(MAX(B18:B27),B18:B27,0)) -> AI-led | C28: =INDEX($A$18:$A$27,MATCH(MAX(C18:C27),C18:C27,0)) -> AI-led | D28: =INDEX($A$18:$A$27,MATCH(MAX(D18:D27),D18:D27,0)) -> AI-led | E28: =INDEX($A$18:$A$27,MATCH(MAX(E18:E27),E18:E27,0)) -> Adaptive (evidence-responsive) | F28: =INDEX($A$18:$A$27,MATCH(MAX(F18:F27),F18:F27,0)) -> Adaptive (evidence-responsive) | G28: =INDEX($A$18:$A$27,MATCH(MAX(G18:G27),G18:G27,0)) -> AI-led | H28: =INDEX($A$18:$A$27,MATCH(MAX(H18:H27),H18:H27,0)) -> AI-led | I28: =INDEX($A$18:$A$27,MATCH(MAX(I18:I27),I18:I27,0)) -> Adaptive (evidence-responsive) | ... K28: =INDEX($A$18:$A$27,MATCH(MAX(K18:K27),K18:K27,0)) -> AI-led
A30: Strategy | B30: Authored arc | C30: Consumer weaker | D30: Consumer stronger | E30: Enterprise boom | F30: Enterprise slump | G30: AI boom | H30: University boom | I30: No AI disruption | J30: Severe recession | K30: No recession | L30: Mean | M30: Min | N30: Max
A31: Consumer-led | B31: 212.37071 | C31: 202.95015 | D31: 227.84432 | E31: 213.36364 | F31: 211.66741 | G31: 213.30929 | H31: 212.75741 | I31: 228.70279 | J31: 208.4811 | K31: 218.70423 | L31: =AVERAGE(B31:K31) -> 215.0151 | M31: =MIN(B31:K31) -> 202.95015 | N31: =MAX(B31:K31) -> 228.70279
A32: Enterprise-led | B32: 197.52408 | C32: 190.07874 | D32: 213.44095 | E32: 199.40707 | F32: 196.18739 | G32: 198.47742 | H32: 197.88806 | I32: 216.36267 | J32: 194.3 | K32: 202.94661 | L32: =AVERAGE(B32:K32) -> 200.6613 | M32: =MIN(B32:K32) -> 190.07874 | N32: =MAX(B32:K32) -> 216.36267
A33: AI-led | B33: 234.70009 | C33: 227.86891 | D33: 245.24242 | E33: 235.8819 | F33: 233.88095 | G33: 252.52276 | H33: 235.06067 | I33: 229.38236 | J33: 228.67164 | K33: 242.54702 | L33: =AVERAGE(B33:K33) -> 236.57587 | M33: =MIN(B33:K33) -> 227.86891 | N33: =MAX(B33:K33) -> 252.52276
A34: Diversified | B34: 226.21999 | C34: 218.47465 | D34: 238.1158 | E34: 227.83079 | F34: 225.09433 | G34: 238.71511 | H34: 226.58536 | I34: 229.62791 | J34: 221.01414 | K34: 233.4717 | L34: =AVERAGE(B34:K34) -> 228.51498 | M34: =MIN(B34:K34) -> 218.47465 | N34: =MAX(B34:K34) -> 238.71511
A35: Consumer-only | B35: 203.89316 | C35: 194.86786 | D35: 218.33581 | E35: 204.84783 | F35: 203.21813 | G35: 204.75199 | H35: 204.2673 | I35: 219.61766 | J35: 200.2341 | K35: 209.99775 | L35: =AVERAGE(B35:K35) -> 206.40316 | M35: =MIN(B35:K35) -> 194.86786 | N35: =MAX(B35:K35) -> 219.61766
A36: Enterprise-only | B36: 193.27843 | C36: 186.13045 | D36: 203.68369 | E36: 195.25155 | F36: 191.8781 | G36: 194.10902 | H36: 193.62419 | I36: 204.76143 | J36: 190.24979 | K36: 198.39102 | L36: =AVERAGE(B36:K36) -> 195.13577 | M36: =MIN(B36:K36) -> 186.13045 | N36: =MAX(B36:K36) -> 204.76143
A37: AI-only | B37: 220.94389 | C37: 214.31772 | D37: 230.80566 | E37: 222.07829 | F37: 220.1599 | G37: 239.35483 | H37: 221.29343 | I37: 215.34489 | J37: 215.13982 | K37: 228.49469 | L37: =AVERAGE(B37:K37) -> 222.79331 | M37: =MIN(B37:K37) -> 214.31772 | N37: =MAX(B37:K37) -> 239.35483
A38: University-led | B38: 198.16419 | C38: 190.22685 | D38: 210.1325 | E38: 199.23062 | F38: 197.40803 | G38: 199.08119 | H38: 198.93744 | I38: 210.82479 | J38: 194.74039 | K38: 203.80714 | L38: =AVERAGE(B38:K38) -> 200.25532 | M38: =MIN(B38:K38) -> 190.22685 | N38: =MAX(B38:K38) -> 210.82479
A39: Cash preservation | B39: 196.35179 | C39: 188.81543 | D39: 207.60276 | E39: 197.5125 | F39: 195.53343 | G39: 200.8995 | H39: 196.70462 | I39: 205.90977 | J39: 192.53262 | K39: 202.14703 | L39: =AVERAGE(B39:K39) -> 198.40094 | M39: =MIN(B39:K39) -> 188.81543 | N39: =MAX(B39:K39) -> 207.60276
A40: Adaptive (evidence-responsive) | B40: 233.34923 | C40: 225.72413 | D40: 245.04775 | E40: 234.93112 | F40: 233.42885 | G40: 245.44281 | H40: 233.77313 | I40: 236.90148 | J40: 228.08488 | K40: 240.61206 | L40: =AVERAGE(B40:K40) -> 235.72954 | M40: =MIN(B40:K40) -> 225.72413 | N40: =MAX(B40:K40) -> 245.44281
A41: Leader | B41: =INDEX($A$31:$A$40,MATCH(MAX(B31:B40),B31:B40,0)) -> AI-led | C41: =INDEX($A$31:$A$40,MATCH(MAX(C31:C40),C31:C40,0)) -> AI-led | D41: =INDEX($A$31:$A$40,MATCH(MAX(D31:D40),D31:D40,0)) -> AI-led | E41: =INDEX($A$31:$A$40,MATCH(MAX(E31:E40),E31:E40,0)) -> AI-led | F41: =INDEX($A$31:$A$40,MATCH(MAX(F31:F40),F31:F40,0)) -> AI-led | G41: =INDEX($A$31:$A$40,MATCH(MAX(G31:G40),G31:G40,0)) -> AI-led | H41: =INDEX($A$31:$A$40,MATCH(MAX(H31:H40),H31:H40,0)) -> AI-led | I41: =INDEX($A$31:$A$40,MATCH(MAX(I31:I40),I31:I40,0)) -> Adaptive (evidence-responsive) | ... K41: =INDEX($A$31:$A$40,MATCH(MAX(K31:K40),K31:K40,0)) -> AI-led
A43: Strategy | B43: Authored arc | C43: Consumer weaker | D43: Consumer stronger | E43: Enterprise boom | F43: Enterprise slump | G43: AI boom | H43: University boom | I43: No AI disruption | J43: Severe recession | K43: No recession | L43: Mean | M43: Min | N43: Max
A44: Consumer-led | B44: 249.95285 | C44: 229.50877 | D44: 283.29804 | E44: 251.26576 | F44: 249.01636 | G44: 253.26847 | H44: 250.69201 | I44: 287.52987 | J44: 245.20653 | K44: 258.62363 | L44: =AVERAGE(B44:K44) -> 255.83623 | M44: =MIN(B44:K44) -> 229.50877 | N44: =MAX(B44:K44) -> 287.52987
A45: Enterprise-led | B45: 199.8321 | C45: 181.55463 | D45: 232.36139 | E45: 202.12872 | F45: 198.19468 | G45: 203.23746 | H45: 200.55361 | I45: 222.26541 | J45: 196.01346 | K45: 206.98696 | L45: =AVERAGE(B45:K45) -> 204.31284 | M45: =MIN(B45:K45) -> 181.55463 | N45: =MAX(B45:K45) -> 232.36139
A46: AI-led | B46: 277.75757 | C46: 263.03889 | D46: 301.56923 | E46: 279.27435 | F46: 276.6964 | G46: 328.8439 | H46: 278.45817 | I46: 262.4074 | J46: 269.01776 | K46: 289.98775 | L46: =AVERAGE(B46:K46) -> 282.70514 | M46: =MIN(B46:K46) -> 262.4074 | N46: =MAX(B46:K46) -> 328.8439
A47: Diversified | B47: 273.094 | C47: 255.45382 | D47: 300.65822 | E47: 275.04448 | F47: 271.71957 | G47: 304.0168 | H47: 273.81333 | I47: 282.78729 | J47: 265.98364 | K47: 283.69864 | L47: =AVERAGE(B47:K47) -> 278.62698 | M47: =MIN(B47:K47) -> 255.45382 | N47: =MAX(B47:K47) -> 304.0168
A48: Consumer-only | B48: 257.07733 | C48: 235.87414 | D48: 289.87075 | E48: 258.37412 | F48: 256.15315 | G48: 260.26843 | H48: 257.81197 | I48: 294.90161 | J48: 252.57406 | K48: 265.38654 | L48: =AVERAGE(B48:K48) -> 262.82921 | M48: =MIN(B48:K48) -> 235.87414 | N48: =MAX(B48:K48) -> 294.90161
A49: Enterprise-only | B49: 196.9351 | C49: 178.61524 | D49: 224.44661 | E49: 199.44843 | F49: 195.14374 | G49: 200.35547 | H49: 197.67929 | I49: 228.87716 | J49: 193.25683 | K49: 203.99648 | L49: =AVERAGE(B49:K49) -> 201.87543 | M49: =MIN(B49:K49) -> 178.61524 | N49: =MAX(B49:K49) -> 228.87716
A50: AI-only | B50: 258.24927 | C50: 243.36839 | D50: 281.51438 | E50: 259.76115 | F50: 257.1936 | G50: 311.22026 | H50: 258.94633 | I50: 242.16914 | J50: 249.86474 | K50: 269.98566 | L50: =AVERAGE(B50:K50) -> 263.22729 | M50: =MIN(B50:K50) -> 242.16914 | N50: =MAX(B50:K50) -> 311.22026
A51: University-led | B51: 214.01273 | C51: 195.10628 | D51: 242.15463 | E51: 215.49389 | F51: 212.95539 | G51: 217.5587 | H51: 215.34016 | I51: 245.70992 | J51: 209.76877 | K51: 221.94511 | L51: =AVERAGE(B51:K51) -> 219.00456 | M51: =MIN(B51:K51) -> 195.10628 | N51: =MAX(B51:K51) -> 245.70992
A52: Cash preservation | B52: 223.16578 | C52: 204.57952 | D52: 251.40385 | E52: 224.76075 | F52: 222.03163 | G52: 234.15884 | H52: 223.90511 | I52: 250.44843 | J52: 218.14309 | K52: 231.64701 | L52: =AVERAGE(B52:K52) -> 228.4244 | M52: =MIN(B52:K52) -> 204.57952 | N52: =MAX(B52:K52) -> 251.40385
A53: Adaptive (evidence-responsive) | B53: 262.125 | C53: 245.02477 | D53: 288.72406 | E53: 263.98512 | F53: 263.42762 | G53: 289.63272 | H53: 262.90704 | I53: 273.59292 | J53: 254.99811 | K53: 272.65581 | L53: =AVERAGE(B53:K53) -> 267.70732 | M53: =MIN(B53:K53) -> 245.02477 | N53: =MAX(B53:K53) -> 289.63272
A54: Leader | B54: =INDEX($A$44:$A$53,MATCH(MAX(B44:B53),B44:B53,0)) -> AI-led | C54: =INDEX($A$44:$A$53,MATCH(MAX(C44:C53),C44:C53,0)) -> AI-led | D54: =INDEX($A$44:$A$53,MATCH(MAX(D44:D53),D44:D53,0)) -> AI-led | E54: =INDEX($A$44:$A$53,MATCH(MAX(E44:E53),E44:E53,0)) -> AI-led | F54: =INDEX($A$44:$A$53,MATCH(MAX(F44:F53),F44:F53,0)) -> AI-led | G54: =INDEX($A$44:$A$53,MATCH(MAX(G44:G53),G44:G53,0)) -> AI-led | H54: =INDEX($A$44:$A$53,MATCH(MAX(H44:H53),H44:H53,0)) -> AI-led | I54: =INDEX($A$44:$A$53,MATCH(MAX(I44:I53),I44:I53,0)) -> Consumer-only | ... K54: =INDEX($A$44:$A$53,MATCH(MAX(K44:K53),K44:K53,0)) -> AI-led
A56: Strategy | B56: Authored arc | C56: Consumer weaker | D56: Consumer stronger | E56: Enterprise boom | F56: Enterprise slump | G56: AI boom | H56: University boom | I56: No AI disruption | J56: Severe recession | K56: No recession | L56: Best rank | M56: Worst rank
A57: Consumer-led | B57: =RANK(B5,B$5:B$14) -> 5 | C57: =RANK(C5,C$5:C$14) -> 5 | D57: =RANK(D5,D$5:D$14) -> 5 | E57: =RANK(E5,E$5:E$14) -> 5 | F57: =RANK(F5,F$5:F$14) -> 5 | G57: =RANK(G5,G$5:G$14) -> 5 | H57: =RANK(H5,H$5:H$14) -> 5 | I57: =RANK(I5,I$5:I$14) -> 4 | ... K57: =RANK(K5,K$5:K$14) -> 5 | L57: =MIN(B57:K57) -> 4 | M57: =MAX(B57:K57) -> 5
A58: Enterprise-led | B58: =RANK(B6,B$5:B$14) -> 9 | C58: =RANK(C6,C$5:C$14) -> 9 | D58: =RANK(D6,D$5:D$14) -> 9 | E58: =RANK(E6,E$5:E$14) -> 9 | F58: =RANK(F6,F$5:F$14) -> 9 | G58: =RANK(G6,G$5:G$14) -> 9 | H58: =RANK(H6,H$5:H$14) -> 9 | I58: =RANK(I6,I$5:I$14) -> 9 | ... K58: =RANK(K6,K$5:K$14) -> 9 | L58: =MIN(B58:K58) -> 9 | M58: =MAX(B58:K58) -> 9
A59: AI-led | B59: =RANK(B7,B$5:B$14) -> 2 | C59: =RANK(C7,C$5:C$14) -> 1 | D59: =RANK(D7,D$5:D$14) -> 2 | E59: =RANK(E7,E$5:E$14) -> 2 | F59: =RANK(F7,F$5:F$14) -> 2 | G59: =RANK(G7,G$5:G$14) -> 1 | H59: =RANK(H7,H$5:H$14) -> 2 | I59: =RANK(I7,I$5:I$14) -> 3 | ... K59: =RANK(K7,K$5:K$14) -> 2 | L59: =MIN(B59:K59) -> 1 | M59: =MAX(B59:K59) -> 3
A60: Diversified | B60: =RANK(B8,B$5:B$14) -> 3 | C60: =RANK(C8,C$5:C$14) -> 3 | D60: =RANK(D8,D$5:D$14) -> 3 | E60: =RANK(E8,E$5:E$14) -> 3 | F60: =RANK(F8,F$5:F$14) -> 3 | G60: =RANK(G8,G$5:G$14) -> 3 | H60: =RANK(H8,H$5:H$14) -> 3 | I60: =RANK(I8,I$5:I$14) -> 2 | ... K60: =RANK(K8,K$5:K$14) -> 3 | L60: =MIN(B60:K60) -> 2 | M60: =MAX(B60:K60) -> 3
A61: Consumer-only | B61: =RANK(B9,B$5:B$14) -> 7 | C61: =RANK(C9,C$5:C$14) -> 6 | D61: =RANK(D9,D$5:D$14) -> 7 | E61: =RANK(E9,E$5:E$14) -> 7 | F61: =RANK(F9,F$5:F$14) -> 6 | G61: =RANK(G9,G$5:G$14) -> 6 | H61: =RANK(H9,H$5:H$14) -> 7 | I61: =RANK(I9,I$5:I$14) -> 6 | ... K61: =RANK(K9,K$5:K$14) -> 6 | L61: =MIN(B61:K61) -> 6 | M61: =MAX(B61:K61) -> 7
A62: Enterprise-only | B62: =RANK(B10,B$5:B$14) -> 10 | C62: =RANK(C10,C$5:C$14) -> 10 | D62: =RANK(D10,D$5:D$14) -> 10 | E62: =RANK(E10,E$5:E$14) -> 10 | F62: =RANK(F10,F$5:F$14) -> 10 | G62: =RANK(G10,G$5:G$14) -> 10 | H62: =RANK(H10,H$5:H$14) -> 10 | I62: =RANK(I10,I$5:I$14) -> 10 | ... K62: =RANK(K10,K$5:K$14) -> 10 | L62: =MIN(B62:K62) -> 10 | M62: =MAX(B62:K62) -> 10
A63: AI-only | B63: =RANK(B11,B$5:B$14) -> 4 | C63: =RANK(C11,C$5:C$14) -> 4 | D63: =RANK(D11,D$5:D$14) -> 4 | E63: =RANK(E11,E$5:E$14) -> 4 | F63: =RANK(F11,F$5:F$14) -> 4 | G63: =RANK(G11,G$5:G$14) -> 4 | H63: =RANK(H11,H$5:H$14) -> 4 | I63: =RANK(I11,I$5:I$14) -> 7 | ... K63: =RANK(K11,K$5:K$14) -> 4 | L63: =MIN(B63:K63) -> 4 | M63: =MAX(B63:K63) -> 7
A64: University-led | B64: =RANK(B12,B$5:B$14) -> 6 | C64: =RANK(C12,C$5:C$14) -> 7 | D64: =RANK(D12,D$5:D$14) -> 6 | E64: =RANK(E12,E$5:E$14) -> 6 | F64: =RANK(F12,F$5:F$14) -> 7 | G64: =RANK(G12,G$5:G$14) -> 8 | H64: =RANK(H12,H$5:H$14) -> 6 | I64: =RANK(I12,I$5:I$14) -> 5 | ... K64: =RANK(K12,K$5:K$14) -> 7 | L64: =MIN(B64:K64) -> 5 | M64: =MAX(B64:K64) -> 8
A65: Cash preservation | B65: =RANK(B13,B$5:B$14) -> 8 | C65: =RANK(C13,C$5:C$14) -> 8 | D65: =RANK(D13,D$5:D$14) -> 8 | E65: =RANK(E13,E$5:E$14) -> 8 | F65: =RANK(F13,F$5:F$14) -> 8 | G65: =RANK(G13,G$5:G$14) -> 7 | H65: =RANK(H13,H$5:H$14) -> 8 | I65: =RANK(I13,I$5:I$14) -> 8 | ... K65: =RANK(K13,K$5:K$14) -> 8 | L65: =MIN(B65:K65) -> 7 | M65: =MAX(B65:K65) -> 8
A66: Adaptive (evidence-responsive) | B66: =RANK(B14,B$5:B$14) -> 1 | C66: =RANK(C14,C$5:C$14) -> 2 | D66: =RANK(D14,D$5:D$14) -> 1 | E66: =RANK(E14,E$5:E$14) -> 1 | F66: =RANK(F14,F$5:F$14) -> 1 | G66: =RANK(G14,G$5:G$14) -> 2 | H66: =RANK(H14,H$5:H$14) -> 1 | I66: =RANK(I14,I$5:I$14) -> 1 | ... K66: =RANK(K14,K$5:K$14) -> 1 | L66: =MIN(B66:K66) -> 1 | M66: =MAX(B66:K66) -> 2
A68: Reading
A69: • Rankings are stable across all ten scenarios. Enterprise-only is last in every one and Enterprise-led 9th in every one. Consumer-only ranks 6th–7th everywhere: it is never dominant.
A70: • Even favourable conditions do not rescue the weak families. An Enterprise boom (demand ×1.2) adds only $3 to Enterprise-only, and a University boom adds $4 to University-led: their conversion formulas, not demand, limit them.
A71: • Consumer-led and Consumer-only do best without the AI disruption ($132 and $126, 4th and 6th). Adaptive or AI-led wins every scenario.

Sheet Contract & financing audit
A1: 6 · Contract, financing and recession audit
A2: Forced accept/decline of the Q5 contract and forced recession responses, everything else identical. Deltas are formulas.
A4: A · Does the strategic envelope cap investment regardless of cash? (direct engine validation)
A5: Check | B5: Result
A6: $30M invested within the $30M envelope | B6: accepted
A7: $40M invested within the $30M envelope (e.g. after borrowing $20M) | B7: rejected: V2 allocation must total the strategic envelope 30, got 40
A8: $20M invested + $10M reserve within $30M | B8: accepted
A9: $45M invested within the Q8 scale-independently envelope ($45M) | B9: accepted
A11: B · Q5 global enterprise contract: accept vs decline
A12: Contract costs are event costs (cash) and a recurring delivery-team commitment; the Q5 investment and envelope are identical either way.
A13: Strategy | B13: Choice | C13: Q5 investment | D13: Q5 envelope | E13: Q5 contract cash cost | F13: Q5 closing cash | G13: Delivery team $M/q | H13: Load ÷ capacity Q5 | I13: Q8 revenue | J13: Q8 Enterprise rev | K13: Cum OP | L13: Net cash Q8 | M13: Price Q8 | N13: Terminal | O13: Financing raised | P13: Insolvent
A14: Consumer-led | B14: accept | C14: 30 | D14: 30 | E14: 9.6455328 | F14: 49.823363 | G14: 1.5 | H14: 0.53131277 | I14: 212.75519 | J14: 44.488181 | K14: 245.12276 | L14: 40.695116 | M14: 110.59857 | N14: 63.948085 | O14: 0 | P14: no
A15: Consumer-led | B15: decline | C15: 30 | D15: 30 | E15: 0 | F15: 59.802555 | G15: 0 | H15: 0.36629846 | I15: 212.37071 | J15: 39.542181 | K15: 249.95285 | L15: 46.64691 | M15: 116.21624 | N15: 68.063016 | O15: 0 | P15: no
A16: Enterprise-led | B16: accept | C16: 30 | D16: 30 | E16: 9.6407095 | F16: 30.840366 | G16: 1.5 | H16: 0.45165917 | I16: 197.52408 | J16: 50.102165 | K16: 199.8321 | L16: 24.934135 | M16: 81.785813 | N16: 58.631732 | O16: 0.065865433 | P16: no
A17: Enterprise-led | B17: decline | C17: 30 | D17: 30 | E17: 0 | F17: 40.483135 | G17: 0 | H17: 0.37602523 | I17: 193.08661 | J17: 44.6182 | K17: 183.33766 | L17: 21.169779 | M17: 74.40562 | N17: 58.65153 | O17: 3.8302213 | P17: no
A18: AI-led | B18: accept | C18: 30 | D18: 30 | E18: 6.6189848 | F18: 57.382031 | G18: 1.5 | H18: 0.54576394 | I18: 241.57562 | J18: 48.633133 | K18: 279.95348 | L18: 78.119783 | M18: 150.93474 | N18: 79.06885 | O18: 0 | P18: no
A19: AI-led | B19: decline | C19: 30 | D19: 30 | E19: 0 | F19: 64.187482 | G19: 0 | H19: 0.3868659 | I19: 234.70009 | J19: 39.370979 | K19: 277.75757 | L19: 84.507569 | M19: 148.51302 | N19: 80.49111 | O19: 0 | P19: no
A20: Diversified | B20: accept | C20: 30 | D20: 30 | E20: 8.5664994 | F20: 51.112384 | G20: 1.5 | H20: 0.89343694 | I20: 236.53152 | J20: 55.728119 | K20: 278.8913 | L20: 73.377061 | M20: 150.28433 | N20: 77.018469 | O20: 0 | P20: no
A21: Diversified | B21: decline | C21: 30 | D21: 30 | E21: 0 | F21: 59.72972 | G21: 0 | H21: 0.70775495 | I21: 226.21999 | J21: 43.797326 | K21: 273.094 | L21: 76.420295 | M21: 143.75331 | N21: 76.715858 | O21: 0 | P21: no
A22: Consumer-only | B22: accept | C22: 30 | D22: 30 | E22: 10.375 | F22: 52.39275 | G22: 1.5 | H22: 0.77925 | I22: 203.51793 | J22: 42.995716 | K22: 251.47912 | L22: 37.538889 | M22: 101.20349 | N22: 59.701126 | O22: 0 | P22: no
A23: Consumer-only | B23: decline | C23: 30 | D23: 30 | E23: 0 | F23: 63.128157 | G23: 0 | H23: 0.53454167 | I23: 203.89316 | J23: 39.246379 | K23: 257.07733 | L23: 56.391335 | M23: 109.88221 | N23: 61.803585 | O23: 0 | P23: no
A24: Enterprise-only | B24: accept | C24: 30 | D24: 30 | E24: 10.375 | F24: 28.400387 | G24: 1.5 | H24: 0.61420339 | I24: 193.27843 | J24: 51.985268 | K24: 196.9351 | L24: -1.681658 | M24: 74.746025 | N24: 51.717494 | O24: 26.681658 | P24: no
A25: Enterprise-only | B25: decline | C25: 30 | D25: 30 | E25: 0 | F25: 38.777899 | G25: 0 | H25: 0.50598849 | I25: 187.16111 | J25: 45.770885 | K25: 195.03938 | L25: 7.9628095 | M25: 71.253707 | N25: 50.339373 | O25: 17.037191 | P25: no
... A33: Adaptive (evidence-responsive) | B33: decline | C33: 25 | D33: 30 | E33: 0 | F33: 70.143972 | G33: 0 | H33: 0.58443011 | I33: 224.80901 | J33: 42.644635 | K33: 257.7092 | L33: 87.162848 | M33: 142.64262 | N33: 78.703965 | O33: 0 | P33: no
A35: Effect of accepting (accept − decline)
A36: Strategy | C36: Δ Q5 investment | E36: Contract cash | F36: Δ Q5 cash | G36: Delivery $M/q | H36: Δ Load | I36: Δ Q8 revenue | J36: Δ Q8 Enterprise | K36: Δ Cum OP | L36: Δ Net cash | M36: Δ Price | N36: Δ Terminal
A37: =A14 -> Consumer-led | C37: =C14-C15 -> 0 | E37: =E14 -> 9.6455328 | F37: =F14-F15 -> -9.9791922 | G37: =G14 -> 1.5 | H37: =H14-H15 -> 0.16501431 | I37: =I14-I15 -> 0.38448485 | J37: =J14-J15 -> 4.9459996 | K37: =K14-K15 -> -4.8300847 | L37: =L14-L15 -> -5.9517941 | M37: =M14-M15 -> -5.6176623 | N37: =N14-N15 -> -4.1149316
A38: =A16 -> Enterprise-led | C38: =C16-C17 -> 0 | E38: =E16 -> 9.6407095 | F38: =F16-F17 -> -9.6427685 | G38: =G16 -> 1.5 | H38: =H16-H17 -> 0.075633939 | I38: =I16-I17 -> 4.4374636 | J38: =J16-J17 -> 5.4839649 | K38: =K16-K17 -> 16.494441 | L38: =L16-L17 -> 3.7643559 | M38: =M16-M17 -> 7.3801925 | N38: =N16-N17 -> -0.019798613
A39: =A18 -> AI-led | C39: =C18-C19 -> 0 | E39: =E18 -> 6.6189848 | F39: =F18-F19 -> -6.8054502 | G39: =G18 -> 1.5 | H39: =H18-H19 -> 0.15889804 | I39: =I18-I19 -> 6.8755214 | J39: =J18-J19 -> 9.2621538 | K39: =K18-K19 -> 2.1959139 | L39: =L18-L19 -> -6.3877862 | M39: =M18-M19 -> 2.4217232 | N39: =N18-N19 -> -1.4222593
A40: =A20 -> Diversified | C40: =C20-C21 -> 0 | E40: =E20 -> 8.5664994 | F40: =F20-F21 -> -8.6173359 | G40: =G20 -> 1.5 | H40: =H20-H21 -> 0.18568199 | I40: =I20-I21 -> 10.311529 | J40: =J20-J21 -> 11.930792 | K40: =K20-K21 -> 5.7973053 | L40: =L20-L21 -> -3.0432342 | M40: =M20-M21 -> 6.5310165 | N40: =N20-N21 -> 0.30261038
A41: =A22 -> Consumer-only | C41: =C22-C23 -> 0 | E41: =E22 -> 10.375 | F41: =F22-F23 -> -10.735407 | G41: =G22 -> 1.5 | H41: =H22-H23 -> 0.24470833 | I41: =I22-I23 -> -0.37522572 | J41: =J22-J23 -> 3.7493375 | K41: =K22-K23 -> -5.5982159 | L41: =L22-L23 -> -18.852446 | M41: =M22-M23 -> -8.6787251 | N41: =N22-N23 -> -2.102459
A42: =A24 -> Enterprise-only | C42: =C24-C25 -> 0 | E42: =E24 -> 10.375 | F42: =F24-F25 -> -10.377512 | G42: =G24 -> 1.5 | H42: =H24-H25 -> 0.10821489 | I42: =I24-I25 -> 6.1173233 | J42: =J24-J25 -> 6.2143835 | K42: =K24-K25 -> 1.8957195 | L42: =L24-L25 -> -9.6444675 | M42: =M24-M25 -> 3.4923179 | N42: =N24-N25 -> 1.3781208
A43: =A26 -> AI-only | C43: =C26-C27 -> 0 | E43: =E26 -> 7.223864 | F43: =F26-F27 -> -7.2610281 | G43: =G26 -> 1.5 | H43: =H26-H27 -> 0.22598371 | I43: =I26-I27 -> 7.1389137 | J43: =J26-J27 -> 8.1464193 | K43: =K26-K27 -> 3.1977438 | L43: =L26-L27 -> -6.2224373 | M43: =M26-M27 -> 3.4854732 | N43: =N26-N27 -> -0.81914355
A44: =A28 -> University-led | C44: =C28-C29 -> 0 | E44: =E28 -> 9.6310083 | F44: =F28-F29 -> -9.6785415 | G44: =G28 -> 1.5 | H44: =H28-H29 -> 0.15844005 | I44: =I28-I29 -> 2.7604989 | J44: =J28-J29 -> 4.991923 | K44: =K28-K29 -> 15.692473 | L44: =L28-L29 -> -3.1136095 | M44: =M28-M29 -> -0.72772856 | N44: =N28-N29 -> 1.1768628
A45: =A30 -> Cash preservation | C45: =C30-C31 -> 0 | E45: =E30 -> 10.270252 | F45: =F30-F31 -> -10.296736 | G45: =G30 -> 1.5 | H45: =H30-H31 -> 0.21230719 | I45: =I30-I31 -> 4.9582275 | J45: =J30-J31 -> 6.366078 | K45: =K30-K31 -> 1.6005368 | L45: =L30-L31 -> -11.257062 | M45: =M30-M31 -> 0.72798388 | N45: =N30-N31 -> 0.52535728
A46: =A32 -> Adaptive (evidence-responsive) | C46: =C32-C33 -> 0 | E46: =E32 -> 8.6834162 | F46: =F32-F33 -> -8.7002324 | G46: =G32 -> 1.5 | H46: =H32-H33 -> 0.0960511 | I46: =I32-I33 -> 8.5402222 | J46: =J32-J33 -> 9.0160173 | K46: =K32-K33 -> 4.415793 | L46: =L32-L33 -> -6.2584285 | M46: =M32-M33 -> 6.1785067 | N46: =N32-N33 -> 1.6271742
A48: C · Financing: default debt-first policy vs refusing all financing
A49: Strategy | B49: Policy | C49: Q8 revenue | D49: Q8 cash | E49: Minimum cash | F49: Q8 debt | G49: Equity raised | H49: Ownership | I49: Price Q8 | J49: Terminal | K49: Ever insolvent | L49: Insolvent quarters | M49: Distressed quarters
A50: Consumer-led | B50: debt-first (default) | C50: 212.37071 | D50: 46.64691 | E50: 46.64691 | F50: 0 | G50: 0 | H50: 1 | I50: 116.21624 | J50: 68.063016 | K50: no | L50: 0 | M50: 0
A51: Consumer-led | B51: refuse all financing | C51: 212.37071 | D51: 46.64691 | E51: 46.64691 | F51: 0 | G51: 0 | H51: 1 | I51: 116.21624 | J51: 68.063016 | K51: no | L51: 0 | M51: 0
A52: Enterprise-led | B52: debt-first (default) | C52: 197.52408 | D52: 25 | E52: 25 | F52: 0.065865433 | G52: 0 | H52: 1 | I52: 81.785813 | J52: 58.631732 | K52: no | L52: 0 | M52: 0
A53: Enterprise-led | B53: refuse all financing | C53: 197.69156 | D53: 11.841351 | E53: 11.841351 | F53: 0 | G53: 0 | H53: 1 | I53: 64.418634 | J53: 57.588073 | K53: no | L53: 0 | M53: 1
A54: AI-led | B54: debt-first (default) | C54: 234.70009 | D54: 84.507569 | E54: 57.474249 | F54: 0 | G54: 0 | H54: 1 | I54: 148.51302 | J54: 80.49111 | K54: no | L54: 0 | M54: 0
A55: AI-led | B55: refuse all financing | C55: 234.70009 | D55: 84.507569 | E55: 57.474249 | F55: 0 | G55: 0 | H55: 1 | I55: 148.51302 | J55: 80.49111 | K55: no | L55: 0 | M55: 0
A56: Diversified | B56: debt-first (default) | C56: 226.21999 | D56: 76.420295 | E56: 57.118185 | F56: 0 | G56: 0 | H56: 1 | I56: 143.75331 | J56: 76.715858 | K56: no | L56: 0 | M56: 0
A57: Diversified | B57: refuse all financing | C57: 226.21999 | D57: 76.420295 | E57: 57.118185 | F57: 0 | G57: 0 | H57: 1 | I57: 143.75331 | J57: 76.715858 | K57: no | L57: 0 | M57: 0
A58: Consumer-only | B58: debt-first (default) | C58: 203.89316 | D58: 56.391335 | E58: 56.391335 | F58: 0 | G58: 0 | H58: 1 | I58: 109.88221 | J58: 61.803585 | K58: no | L58: 0 | M58: 0
A59: Consumer-only | B59: refuse all financing | C59: 203.89316 | D59: 56.391335 | E59: 56.391335 | F59: 0 | G59: 0 | H59: 1 | I59: 109.88221 | J59: 61.803585 | K59: no | L59: 0 | M59: 0
A60: Enterprise-only | B60: debt-first (default) | C60: 193.27843 | D60: 25 | E60: 25 | F60: 26.681658 | G60: 0 | H60: 1 | I60: 74.746025 | J60: 51.717494 | K60: no | L60: 0 | M60: 0
A61: Enterprise-only | B61: refuse all financing | C61: 193.20632 | D61: 13.367597 | E61: 6.3178677 | F61: 0 | G61: 0 | H61: 1 | I61: 69.635591 | J61: 53.64789 | K61: no | L61: 0 | M61: 2
... A71: All-in + contract | B71: refuse all financing | C71: 236.11062 | D71: 61.724635 | E71: 51.128748 | F71: 0 | G71: 0 | H71: 1 | I71: 153.9301 | J71: 78.316626 | K71: no | L71: 0 | M71: 0
A73: D · Q6 recession responses (forced)
A74: Hiring freeze is rejected by the engine whenever the quarter includes People investment. Deep reductions raise the share price for most strategies while lowering the terminal score.
A75: Strategy | B75: Response | C75: Feasible | D75: Q6 operating profit | E75: Q8 cash | F75: Q8 revenue | G75: Cum OP | H75: Price Q8 | I75: Terminal | J75: Culture Q8 | K75: Talent Q8 | L75: Q8 option | M75: Δ Price vs no action | N75: Δ Terminal vs no action
A76: Consumer-led | B76: no action | C76: yes | D76: 33.507525 | E76: 46.64691 | F76: 212.37071 | G76: 249.95285 | H76: 116.21624 | I76: 68.063016 | J76: 72 | K76: 100 | L76: scale-independently | M76: =H76-H76 -> 0 | N76: =I76-I76 -> 0
A77: Consumer-led | B77: hiring freeze | C77: no | D77: A hiring freeze cannot be combined with People investment in the same quarter
A78: Consumer-led | B78: targeted reduction (protect R&D) | C78: yes | D78: 38.544782 | E78: 54.751124 | F78: 211.69383 | G78: 264.5665 | H78: 119.47391 | I78: 67.508767 | J78: 63 | K78: 97.026612 | L78: scale-independently | M78: =H78-H76 -> 3.2576791 | N78: =I78-I76 -> -0.55424935
A79: Consumer-led | B79: deep reduction | C79: yes | D79: 49.129923 | E79: 81.854969 | F79: 209.50339 | G79: 294.57232 | H79: 124.41178 | I79: 63.507261 | J79: 52 | K79: 87.903025 | L79: continue | M79: =H79-H76 -> 8.1955484 | N79: =I79-I76 -> -4.5557548
A80: Consumer-led | B80: marketing 0.7 + freeze | C80: no | D80: A hiring freeze cannot be combined with People investment in the same quarter
A81: Consumer-led | B81: slow investment by $10M | C81: yes | D81: 33.486475 | E81: 56.815912 | F81: 212.20886 | G81: 250.14929 | H81: 116.13385 | I81: 68.371927 | J81: 72 | K81: 100 | L81: scale-independently | M81: =H81-H76 -> -0.082388097 | N81: =I81-I76 -> 0.30891089
A82: Enterprise-led | B82: no action | C82: yes | D82: 19.990706 | E82: 25 | F82: 199.27718 | G82: 186.14397 | H82: 79.51548 | I82: 60.555566 | J82: 72 | K82: 93.310084 | L82: continue | M82: =H82-H82 -> 0 | N82: =I82-I82 -> 0
A83: Enterprise-led | B83: hiring freeze | C83: no | D83: A hiring freeze cannot be combined with People investment in the same quarter
A84: Enterprise-led | B84: targeted reduction (protect R&D) | C84: yes | D84: 24.874495 | E84: 25 | F84: 197.63906 | G84: 199.72101 | H84: 81.887567 | I84: 58.720421 | J84: 63 | K84: 85.494981 | L84: continue | M84: =H84-H82 -> 2.3720873 | N84: =I84-I82 -> -1.8351447
A85: Enterprise-led | B85: deep reduction | C85: yes | D85: 35.506752 | E85: 27.522747 | F85: 195.99887 | G85: 230.09136 | H85: 89.927404 | I85: 56.845665 | J85: 52 | K85: 81.949541 | L85: continue | M85: =H85-H82 -> 10.411924 | N85: =I85-I82 -> -3.7099014
A86: Enterprise-led | B86: marketing 0.7 + freeze | C86: no | D86: A hiring freeze cannot be combined with People investment in the same quarter
A87: Enterprise-led | B87: slow investment by $10M | C87: yes | D87: 19.98627 | E87: 25 | F87: 199.24672 | G87: 186.55985 | H87: 80.263615 | I87: 60.690541 | J87: 72 | K87: 94.687299 | L87: continue | M87: =H87-H82 -> 0.74813537 | N87: =I87-I82 -> 0.1349748
A88: AI-led | B88: no action | C88: yes | D88: 38.654433 | E88: 84.507569 | F88: 234.70009 | G88: 277.75757 | H88: 148.51302 | I88: 80.49111 | J88: 67.705829 | K88: 99.075189 | L88: scale-independently | M88: =H88-H88 -> 0 | N88: =I88-I88 -> 0
A89: AI-led | B89: hiring freeze | C89: no | D89: A hiring freeze cannot be combined with People investment in the same quarter
A90: AI-led | B90: targeted reduction (protect R&D) | C90: yes | D90: 43.428226 | E90: 89.336369 | F90: 231.58962 | G90: 289.10619 | H90: 147.07467 | I90: 77.175015 | J90: 58.259931 | K90: 89.127812 | L90: scale-independently | M90: =H90-H88 -> -1.4383459 | N90: =I90-I88 -> -3.316095
A91: AI-led | B91: deep reduction | C91: yes | D91: 53.679858 | E91: 108.50098 | F91: 228.49462 | G91: 315.0352 | H91: 148.65107 | I91: 73.195654 | J91: 50.424898 | K91: 82.902553 | L91: continue | M91: =H91-H88 -> 0.13804866 | N91: =I91-I88 -> -7.2954555
A92: AI-led | B92: marketing 0.7 + freeze | C92: no | D92: A hiring freeze cannot be combined with People investment in the same quarter
A93: AI-led | B93: slow investment by $10M | C93: yes | D93: 38.605782 | E93: 95.137366 | F93: 234.24391 | G93: 278.38737 | H93: 148.05645 | I93: 80.69526 | J93: 67.684117 | K93: 97.094429 | L93: scale-independently | M93: =H93-H88 -> -0.45656749 | N93: =I93-I88 -> 0.20415069
A94: Diversified | B94: no action | C94: yes | D94: 35.460768 | E94: 70.746007 | F94: 226.41604 | G94: 267.33286 | H94: 142.63586 | I94: 76.702385 | J94: 70.97249 | K94: 55 | L94: scale-independently | M94: =H94-H94 -> 0 | N94: =I94-I94 -> 0
A95: Diversified | B95: hiring freeze | C95: yes | D95: 37.527177 | E95: 76.420295 | F95: 226.21999 | G95: 273.094 | H95: 143.75331 | I95: 76.715858 | J95: 69.451645 | K95: 53.5 | L95: scale-independently | M95: =H95-H94 -> 1.1174459 | N95: =I95-I94 -> 0.013472674
A96: Diversified | B96: targeted reduction (protect R&D) | C96: yes | D96: 40.181377 | E96: 86.225101 | F96: 223.83237 | G96: 279.30481 | H96: 142.5784 | I96: 70.208332 | J96: 61.841321 | K96: 47 | L96: continue | M96: =H96-H94 -> -0.057463171 | N96: =I96-I94 -> -6.4940537
A97: Diversified | B97: deep reduction | C97: yes | D97: 50.282219 | E97: 98.013057 | F97: 218.78748 | G97: 305.30406 | H97: 142.98602 | I97: 64.422259 | J97: 50.724899 | K97: 38 | L97: continue | M97: =H97-H94 -> 0.35015873 | N97: =I97-I94 -> -12.280126
A98: Diversified | B98: marketing 0.7 + freeze | C98: yes | D98: 38.230384 | E98: 76.389942 | F98: 222.58246 | G98: 273.06364 | H98: 141.43263 | I98: 76.108209 | J98: 69.451645 | K98: 53.5 | L98: scale-independently | M98: =H98-H94 -> -1.2032346 | N98: =I98-I94 -> -0.59417631
A99: Diversified | B99: slow investment by $10M | C99: yes | D99: 35.417844 | E99: 81.379471 | F99: 226.21141 | G99: 267.72928 | H99: 142.35772 | I99: 76.962212 | J99: 71.029379 | K99: 55 | L99: scale-independently | M99: =H99-H94 -> -0.2781454 | N99: =I99-I94 -> 0.25982612
A100: Consumer-only | B100: no action | C100: yes | D100: 33.917708 | E100: 50.866337 | F100: 203.89324 | G100: 251.55233 | H100: 108.3604 | I100: 61.686175 | J100: 72 | K100: 55 | L100: scale-independently | M100: =H100-H100 -> 0 | N100: =I100-I100 -> 0
A101: Consumer-only | B101: hiring freeze | C101: yes | D101: 35.791929 | E101: 56.391335 | F101: 203.89316 | G101: 257.07733 | H101: 109.88221 | I101: 61.803585 | J101: 70.5 | K101: 53.5 | L101: scale-independently | M101: =H101-H100 -> 1.521814 | N101: =I101-I100 -> 0.11741061
A102: Consumer-only | B102: targeted reduction (protect R&D) | C102: yes | D102: 39.001557 | E102: 66.795528 | F102: 203.45394 | G102: 266.48038 | H102: 111.87724 | I102: 56.746217 | J102: 63 | K102: 47 | L102: continue | M102: =H102-H100 -> 3.5168458 | N102: =I102-I100 -> -4.9399575
A103: Consumer-only | B103: deep reduction | C103: yes | D103: 49.539356 | E103: 82.670232 | F103: 201.44556 | G103: 296.52737 | H103: 117.58677 | I103: 54.333239 | J103: 52 | K103: 38 | L103: continue | M103: =H103-H100 -> 9.2263737 | N103: =I103-I100 -> -7.3529361
A104: Consumer-only | B104: marketing 0.7 + freeze | C104: yes | D104: 36.356979 | E104: 55.640165 | F104: 199.79677 | G104: 256.3169 | H104: 106.7732 | I104: 61.103276 | J104: 70.5 | K104: 53.5 | L104: scale-independently | M104: =H104-H100 -> -1.5871988 | N104: =I104-I100 -> -0.58289904
A105: Consumer-only | B105: slow investment by $10M | C105: yes | D105: 33.917708 | E105: 60.866337 | F105: 203.89324 | G105: 251.55233 | H105: 108.3604 | I105: 62.013497 | J105: 72 | K105: 55 | L105: scale-independently | M105: =H105-H100 -> 0 | N105: =I105-I100 -> 0.3273224
A106: Enterprise-only | B106: no action | C106: yes | D106: 18.594551 | E106: 25 | F106: 194.71355 | G106: 178.01066 | H106: 69.556451 | I106: 54.613853 | J106: 72 | K106: 55 | L106: continue | M106: =H106-H106 -> 0 | N106: =I106-I106 -> 0
A107: Enterprise-only | B107: hiring freeze | C107: yes | D107: 20.325961 | E107: 25 | F107: 194.7088 | G107: 183.30488 | H107: 71.7698 | I107: 54.729625 | J107: 70.5 | K107: 53.5 | L107: continue | M107: =H107-H106 -> 2.2133487 | N107: =I107-I106 -> 0.11577202
A108: Enterprise-only | B108: targeted reduction (protect R&D) | C108: yes | D108: 23.527496 | E108: 25 | F108: 193.28615 | G108: 191.64425 | H108: 72.52703 | I108: 51.602262 | J108: 63 | K108: 47 | L108: continue | M108: =H108-H106 -> 2.9705786 | N108: =I108-I106 -> -3.0115916
A109: Enterprise-only | B109: deep reduction | C109: yes | D109: 34.3038 | E109: 25.350737 | F109: 191.78882 | G109: 222.75853 | H109: 81.511757 | I109: 48.684713 | J109: 52 | K109: 38 | L109: continue | M109: =H109-H106 -> 11.955306 | N109: =I109-I106 -> -5.9291399
A110: Enterprise-only | B110: marketing 0.7 + freeze | C110: yes | D110: 21.11878 | E110: 25 | F110: 191.58202 | G110: 183.77905 | H110: 69.554427 | I110: 54.321953 | J110: 70.5 | K110: 53.5 | L110: continue | M110: =H110-H106 -> -0.0020241747 | N110: =I110-I106 -> -0.29189976
A111: Enterprise-only | B111: slow investment by $10M | C111: yes | D111: 18.583832 | E111: 25 | F111: 194.59253 | G111: 179.03316 | H111: 71.19968 | I111: 54.989762 | J111: 72 | K111: 55 | L111: continue | M111: =H111-H106 -> 1.6432285 | N111: =I111-I106 -> 0.37590837
A112: AI-only | B112: no action | C112: yes | D112: 33.478787 | E112: 54.083772 | F112: 220.98763 | G112: 252.04283 | H112: 125.77004 | I112: 69.129718 | J112: 72 | K112: 55 | L112: scale-independently | M112: =H112-H112 -> 0 | N112: =I112-I112 -> 0
A113: AI-only | B113: hiring freeze | C113: yes | D113: 35.665351 | E113: 60.269426 | F113: 220.94389 | G113: 258.24927 | H113: 127.25922 | I113: 69.260958 | J113: 70.5 | K113: 53.5 | L113: scale-independently | M113: =H113-H112 -> 1.4891806 | N113: =I113-I112 -> 0.13124013
A114: AI-only | B114: targeted reduction (protect R&D) | C114: yes | D114: 38.268072 | E114: 112.79792 | F114: 219.17269 | G114: 264.94525 | H114: 125.7232 | I114: 65.626466 | J114: 63 | K114: 47 | L114: raise-growth-capital | M114: =H114-H112 -> -0.046842532 | N114: =I114-I112 -> -3.5032517
A115: AI-only | B115: deep reduction | C115: yes | D115: 48.611112 | E115: 81.313845 | F115: 215.60334 | G115: 292.891 | H115: 130.90083 | I115: 60.072984 | J115: 52 | K115: 38 | L115: continue | M115: =H115-H112 -> 5.1307932 | N115: =I115-I112 -> -9.0567338
A116: AI-only | B116: marketing 0.7 + freeze | C116: yes | D116: 36.447699 | E116: 60.887252 | F116: 217.78603 | G116: 258.85832 | H116: 125.35096 | I116: 68.742699 | J116: 70.5 | K116: 53.5 | L116: scale-independently | M116: =H116-H112 -> -0.4190794 | N116: =I116-I112 -> -0.3870189
A117: AI-only | B117: slow investment by $10M | C117: yes | D117: 33.473671 | E117: 65.196763 | F117: 220.91925 | G117: 253.16189 | H117: 126.13029 | I117: 69.551865 | J117: 72 | K117: 55 | L117: scale-independently | M117: =H117-H112 -> 0.36025317 | N117: =I117-I112 -> 0.42214721
A118: University-led | B118: no action | C118: yes | D118: 25.996002 | E118: 32.512726 | F118: 198.16419 | G118: 214.01273 | H118: 110.90344 | I118: 63.653293 | J118: 72 | K118: 100 | L118: continue | M118: =H118-H118 -> 0 | N118: =I118-I118 -> 0
A119: University-led | B119: hiring freeze | C119: no | D119: A hiring freeze cannot be combined with People investment in the same quarter
A120: University-led | B120: targeted reduction (protect R&D) | C120: yes | D120: 30.963738 | E120: 30.048732 | F120: 197.09373 | G120: 228.04292 | H120: 111.60197 | I120: 65.345611 | J120: 63 | K120: 97.933931 | L120: scale-independently | M120: =H120-H118 -> 0.69852971 | N120: =I120-I118 -> 1.6923175
A121: University-led | B121: deep reduction | C121: yes | D121: 41.611909 | E121: 56.898171 | F121: 195.43677 | G121: 258.60232 | H121: 126.90418 | I121: 61.835535 | J121: 52 | K121: 88.850797 | L121: continue | M121: =H121-H118 -> 16.000741 | N121: =I121-I118 -> -1.8177585
...

Sheet Recommendations
A1: 7 · Findings and recommendations
A2: Answers draw on sheets 1–6. Package metrics are formulas over the Proposal tests appendix; grid metrics are recorded engine results.
A4: A · Answers
A5: Is Consumer investment disproportionately rewarded? | B5: Against Enterprise and University, yes; against AI/Product, no. $10M a quarter adds, by Q8: Consumer +$8.3M revenue, +$20M cumulative OP and +$10.9 a share; Enterprise +$2.0M, −$7.4M and +$3.1; University +$3.6M, +$6.7M and +$11.5 (price via strategic readiness, with almost no revenue); AI/Product +$25.0M, +$44.9M and +$30.3. Consumer’s advantage over Enterprise comes from defending the 70% Consumer base, which the AI disruption erodes by $11–19M by Q8 when neither Consumer nor People is funded (Enterprise-only −$19M, AI-only −$13M, Cash preservation −$11M), with no recurring cost commitment and fast maturation.
A6: Does a Consumer-only strategy outperform most alternatives? | B6: No. It ranks 7th of 10 on Q8 share price ($109.9) and 8th on the terminal score (61.8), and sits at the 27th percentile of 462 allocations on price (13th on score). It ranks 6th–7th in all ten market scenarios; it is 2nd–3rd in Q1–Q2, within $1 of the leader, and falls back from Q3. Consumer is valuable as a complement: Consumer + AI ($15M each) is the single best constant strategy ($164.5, 99th percentile).
A7: Are Enterprise, University and AI commercially viable strategic choices? | B7: AI: yes; it is the dominant and effectively mandatory investment. Every destination’s best allocation includes $10M AI, and the best allocation without AI is $116–133 against $156–166 with it. Enterprise: not as a lead investment. Enterprise capability reaches the 120 ceiling, yet win rate moves only 25% → 29% and Enterprise revenue only $40M → $46M (or $52M with the contract). Enterprise-only is last in every scenario, and each $5M of Enterprise lowers the average outcome. It works only paired with AI ($148). University: viable for share price ($111) and score but not commercially. University revenue stays at about $16M through Q8 even with Credential at 120, because wins are recognized from Q+2 to Q+5 and the $40M University market is small. Every destination is reachable at a similar best ($156–166), but only with AI.
A8: Does the starting revenue mix create the imbalance, or do the investment-return formulas? | B8: Mostly the formulas, with the mix amplifying Consumer over Enterprise. Under valid re-based mixes (AI reward held fixed), AI/Product remains the top-return bucket in every mix, and Enterprise’s return stays weak (cumulative OP still negative at Q8): formula effects. Consumer’s return falls as its base shrinks (+$20M → +$13M → +$10M cumulative OP), and Enterprise-only rises from $75 to $96–112 as less revenue is exposed to the consumer disruption: a mix effect. The engine does not support changing the mix on its own; the nine constants and the cost pool on the Starting revenue distribution sheet must change with it.
A9: What is the smallest set of economic changes needed for credible strategic trade-offs? | B9: Five calibration changes, all of which preserve the starting company exactly (package PR, below): (1) AI adoption reward above baseline $0.08M → $0.05M per point; (2) Enterprise conversion: win rate per point of relative capability 0.08 → 0.30 and pipeline inflow amplitude 1.2 → 3.0; (3) Enterprise bookings go live 50/50% over two quarters instead of 25/50/25% over three; (4) Enterprise delivery commitment 4% → 2%; (5) University pipeline: inflow amplitude 0.8 → 4.0 and resolution 0.2 → 0.4. Effects in the authored market: the lead-family price range narrows from $82–149 to $114–135. Enterprise-led moves from 9th to 5th, and AI-only falls from the 49th to the 17th percentile. Enterprise’s share of the top-5% allocations rises from $1.0M to $4.6M. Two issues remain: AI is still part of every winning allocation (a design choice, given the AI-disruption theme), and University revenue still does not grow within eight quarters, which needs a structural change (a larger University market or Credential in the win rate), not calibration.
A10: How should contract costs, recession actions and financing interact with the investment budget? | B10: Make each one a claim on the same capital decision, as set out in section C. The contract’s upfront cost should come out of that quarter’s strategic envelope. The recession response should be an explicit, always-feasible choice. Financing raised in a quarter should be able to expand that quarter’s envelope within debt, dilution, cash-floor and absorption limits, so long-payback strategies (Enterprise, University) have a funding path that costs something.
A12: B · Candidate calibration changes (tested in memory; not implemented)
A13: Change | B13: Constant | C13: Current | D13: Tested | E13: Rationale
A14: Moderate the AI adoption reward | B14: revenue.aiNative.monetizationPerPointAbove | C14: 0.08 | D14: 0.05 | E14: AI-native new monetization above the starting adoption level: $0.08M → $0.05M per adoption point per quarter. AI-native revenue currently compounds by $6–8M a quarter once adoption passes ~70, the largest growth flow in the model.
A15: Enterprise capability converts to bookings | B15: commercial.enterprise.winPerRelCapability | C15: 0.08 | D15: 0.3 | E15: Enterprise win rate per point of relative capability 0.08 → 0.30 and pipeline inflow amplitude 1.2 → 3.0. Enterprise capability 30 → 120 currently lifts the win rate ~4 points and Enterprise revenue only $40M → $46M by Q8.
B16: commercial.enterprise.inflowCapabilityAmplitude | C16: 1.2 | D16: 3
A17: Enterprise bookings go live faster | B17: revenue.enterprise.recognition | C17: [[1, 0.25], [2, 0.5], [3, 0.25]] | D17: [[1, 0.5], [2, 0.5]] | E17: Recognition 25/50/25% over Q+1..Q+3 → 50/50% over Q+1..Q+2.
A18: Lower Enterprise run-cost commitment | B18: costs.commitments.enterprise.perDollar | C18: 0.04 | D18: 0.02 | E18: Delivery/CS commitment 4% → 2% of investment per quarter for 6 quarters.
A19: University pipeline responds to Credential | B19: commercial.university.inflowCapabilityAmplitude | C19: 0.8 | D19: 4 | E19: University pipeline inflow amplitude 0.8 → 4.0 and resolution 0.2 → 0.4. Credential 40 → 120 currently grows the pipeline 24 → 42 and University revenue not at all within eight quarters.
B20: commercial.university.resolutionRate | C20: 0.2 | D20: 0.4
A21: University wins go live sooner | B21: revenue.university.recognition | C21: [[2, 0.1], [3, 0.3], [4, 0.3], [5, 0.3]] | D21: [[1, 0.3], [2, 0.4], [3, 0.3]] | E21: Recognition 10/30/30/30% over Q+2..Q+5 → 30/40/30% over Q+1..Q+3.
A23: C · Packages compared (formulas over the Proposal tests appendix)
A24: Lead family = Consumer-led, Enterprise-led, AI-led, University-led ($20M lead + $10M People).
A25: Package | B25: Contents | C25: Scenario | D25: Lead-family min price | E25: Lead-family max price | F25: Lead-family spread | G25: Enterprise-led price | H25: University-led price | I25: Consumer-only price | J25: AI-only price | K25: Best price (any) | L25: Lowest price (any)
A26: P0 | B26: Current calibration | C26: authored | D26: =MIN(SUMIFS('Proposal tests'!$K$5:$K$784,'Proposal tests'!$A$5:$A$784,$A26,'Proposal tests'!$B$5:$B$784,$C26,'Proposal tests'!$C$5:$C$784,"Consumer-led"),SUMIFS('Proposal tests'!$K$5:$K$784,'Proposal tests'!$A$5:$A$784,$A26,'Proposal tests'!$B$5:$B$784,$C26,'Proposal tests'!$C$5:$C$784,"Enterprise-led"),SUMIFS('Proposal tests'!$K$5:$K$784,'Proposal tests'!$A$5:$A$784,$A26,'Proposal tests'!$B$5:$B$784,$C26,'Proposal tests'!$C$5:$C$784,"AI-led"),SUMIFS('Proposal tests'!$K$5:$K$784,'Proposal tests'!$A$5:$A$784,$A26,'Proposal tests'!$B$5:$B$784,$C26,'Proposal tests'!$C$5:$C$784,"University-led")) -> 81.785813 | E26: =MAX(SUMIFS('Proposal tests'!$K$5:$K$784,'Proposal tests'!$A$5:$A$784,$A26,'Proposal tests'!$B$5:$B$784,$C26,'Proposal tests'!$C$5:$C$784,"Consumer-led"),SUMIFS('Proposal tests'!$K$5:$K$784,'Proposal tests'!$A$5:$A$784,$A26,'Proposal tests'!$B$5:$B$784,$C26,'Proposal tests'!$C$5:$C$784,"Enterprise-led"),SUMIFS('Proposal tests'!$K$5:$K$784,'Proposal tests'!$A$5:$A$784,$A26,'Proposal tests'!$B$5:$B$784,$C26,'Proposal tests'!$C$5:$C$784,"AI-led"),SUMIFS('Proposal tests'!$K$5:$K$784,'Proposal tests'!$A$5:$A$784,$A26,'Proposal tests'!$B$5:$B$784,$C26,'Proposal tests'!$C$5:$C$784,"University-led")) -> 148.51302 | F26: =E26-D26 -> 66.727206 | G26: =SUMIFS('Proposal tests'!$K$5:$K$784,'Proposal tests'!$A$5:$A$784,$A26,'Proposal tests'!$B$5:$B$784,$C26,'Proposal tests'!$C$5:$C$784,"Enterprise-led") -> 81.785813 | H26: =SUMIFS('Proposal tests'!$K$5:$K$784,'Proposal tests'!$A$5:$A$784,$A26,'Proposal tests'!$B$5:$B$784,$C26,'Proposal tests'!$C$5:$C$784,"University-led") -> 110.90344 | I26: =SUMIFS('Proposal tests'!$K$5:$K$784,'Proposal tests'!$A$5:$A$784,$A26,'Proposal tests'!$B$5:$B$784,$C26,'Proposal tests'!$C$5:$C$784,"Consumer-only") -> 109.88221 | J26: =SUMIFS('Proposal tests'!$K$5:$K$784,'Proposal tests'!$A$5:$A$784,$A26,'Proposal tests'!$B$5:$B$784,$C26,'Proposal tests'!$C$5:$C$784,"AI-only") -> 127.25922 | K26: =_xlfn.MAXIFS('Proposal tests'!$K$5:$K$784,'Proposal tests'!$A$5:$A$784,$A26,'Proposal tests'!$B$5:$B$784,$C26) -> 148.82113 | L26: =_xlfn.MINIFS('Proposal tests'!$K$5:$K$784,'Proposal tests'!$A$5:$A$784,$A26,'Proposal tests'!$B$5:$B$784,$C26) -> 74.746025
A27: P0 | B27: Current calibration | C27: consumer-weak | D27: =MIN(SUMIFS('Proposal tests'!$K$5:$K$784,'Proposal tests'!$A$5:$A$784,$A27,'Proposal tests'!$B$5:$B$784,$C27,'Proposal tests'!$C$5:$C$784,"Consumer-led"),SUMIFS('Proposal tests'!$K$5:$K$784,'Proposal tests'!$A$5:$A$784,$A27,'Proposal tests'!$B$5:$B$784,$C27,'Proposal tests'!$C$5:$C$784,"Enterprise-led"),SUMIFS('Proposal tests'!$K$5:$K$784,'Proposal tests'!$A$5:$A$784,$A27,'Proposal tests'!$B$5:$B$784,$C27,'Proposal tests'!$C$5:$C$784,"AI-led"),SUMIFS('Proposal tests'!$K$5:$K$784,'Proposal tests'!$A$5:$A$784,$A27,'Proposal tests'!$B$5:$B$784,$C27,'Proposal tests'!$C$5:$C$784,"University-led")) -> 71.575302 | E27: =MAX(SUMIFS('Proposal tests'!$K$5:$K$784,'Proposal tests'!$A$5:$A$784,$A27,'Proposal tests'!$B$5:$B$784,$C27,'Proposal tests'!$C$5:$C$784,"Consumer-led"),SUMIFS('Proposal tests'!$K$5:$K$784,'Proposal tests'!$A$5:$A$784,$A27,'Proposal tests'!$B$5:$B$784,$C27,'Proposal tests'!$C$5:$C$784,"Enterprise-led"),SUMIFS('Proposal tests'!$K$5:$K$784,'Proposal tests'!$A$5:$A$784,$A27,'Proposal tests'!$B$5:$B$784,$C27,'Proposal tests'!$C$5:$C$784,"AI-led"),SUMIFS('Proposal tests'!$K$5:$K$784,'Proposal tests'!$A$5:$A$784,$A27,'Proposal tests'!$B$5:$B$784,$C27,'Proposal tests'!$C$5:$C$784,"University-led")) -> 142.52239 | F27: =E27-D27 -> 70.947089 | G27: =SUMIFS('Proposal tests'!$K$5:$K$784,'Proposal tests'!$A$5:$A$784,$A27,'Proposal tests'!$B$5:$B$784,$C27,'Proposal tests'!$C$5:$C$784,"Enterprise-led") -> 71.575302 | H27: =SUMIFS('Proposal tests'!$K$5:$K$784,'Proposal tests'!$A$5:$A$784,$A27,'Proposal tests'!$B$5:$B$784,$C27,'Proposal tests'!$C$5:$C$784,"University-led") -> 94.970782 | I27: =SUMIFS('Proposal tests'!$K$5:$K$784,'Proposal tests'!$A$5:$A$784,$A27,'Proposal tests'!$B$5:$B$784,$C27,'Proposal tests'!$C$5:$C$784,"Consumer-only") -> 95.558665 | J27: =SUMIFS('Proposal tests'!$K$5:$K$784,'Proposal tests'!$A$5:$A$784,$A27,'Proposal tests'!$B$5:$B$784,$C27,'Proposal tests'!$C$5:$C$784,"AI-only") -> 120.91943 | K27: =_xlfn.MAXIFS('Proposal tests'!$K$5:$K$784,'Proposal tests'!$A$5:$A$784,$A27,'Proposal tests'!$B$5:$B$784,$C27) -> 142.52239 | L27: =_xlfn.MINIFS('Proposal tests'!$K$5:$K$784,'Proposal tests'!$A$5:$A$784,$A27,'Proposal tests'!$B$5:$B$784,$C27) -> 63.717205
A28: P0 | B28: Current calibration | C28: enterprise-boom | D28: =MIN(SUMIFS('Proposal tests'!$K$5:$K$784,'Proposal tests'!$A$5:$A$784,$A28,'Proposal tests'!$B$5:$B$784,$C28,'Proposal tests'!$C$5:$C$784,"Consumer-led"),SUMIFS('Proposal tests'!$K$5:$K$784,'Proposal tests'!$A$5:$A$784,$A28,'Proposal tests'!$B$5:$B$784,$C28,'Proposal tests'!$C$5:$C$784,"Enterprise-led"),SUMIFS('Proposal tests'!$K$5:$K$784,'Proposal tests'!$A$5:$A$784,$A28,'Proposal tests'!$B$5:$B$784,$C28,'Proposal tests'!$C$5:$C$784,"AI-led"),SUMIFS('Proposal tests'!$K$5:$K$784,'Proposal tests'!$A$5:$A$784,$A28,'Proposal tests'!$B$5:$B$784,$C28,'Proposal tests'!$C$5:$C$784,"University-led")) -> 84.932614 | E28: =MAX(SUMIFS('Proposal tests'!$K$5:$K$784,'Proposal tests'!$A$5:$A$784,$A28,'Proposal tests'!$B$5:$B$784,$C28,'Proposal tests'!$C$5:$C$784,"Consumer-led"),SUMIFS('Proposal tests'!$K$5:$K$784,'Proposal tests'!$A$5:$A$784,$A28,'Proposal tests'!$B$5:$B$784,$C28,'Proposal tests'!$C$5:$C$784,"Enterprise-led"),SUMIFS('Proposal tests'!$K$5:$K$784,'Proposal tests'!$A$5:$A$784,$A28,'Proposal tests'!$B$5:$B$784,$C28,'Proposal tests'!$C$5:$C$784,"AI-led"),SUMIFS('Proposal tests'!$K$5:$K$784,'Proposal tests'!$A$5:$A$784,$A28,'Proposal tests'!$B$5:$B$784,$C28,'Proposal tests'!$C$5:$C$784,"University-led")) -> 150.24852 | F28: =E28-D28 -> 65.315906 | G28: =SUMIFS('Proposal tests'!$K$5:$K$784,'Proposal tests'!$A$5:$A$784,$A28,'Proposal tests'!$B$5:$B$784,$C28,'Proposal tests'!$C$5:$C$784,"Enterprise-led") -> 84.932614 | H28: =SUMIFS('Proposal tests'!$K$5:$K$784,'Proposal tests'!$A$5:$A$784,$A28,'Proposal tests'!$B$5:$B$784,$C28,'Proposal tests'!$C$5:$C$784,"University-led") -> 113.98221 | I28: =SUMIFS('Proposal tests'!$K$5:$K$784,'Proposal tests'!$A$5:$A$784,$A28,'Proposal tests'!$B$5:$B$784,$C28,'Proposal tests'!$C$5:$C$784,"Consumer-only") -> 111.38572 | J28: =SUMIFS('Proposal tests'!$K$5:$K$784,'Proposal tests'!$A$5:$A$784,$A28,'Proposal tests'!$B$5:$B$784,$C28,'Proposal tests'!$C$5:$C$784,"AI-only") -> 129.00572 | K28: =_xlfn.MAXIFS('Proposal tests'!$K$5:$K$784,'Proposal tests'!$A$5:$A$784,$A28,'Proposal tests'!$B$5:$B$784,$C28) -> 151.31999 | L28: =_xlfn.MINIFS('Proposal tests'!$K$5:$K$784,'Proposal tests'!$A$5:$A$784,$A28,'Proposal tests'!$B$5:$B$784,$C28) -> 78.423017
A29: P0 | B29: Current calibration | C29: ai-boom | D29: =MIN(SUMIFS('Proposal tests'!$K$5:$K$784,'Proposal tests'!$A$5:$A$784,$A29,'Proposal tests'!$B$5:$B$784,$C29,'Proposal tests'!$C$5:$C$784,"Consumer-led"),SUMIFS('Proposal tests'!$K$5:$K$784,'Proposal tests'!$A$5:$A$784,$A29,'Proposal tests'!$B$5:$B$784,$C29,'Proposal tests'!$C$5:$C$784,"Enterprise-led"),SUMIFS('Proposal tests'!$K$5:$K$784,'Proposal tests'!$A$5:$A$784,$A29,'Proposal tests'!$B$5:$B$784,$C29,'Proposal tests'!$C$5:$C$784,"AI-led"),SUMIFS('Proposal tests'!$K$5:$K$784,'Proposal tests'!$A$5:$A$784,$A29,'Proposal tests'!$B$5:$B$784,$C29,'Proposal tests'!$C$5:$C$784,"University-led")) -> 82.796971 | E29: =MAX(SUMIFS('Proposal tests'!$K$5:$K$784,'Proposal tests'!$A$5:$A$784,$A29,'Proposal tests'!$B$5:$B$784,$C29,'Proposal tests'!$C$5:$C$784,"Consumer-led"),SUMIFS('Proposal tests'!$K$5:$K$784,'Proposal tests'!$A$5:$A$784,$A29,'Proposal tests'!$B$5:$B$784,$C29,'Proposal tests'!$C$5:$C$784,"Enterprise-led"),SUMIFS('Proposal tests'!$K$5:$K$784,'Proposal tests'!$A$5:$A$784,$A29,'Proposal tests'!$B$5:$B$784,$C29,'Proposal tests'!$C$5:$C$784,"AI-led"),SUMIFS('Proposal tests'!$K$5:$K$784,'Proposal tests'!$A$5:$A$784,$A29,'Proposal tests'!$B$5:$B$784,$C29,'Proposal tests'!$C$5:$C$784,"University-led")) -> 164.08849 | F29: =E29-D29 -> 81.291516 | G29: =SUMIFS('Proposal tests'!$K$5:$K$784,'Proposal tests'!$A$5:$A$784,$A29,'Proposal tests'!$B$5:$B$784,$C29,'Proposal tests'!$C$5:$C$784,"Enterprise-led") -> 82.796971 | H29: =SUMIFS('Proposal tests'!$K$5:$K$784,'Proposal tests'!$A$5:$A$784,$A29,'Proposal tests'!$B$5:$B$784,$C29,'Proposal tests'!$C$5:$C$784,"University-led") -> 106.40892 | I29: =SUMIFS('Proposal tests'!$K$5:$K$784,'Proposal tests'!$A$5:$A$784,$A29,'Proposal tests'!$B$5:$B$784,$C29,'Proposal tests'!$C$5:$C$784,"Consumer-only") -> 110.74617 | J29: =SUMIFS('Proposal tests'!$K$5:$K$784,'Proposal tests'!$A$5:$A$784,$A29,'Proposal tests'!$B$5:$B$784,$C29,'Proposal tests'!$C$5:$C$784,"AI-only") -> 144.50163 | K29: =_xlfn.MAXIFS('Proposal tests'!$K$5:$K$784,'Proposal tests'!$A$5:$A$784,$A29,'Proposal tests'!$B$5:$B$784,$C29) -> 164.08849 | L29: =_xlfn.MINIFS('Proposal tests'!$K$5:$K$784,'Proposal tests'!$A$5:$A$784,$A29,'Proposal tests'!$B$5:$B$784,$C29) -> 76.165661
A30: P0 | B30: Current calibration | C30: no-disruption | D30: =MIN(SUMIFS('Proposal tests'!$K$5:$K$784,'Proposal tests'!$A$5:$A$784,$A30,'Proposal tests'!$B$5:$B$784,$C30,'Proposal tests'!$C$5:$C$784,"Consumer-led"),SUMIFS('Proposal tests'!$K$5:$K$784,'Proposal tests'!$A$5:$A$784,$A30,'Proposal tests'!$B$5:$B$784,$C30,'Proposal tests'!$C$5:$C$784,"Enterprise-led"),SUMIFS('Proposal tests'!$K$5:$K$784,'Proposal tests'!$A$5:$A$784,$A30,'Proposal tests'!$B$5:$B$784,$C30,'Proposal tests'!$C$5:$C$784,"AI-led"),SUMIFS('Proposal tests'!$K$5:$K$784,'Proposal tests'!$A$5:$A$784,$A30,'Proposal tests'!$B$5:$B$784,$C30,'Proposal tests'!$C$5:$C$784,"University-led")) -> 111.09206 | E30: =MAX(SUMIFS('Proposal tests'!$K$5:$K$784,'Proposal tests'!$A$5:$A$784,$A30,'Proposal tests'!$B$5:$B$784,$C30,'Proposal tests'!$C$5:$C$784,"Consumer-led"),SUMIFS('Proposal tests'!$K$5:$K$784,'Proposal tests'!$A$5:$A$784,$A30,'Proposal tests'!$B$5:$B$784,$C30,'Proposal tests'!$C$5:$C$784,"Enterprise-led"),SUMIFS('Proposal tests'!$K$5:$K$784,'Proposal tests'!$A$5:$A$784,$A30,'Proposal tests'!$B$5:$B$784,$C30,'Proposal tests'!$C$5:$C$784,"AI-led"),SUMIFS('Proposal tests'!$K$5:$K$784,'Proposal tests'!$A$5:$A$784,$A30,'Proposal tests'!$B$5:$B$784,$C30,'Proposal tests'!$C$5:$C$784,"University-led")) -> 142.05412 | F30: =E30-D30 -> 30.962062 | G30: =SUMIFS('Proposal tests'!$K$5:$K$784,'Proposal tests'!$A$5:$A$784,$A30,'Proposal tests'!$B$5:$B$784,$C30,'Proposal tests'!$C$5:$C$784,"Enterprise-led") -> 111.09206 | H30: =SUMIFS('Proposal tests'!$K$5:$K$784,'Proposal tests'!$A$5:$A$784,$A30,'Proposal tests'!$B$5:$B$784,$C30,'Proposal tests'!$C$5:$C$784,"University-led") -> 131.20383 | I30: =SUMIFS('Proposal tests'!$K$5:$K$784,'Proposal tests'!$A$5:$A$784,$A30,'Proposal tests'!$B$5:$B$784,$C30,'Proposal tests'!$C$5:$C$784,"Consumer-only") -> 125.95702 | J30: =SUMIFS('Proposal tests'!$K$5:$K$784,'Proposal tests'!$A$5:$A$784,$A30,'Proposal tests'!$B$5:$B$784,$C30,'Proposal tests'!$C$5:$C$784,"AI-only") -> 120.47805 | K30: =_xlfn.MAXIFS('Proposal tests'!$K$5:$K$784,'Proposal tests'!$A$5:$A$784,$A30,'Proposal tests'!$B$5:$B$784,$C30) -> 149.55691 | L30: =_xlfn.MINIFS('Proposal tests'!$K$5:$K$784,'Proposal tests'!$A$5:$A$784,$A30,'Proposal tests'!$B$5:$B$784,$C30) -> 96.14365
A31: P0 | B31: Current calibration | C31: severe-recession | D31: =MIN(SUMIFS('Proposal tests'!$K$5:$K$784,'Proposal tests'!$A$5:$A$784,$A31,'Proposal tests'!$B$5:$B$784,$C31,'Proposal tests'!$C$5:$C$784,"Consumer-led"),SUMIFS('Proposal tests'!$K$5:$K$784,'Proposal tests'!$A$5:$A$784,$A31,'Proposal tests'!$B$5:$B$784,$C31,'Proposal tests'!$C$5:$C$784,"Enterprise-led"),SUMIFS('Proposal tests'!$K$5:$K$784,'Proposal tests'!$A$5:$A$784,$A31,'Proposal tests'!$B$5:$B$784,$C31,'Proposal tests'!$C$5:$C$784,"AI-led"),SUMIFS('Proposal tests'!$K$5:$K$784,'Proposal tests'!$A$5:$A$784,$A31,'Proposal tests'!$B$5:$B$784,$C31,'Proposal tests'!$C$5:$C$784,"University-led")) -> 75.849984 | E31: =MAX(SUMIFS('Proposal tests'!$K$5:$K$784,'Proposal tests'!$A$5:$A$784,$A31,'Proposal tests'!$B$5:$B$784,$C31,'Proposal tests'!$C$5:$C$784,"Consumer-led"),SUMIFS('Proposal tests'!$K$5:$K$784,'Proposal tests'!$A$5:$A$784,$A31,'Proposal tests'!$B$5:$B$784,$C31,'Proposal tests'!$C$5:$C$784,"Enterprise-led"),SUMIFS('Proposal tests'!$K$5:$K$784,'Proposal tests'!$A$5:$A$784,$A31,'Proposal tests'!$B$5:$B$784,$C31,'Proposal tests'!$C$5:$C$784,"AI-led"),SUMIFS('Proposal tests'!$K$5:$K$784,'Proposal tests'!$A$5:$A$784,$A31,'Proposal tests'!$B$5:$B$784,$C31,'Proposal tests'!$C$5:$C$784,"University-led")) -> 140.91061 | F31: =E31-D31 -> 65.060624 | G31: =SUMIFS('Proposal tests'!$K$5:$K$784,'Proposal tests'!$A$5:$A$784,$A31,'Proposal tests'!$B$5:$B$784,$C31,'Proposal tests'!$C$5:$C$784,"Enterprise-led") -> 75.849984 | H31: =SUMIFS('Proposal tests'!$K$5:$K$784,'Proposal tests'!$A$5:$A$784,$A31,'Proposal tests'!$B$5:$B$784,$C31,'Proposal tests'!$C$5:$C$784,"University-led") -> 101.21317 | I31: =SUMIFS('Proposal tests'!$K$5:$K$784,'Proposal tests'!$A$5:$A$784,$A31,'Proposal tests'!$B$5:$B$784,$C31,'Proposal tests'!$C$5:$C$784,"Consumer-only") -> 104.12648 | J31: =SUMIFS('Proposal tests'!$K$5:$K$784,'Proposal tests'!$A$5:$A$784,$A31,'Proposal tests'!$B$5:$B$784,$C31,'Proposal tests'!$C$5:$C$784,"AI-only") -> 119.53931 | K31: =_xlfn.MAXIFS('Proposal tests'!$K$5:$K$784,'Proposal tests'!$A$5:$A$784,$A31,'Proposal tests'!$B$5:$B$784,$C31) -> 141.56956 | L31: =_xlfn.MINIFS('Proposal tests'!$K$5:$K$784,'Proposal tests'!$A$5:$A$784,$A31,'Proposal tests'!$B$5:$B$784,$C31) -> 68.474352
A32: P1 | B32: AI moderation only | C32: authored | D32: =MIN(SUMIFS('Proposal tests'!$K$5:$K$784,'Proposal tests'!$A$5:$A$784,$A32,'Proposal tests'!$B$5:$B$784,$C32,'Proposal tests'!$C$5:$C$784,"Consumer-led"),SUMIFS('Proposal tests'!$K$5:$K$784,'Proposal tests'!$A$5:$A$784,$A32,'Proposal tests'!$B$5:$B$784,$C32,'Proposal tests'!$C$5:$C$784,"Enterprise-led"),SUMIFS('Proposal tests'!$K$5:$K$784,'Proposal tests'!$A$5:$A$784,$A32,'Proposal tests'!$B$5:$B$784,$C32,'Proposal tests'!$C$5:$C$784,"AI-led"),SUMIFS('Proposal tests'!$K$5:$K$784,'Proposal tests'!$A$5:$A$784,$A32,'Proposal tests'!$B$5:$B$784,$C32,'Proposal tests'!$C$5:$C$784,"University-led")) -> 81.785813 | E32: =MAX(SUMIFS('Proposal tests'!$K$5:$K$784,'Proposal tests'!$A$5:$A$784,$A32,'Proposal tests'!$B$5:$B$784,$C32,'Proposal tests'!$C$5:$C$784,"Consumer-led"),SUMIFS('Proposal tests'!$K$5:$K$784,'Proposal tests'!$A$5:$A$784,$A32,'Proposal tests'!$B$5:$B$784,$C32,'Proposal tests'!$C$5:$C$784,"Enterprise-led"),SUMIFS('Proposal tests'!$K$5:$K$784,'Proposal tests'!$A$5:$A$784,$A32,'Proposal tests'!$B$5:$B$784,$C32,'Proposal tests'!$C$5:$C$784,"AI-led"),SUMIFS('Proposal tests'!$K$5:$K$784,'Proposal tests'!$A$5:$A$784,$A32,'Proposal tests'!$B$5:$B$784,$C32,'Proposal tests'!$C$5:$C$784,"University-led")) -> 137.28286 | F32: =E32-D32 -> 55.497048 | G32: =SUMIFS('Proposal tests'!$K$5:$K$784,'Proposal tests'!$A$5:$A$784,$A32,'Proposal tests'!$B$5:$B$784,$C32,'Proposal tests'!$C$5:$C$784,"Enterprise-led") -> 81.785813 | H32: =SUMIFS('Proposal tests'!$K$5:$K$784,'Proposal tests'!$A$5:$A$784,$A32,'Proposal tests'!$B$5:$B$784,$C32,'Proposal tests'!$C$5:$C$784,"University-led") -> 110.90344 | I32: =SUMIFS('Proposal tests'!$K$5:$K$784,'Proposal tests'!$A$5:$A$784,$A32,'Proposal tests'!$B$5:$B$784,$C32,'Proposal tests'!$C$5:$C$784,"Consumer-only") -> 109.88221 | J32: =SUMIFS('Proposal tests'!$K$5:$K$784,'Proposal tests'!$A$5:$A$784,$A32,'Proposal tests'!$B$5:$B$784,$C32,'Proposal tests'!$C$5:$C$784,"AI-only") -> 112.10632 | K32: =_xlfn.MAXIFS('Proposal tests'!$K$5:$K$784,'Proposal tests'!$A$5:$A$784,$A32,'Proposal tests'!$B$5:$B$784,$C32) -> 142.12558 | L32: =_xlfn.MINIFS('Proposal tests'!$K$5:$K$784,'Proposal tests'!$A$5:$A$784,$A32,'Proposal tests'!$B$5:$B$784,$C32) -> 74.746025
A33: P1 | B33: AI moderation only | C33: consumer-weak | D33: =MIN(SUMIFS('Proposal tests'!$K$5:$K$784,'Proposal tests'!$A$5:$A$784,$A33,'Proposal tests'!$B$5:$B$784,$C33,'Proposal tests'!$C$5:$C$784,"Consumer-led"),SUMIFS('Proposal tests'!$K$5:$K$784,'Proposal tests'!$A$5:$A$784,$A33,'Proposal tests'!$B$5:$B$784,$C33,'Proposal tests'!$C$5:$C$784,"Enterprise-led"),SUMIFS('Proposal tests'!$K$5:$K$784,'Proposal tests'!$A$5:$A$784,$A33,'Proposal tests'!$B$5:$B$784,$C33,'Proposal tests'!$C$5:$C$784,"AI-led"),SUMIFS('Proposal tests'!$K$5:$K$784,'Proposal tests'!$A$5:$A$784,$A33,'Proposal tests'!$B$5:$B$784,$C33,'Proposal tests'!$C$5:$C$784,"University-led")) -> 71.575302 | E33: =MAX(SUMIFS('Proposal tests'!$K$5:$K$784,'Proposal tests'!$A$5:$A$784,$A33,'Proposal tests'!$B$5:$B$784,$C33,'Proposal tests'!$C$5:$C$784,"Consumer-led"),SUMIFS('Proposal tests'!$K$5:$K$784,'Proposal tests'!$A$5:$A$784,$A33,'Proposal tests'!$B$5:$B$784,$C33,'Proposal tests'!$C$5:$C$784,"Enterprise-led"),SUMIFS('Proposal tests'!$K$5:$K$784,'Proposal tests'!$A$5:$A$784,$A33,'Proposal tests'!$B$5:$B$784,$C33,'Proposal tests'!$C$5:$C$784,"AI-led"),SUMIFS('Proposal tests'!$K$5:$K$784,'Proposal tests'!$A$5:$A$784,$A33,'Proposal tests'!$B$5:$B$784,$C33,'Proposal tests'!$C$5:$C$784,"University-led")) -> 130.97339 | F33: =E33-D33 -> 59.398088 | G33: =SUMIFS('Proposal tests'!$K$5:$K$784,'Proposal tests'!$A$5:$A$784,$A33,'Proposal tests'!$B$5:$B$784,$C33,'Proposal tests'!$C$5:$C$784,"Enterprise-led") -> 71.575302 | H33: =SUMIFS('Proposal tests'!$K$5:$K$784,'Proposal tests'!$A$5:$A$784,$A33,'Proposal tests'!$B$5:$B$784,$C33,'Proposal tests'!$C$5:$C$784,"University-led") -> 94.970782 | I33: =SUMIFS('Proposal tests'!$K$5:$K$784,'Proposal tests'!$A$5:$A$784,$A33,'Proposal tests'!$B$5:$B$784,$C33,'Proposal tests'!$C$5:$C$784,"Consumer-only") -> 95.558665 | J33: =SUMIFS('Proposal tests'!$K$5:$K$784,'Proposal tests'!$A$5:$A$784,$A33,'Proposal tests'!$B$5:$B$784,$C33,'Proposal tests'!$C$5:$C$784,"AI-only") -> 94.145988 | K33: =_xlfn.MAXIFS('Proposal tests'!$K$5:$K$784,'Proposal tests'!$A$5:$A$784,$A33,'Proposal tests'!$B$5:$B$784,$C33) -> 135.00571 | L33: =_xlfn.MINIFS('Proposal tests'!$K$5:$K$784,'Proposal tests'!$A$5:$A$784,$A33,'Proposal tests'!$B$5:$B$784,$C33) -> 63.717205
A34: P1 | B34: AI moderation only | C34: enterprise-boom | D34: =MIN(SUMIFS('Proposal tests'!$K$5:$K$784,'Proposal tests'!$A$5:$A$784,$A34,'Proposal tests'!$B$5:$B$784,$C34,'Proposal tests'!$C$5:$C$784,"Consumer-led"),SUMIFS('Proposal tests'!$K$5:$K$784,'Proposal tests'!$A$5:$A$784,$A34,'Proposal tests'!$B$5:$B$784,$C34,'Proposal tests'!$C$5:$C$784,"Enterprise-led"),SUMIFS('Proposal tests'!$K$5:$K$784,'Proposal tests'!$A$5:$A$784,$A34,'Proposal tests'!$B$5:$B$784,$C34,'Proposal tests'!$C$5:$C$784,"AI-led"),SUMIFS('Proposal tests'!$K$5:$K$784,'Proposal tests'!$A$5:$A$784,$A34,'Proposal tests'!$B$5:$B$784,$C34,'Proposal tests'!$C$5:$C$784,"University-led")) -> 84.932614 | E34: =MAX(SUMIFS('Proposal tests'!$K$5:$K$784,'Proposal tests'!$A$5:$A$784,$A34,'Proposal tests'!$B$5:$B$784,$C34,'Proposal tests'!$C$5:$C$784,"Consumer-led"),SUMIFS('Proposal tests'!$K$5:$K$784,'Proposal tests'!$A$5:$A$784,$A34,'Proposal tests'!$B$5:$B$784,$C34,'Proposal tests'!$C$5:$C$784,"Enterprise-led"),SUMIFS('Proposal tests'!$K$5:$K$784,'Proposal tests'!$A$5:$A$784,$A34,'Proposal tests'!$B$5:$B$784,$C34,'Proposal tests'!$C$5:$C$784,"AI-led"),SUMIFS('Proposal tests'!$K$5:$K$784,'Proposal tests'!$A$5:$A$784,$A34,'Proposal tests'!$B$5:$B$784,$C34,'Proposal tests'!$C$5:$C$784,"University-led")) -> 139.07296 | F34: =E34-D34 -> 54.140347 | G34: =SUMIFS('Proposal tests'!$K$5:$K$784,'Proposal tests'!$A$5:$A$784,$A34,'Proposal tests'!$B$5:$B$784,$C34,'Proposal tests'!$C$5:$C$784,"Enterprise-led") -> 84.932614 | H34: =SUMIFS('Proposal tests'!$K$5:$K$784,'Proposal tests'!$A$5:$A$784,$A34,'Proposal tests'!$B$5:$B$784,$C34,'Proposal tests'!$C$5:$C$784,"University-led") -> 113.98221 | I34: =SUMIFS('Proposal tests'!$K$5:$K$784,'Proposal tests'!$A$5:$A$784,$A34,'Proposal tests'!$B$5:$B$784,$C34,'Proposal tests'!$C$5:$C$784,"Consumer-only") -> 111.38572 | J34: =SUMIFS('Proposal tests'!$K$5:$K$784,'Proposal tests'!$A$5:$A$784,$A34,'Proposal tests'!$B$5:$B$784,$C34,'Proposal tests'!$C$5:$C$784,"AI-only") -> 115.23021 | K34: =_xlfn.MAXIFS('Proposal tests'!$K$5:$K$784,'Proposal tests'!$A$5:$A$784,$A34,'Proposal tests'!$B$5:$B$784,$C34) -> 144.66619 | L34: =_xlfn.MINIFS('Proposal tests'!$K$5:$K$784,'Proposal tests'!$A$5:$A$784,$A34,'Proposal tests'!$B$5:$B$784,$C34) -> 78.423017
A35: P1 | B35: AI moderation only | C35: ai-boom | D35: =MIN(SUMIFS('Proposal tests'!$K$5:$K$784,'Proposal tests'!$A$5:$A$784,$A35,'Proposal tests'!$B$5:$B$784,$C35,'Proposal tests'!$C$5:$C$784,"Consumer-led"),SUMIFS('Proposal tests'!$K$5:$K$784,'Proposal tests'!$A$5:$A$784,$A35,'Proposal tests'!$B$5:$B$784,$C35,'Proposal tests'!$C$5:$C$784,"Enterprise-led"),SUMIFS('Proposal tests'!$K$5:$K$784,'Proposal tests'!$A$5:$A$784,$A35,'Proposal tests'!$B$5:$B$784,$C35,'Proposal tests'!$C$5:$C$784,"AI-led"),SUMIFS('Proposal tests'!$K$5:$K$784,'Proposal tests'!$A$5:$A$784,$A35,'Proposal tests'!$B$5:$B$784,$C35,'Proposal tests'!$C$5:$C$784,"University-led")) -> 82.796971 | E35: =MAX(SUMIFS('Proposal tests'!$K$5:$K$784,'Proposal tests'!$A$5:$A$784,$A35,'Proposal tests'!$B$5:$B$784,$C35,'Proposal tests'!$C$5:$C$784,"Consumer-led"),SUMIFS('Proposal tests'!$K$5:$K$784,'Proposal tests'!$A$5:$A$784,$A35,'Proposal tests'!$B$5:$B$784,$C35,'Proposal tests'!$C$5:$C$784,"Enterprise-led"),SUMIFS('Proposal tests'!$K$5:$K$784,'Proposal tests'!$A$5:$A$784,$A35,'Proposal tests'!$B$5:$B$784,$C35,'Proposal tests'!$C$5:$C$784,"AI-led"),SUMIFS('Proposal tests'!$K$5:$K$784,'Proposal tests'!$A$5:$A$784,$A35,'Proposal tests'!$B$5:$B$784,$C35,'Proposal tests'!$C$5:$C$784,"University-led")) -> 149.50103 | F35: =E35-D35 -> 66.704055 | G35: =SUMIFS('Proposal tests'!$K$5:$K$784,'Proposal tests'!$A$5:$A$784,$A35,'Proposal tests'!$B$5:$B$784,$C35,'Proposal tests'!$C$5:$C$784,"Enterprise-led") -> 82.796971 | H35: =SUMIFS('Proposal tests'!$K$5:$K$784,'Proposal tests'!$A$5:$A$784,$A35,'Proposal tests'!$B$5:$B$784,$C35,'Proposal tests'!$C$5:$C$784,"University-led") -> 106.40892 | I35: =SUMIFS('Proposal tests'!$K$5:$K$784,'Proposal tests'!$A$5:$A$784,$A35,'Proposal tests'!$B$5:$B$784,$C35,'Proposal tests'!$C$5:$C$784,"Consumer-only") -> 110.74617 | J35: =SUMIFS('Proposal tests'!$K$5:$K$784,'Proposal tests'!$A$5:$A$784,$A35,'Proposal tests'!$B$5:$B$784,$C35,'Proposal tests'!$C$5:$C$784,"AI-only") -> 128.39697 | K35: =_xlfn.MAXIFS('Proposal tests'!$K$5:$K$784,'Proposal tests'!$A$5:$A$784,$A35,'Proposal tests'!$B$5:$B$784,$C35) -> 150.6914 | L35: =_xlfn.MINIFS('Proposal tests'!$K$5:$K$784,'Proposal tests'!$A$5:$A$784,$A35,'Proposal tests'!$B$5:$B$784,$C35) -> 76.165661
A36: P1 | B36: AI moderation only | C36: no-disruption | D36: =MIN(SUMIFS('Proposal tests'!$K$5:$K$784,'Proposal tests'!$A$5:$A$784,$A36,'Proposal tests'!$B$5:$B$784,$C36,'Proposal tests'!$C$5:$C$784,"Consumer-led"),SUMIFS('Proposal tests'!$K$5:$K$784,'Proposal tests'!$A$5:$A$784,$A36,'Proposal tests'!$B$5:$B$784,$C36,'Proposal tests'!$C$5:$C$784,"Enterprise-led"),SUMIFS('Proposal tests'!$K$5:$K$784,'Proposal tests'!$A$5:$A$784,$A36,'Proposal tests'!$B$5:$B$784,$C36,'Proposal tests'!$C$5:$C$784,"AI-led"),SUMIFS('Proposal tests'!$K$5:$K$784,'Proposal tests'!$A$5:$A$784,$A36,'Proposal tests'!$B$5:$B$784,$C36,'Proposal tests'!$C$5:$C$784,"University-led")) -> 111.07101 | E36: =MAX(SUMIFS('Proposal tests'!$K$5:$K$784,'Proposal tests'!$A$5:$A$784,$A36,'Proposal tests'!$B$5:$B$784,$C36,'Proposal tests'!$C$5:$C$784,"Consumer-led"),SUMIFS('Proposal tests'!$K$5:$K$784,'Proposal tests'!$A$5:$A$784,$A36,'Proposal tests'!$B$5:$B$784,$C36,'Proposal tests'!$C$5:$C$784,"Enterprise-led"),SUMIFS('Proposal tests'!$K$5:$K$784,'Proposal tests'!$A$5:$A$784,$A36,'Proposal tests'!$B$5:$B$784,$C36,'Proposal tests'!$C$5:$C$784,"AI-led"),SUMIFS('Proposal tests'!$K$5:$K$784,'Proposal tests'!$A$5:$A$784,$A36,'Proposal tests'!$B$5:$B$784,$C36,'Proposal tests'!$C$5:$C$784,"University-led")) -> 135.44066 | F36: =E36-D36 -> 24.36965 | G36: =SUMIFS('Proposal tests'!$K$5:$K$784,'Proposal tests'!$A$5:$A$784,$A36,'Proposal tests'!$B$5:$B$784,$C36,'Proposal tests'!$C$5:$C$784,"Enterprise-led") -> 111.07101 | H36: =SUMIFS('Proposal tests'!$K$5:$K$784,'Proposal tests'!$A$5:$A$784,$A36,'Proposal tests'!$B$5:$B$784,$C36,'Proposal tests'!$C$5:$C$784,"University-led") -> 131.20383 | I36: =SUMIFS('Proposal tests'!$K$5:$K$784,'Proposal tests'!$A$5:$A$784,$A36,'Proposal tests'!$B$5:$B$784,$C36,'Proposal tests'!$C$5:$C$784,"Consumer-only") -> 125.95702 | J36: =SUMIFS('Proposal tests'!$K$5:$K$784,'Proposal tests'!$A$5:$A$784,$A36,'Proposal tests'!$B$5:$B$784,$C36,'Proposal tests'!$C$5:$C$784,"AI-only") -> 108.8904 | K36: =_xlfn.MAXIFS('Proposal tests'!$K$5:$K$784,'Proposal tests'!$A$5:$A$784,$A36,'Proposal tests'!$B$5:$B$784,$C36) -> 145.91837 | L36: =_xlfn.MINIFS('Proposal tests'!$K$5:$K$784,'Proposal tests'!$A$5:$A$784,$A36,'Proposal tests'!$B$5:$B$784,$C36) -> 96.14365
A37: P1 | B37: AI moderation only | C37: severe-recession | D37: =MIN(SUMIFS('Proposal tests'!$K$5:$K$784,'Proposal tests'!$A$5:$A$784,$A37,'Proposal tests'!$B$5:$B$784,$C37,'Proposal tests'!$C$5:$C$784,"Consumer-led"),SUMIFS('Proposal tests'!$K$5:$K$784,'Proposal tests'!$A$5:$A$784,$A37,'Proposal tests'!$B$5:$B$784,$C37,'Proposal tests'!$C$5:$C$784,"Enterprise-led"),SUMIFS('Proposal tests'!$K$5:$K$784,'Proposal tests'!$A$5:$A$784,$A37,'Proposal tests'!$B$5:$B$784,$C37,'Proposal tests'!$C$5:$C$784,"AI-led"),SUMIFS('Proposal tests'!$K$5:$K$784,'Proposal tests'!$A$5:$A$784,$A37,'Proposal tests'!$B$5:$B$784,$C37,'Proposal tests'!$C$5:$C$784,"University-led")) -> 75.849984 | E37: =MAX(SUMIFS('Proposal tests'!$K$5:$K$784,'Proposal tests'!$A$5:$A$784,$A37,'Proposal tests'!$B$5:$B$784,$C37,'Proposal tests'!$C$5:$C$784,"Consumer-led"),SUMIFS('Proposal tests'!$K$5:$K$784,'Proposal tests'!$A$5:$A$784,$A37,'Proposal tests'!$B$5:$B$784,$C37,'Proposal tests'!$C$5:$C$784,"Enterprise-led"),SUMIFS('Proposal tests'!$K$5:$K$784,'Proposal tests'!$A$5:$A$784,$A37,'Proposal tests'!$B$5:$B$784,$C37,'Proposal tests'!$C$5:$C$784,"AI-led"),SUMIFS('Proposal tests'!$K$5:$K$784,'Proposal tests'!$A$5:$A$784,$A37,'Proposal tests'!$B$5:$B$784,$C37,'Proposal tests'!$C$5:$C$784,"University-led")) -> 130.20018 | F37: =E37-D37 -> 54.350193 | G37: =SUMIFS('Proposal tests'!$K$5:$K$784,'Proposal tests'!$A$5:$A$784,$A37,'Proposal tests'!$B$5:$B$784,$C37,'Proposal tests'!$C$5:$C$784,"Enterprise-led") -> 75.849984 | H37: =SUMIFS('Proposal tests'!$K$5:$K$784,'Proposal tests'!$A$5:$A$784,$A37,'Proposal tests'!$B$5:$B$784,$C37,'Proposal tests'!$C$5:$C$784,"University-led") -> 101.21317 | I37: =SUMIFS('Proposal tests'!$K$5:$K$784,'Proposal tests'!$A$5:$A$784,$A37,'Proposal tests'!$B$5:$B$784,$C37,'Proposal tests'!$C$5:$C$784,"Consumer-only") -> 104.12648 | J37: =SUMIFS('Proposal tests'!$K$5:$K$784,'Proposal tests'!$A$5:$A$784,$A37,'Proposal tests'!$B$5:$B$784,$C37,'Proposal tests'!$C$5:$C$784,"AI-only") -> 99.006818 | K37: =_xlfn.MAXIFS('Proposal tests'!$K$5:$K$784,'Proposal tests'!$A$5:$A$784,$A37,'Proposal tests'!$B$5:$B$784,$C37) -> 135.35242 | L37: =_xlfn.MINIFS('Proposal tests'!$K$5:$K$784,'Proposal tests'!$A$5:$A$784,$A37,'Proposal tests'!$B$5:$B$784,$C37) -> 68.474352
... A67: PR | B67: Recommended minimal set (P5 without University go-live, which adds nothing) | C67: severe-recession | D67: =MIN(SUMIFS('Proposal tests'!$K$5:$K$784,'Proposal tests'!$A$5:$A$784,$A67,'Proposal tests'!$B$5:$B$784,$C67,'Proposal tests'!$C$5:$C$784,"Consumer-led"),SUMIFS('Proposal tests'!$K$5:$K$784,'Proposal tests'!$A$5:$A$784,$A67,'Proposal tests'!$B$5:$B$784,$C67,'Proposal tests'!$C$5:$C$784,"Enterprise-led"),SUMIFS('Proposal tests'!$K$5:$K$784,'Proposal tests'!$A$5:$A$784,$A67,'Proposal tests'!$B$5:$B$784,$C67,'Proposal tests'!$C$5:$C$784,"AI-led"),SUMIFS('Proposal tests'!$K$5:$K$784,'Proposal tests'!$A$5:$A$784,$A67,'Proposal tests'!$B$5:$B$784,$C67,'Proposal tests'!$C$5:$C$784,"University-led")) -> 106.25563 | E67: =MAX(SUMIFS('Proposal tests'!$K$5:$K$784,'Proposal tests'!$A$5:$A$784,$A67,'Proposal tests'!$B$5:$B$784,$C67,'Proposal tests'!$C$5:$C$784,"Consumer-led"),SUMIFS('Proposal tests'!$K$5:$K$784,'Proposal tests'!$A$5:$A$784,$A67,'Proposal tests'!$B$5:$B$784,$C67,'Proposal tests'!$C$5:$C$784,"Enterprise-led"),SUMIFS('Proposal tests'!$K$5:$K$784,'Proposal tests'!$A$5:$A$784,$A67,'Proposal tests'!$B$5:$B$784,$C67,'Proposal tests'!$C$5:$C$784,"AI-led"),SUMIFS('Proposal tests'!$K$5:$K$784,'Proposal tests'!$A$5:$A$784,$A67,'Proposal tests'!$B$5:$B$784,$C67,'Proposal tests'!$C$5:$C$784,"University-led")) -> 127.94058 | F67: =E67-D67 -> 21.684945 | G67: =SUMIFS('Proposal tests'!$K$5:$K$784,'Proposal tests'!$A$5:$A$784,$A67,'Proposal tests'!$B$5:$B$784,$C67,'Proposal tests'!$C$5:$C$784,"Enterprise-led") -> 109.10573 | H67: =SUMIFS('Proposal tests'!$K$5:$K$784,'Proposal tests'!$A$5:$A$784,$A67,'Proposal tests'!$B$5:$B$784,$C67,'Proposal tests'!$C$5:$C$784,"University-led") -> 106.25563 | I67: =SUMIFS('Proposal tests'!$K$5:$K$784,'Proposal tests'!$A$5:$A$784,$A67,'Proposal tests'!$B$5:$B$784,$C67,'Proposal tests'!$C$5:$C$784,"Consumer-only") -> 101.84267 | J67: =SUMIFS('Proposal tests'!$K$5:$K$784,'Proposal tests'!$A$5:$A$784,$A67,'Proposal tests'!$B$5:$B$784,$C67,'Proposal tests'!$C$5:$C$784,"AI-only") -> 97.542887 | K67: =_xlfn.MAXIFS('Proposal tests'!$K$5:$K$784,'Proposal tests'!$A$5:$A$784,$A67,'Proposal tests'!$B$5:$B$784,$C67) -> 142.51976 | L67: =_xlfn.MINIFS('Proposal tests'!$K$5:$K$784,'Proposal tests'!$A$5:$A$784,$A67,'Proposal tests'!$B$5:$B$784,$C67) -> 95.328221
A69: D · Package effects on the full allocation grid (462 allocations × 5 destinations each; recorded results)
A70: Package | B70: Top-5% avg Consumer $M | C70: Top-5% avg Enterprise $M | D70: Top-5% avg AI $M | E70: Top-5% avg People $M | F70: Top-5% avg University $M | G70: Consumer-only pct | H70: Enterprise-only pct | I70: AI-only pct | J70: University-only pct | K70: Best price overall | L70: Spread of destination bests | M70: Best Enterprise AI
A71: P0 | B71: 10.208333 | C71: 1.0416667 | D71: 11.875 | E71: 3.5416667 | F71: 2.5 | G71: 0.26623377 | H71: 0.025974026 | I71: 0.49134199 | J71: 0.29004329 | K71: 166.47262 | L71: 10.43672 | M71: 158.68858
A72: P1 | B72: 10.208333 | C72: 1.25 | D72: 11.666667 | E72: 3.3333333 | F72: 2.7083333 | G72: 0.27705628 | H72: 0.025974026 | I72: 0.36796537 | J72: 0.3008658 | K72: 158.16192 | L72: 10.925378 | M72: 150.34628
A73: P2 | B73: 8.75 | C73: 3.9583333 | D73: 11.666667 | E73: 3.125 | F73: 2.0833333 | G73: 0.16450216 | H73: 0.093073593 | I73: 0.45238095 | J73: 0.16883117 | K73: 166.73233 | L73: 11.364117 | M73: 166.73233
A74: P3 | B74: 9.1666667 | C74: 3.9583333 | D74: 11.25 | E74: 2.5 | F74: 2.2916667 | G74: 0.17316017 | H74: 0.093073593 | I74: 0.23376623 | J74: 0.17748918 | K74: 158.60045 | L74: 11.461059 | M74: 158.60045
A75: P4 | B75: 8.3333333 | C75: 3.9583333 | D75: 10.625 | E75: 2.9166667 | F75: 3.9583333 | G75: 0.13636364 | H75: 0.13852814 | I75: 0.18398268 | J75: 0.32467532 | K75: 158.43807 | L75: 9.6056444 | M75: 157.47989
A76: P5 | B76: 7.9166667 | C76: 4.375 | D76: 10.625 | E76: 2.5 | F76: 4.375 | G76: 0.12770563 | H76: 0.15584416 | I76: 0.17316017 | J76: 0.30519481 | K76: 158.43807 | L76: 9.6056444 | M76: 158.34034
A77: PR | B77: 8.5416667 | C77: 4.5833333 | D77: 10.833333 | E77: 2.7083333 | F77: 2.7083333 | G77: 0.12987013 | H77: 0.15800866 | I77: 0.16666667 | J77: 0.25757576 | K77: 158.49486 | L77: 10.515191 | M77: 158.49486
A79: E · Proposed rules for contracts, recession and financing (documented only — not implemented)
